Workbook

Sheet Assumptions
A1: CIRCLES — KEY ASSUMPTIONS
B2: Assumption | C2: Year 1 | D2: Year 2 | E2: Year 3 | F2: Year 4 | G2: Year 5 | H2: Notes
B3: USER GROWTH
B4: Total Users (EOY) | C4: 20000 | D4: 75000 | E4: 250000 | F4: 750000 | G4: 2000000 | H4: Launch in 2 major cities Y1
B5: YoY User Growth % | C5: — | D5: =(D4-C4)/C4 -> 2.75 | E5: =(E4-D4)/D4 -> 2.3333333 | F5: =(F4-E4)/E4 -> 2 | G5: =(G4-F4)/F4 -> 1.6666667 | H5: Calculated from user targets
B6: Premium Conversion Rate | C6: 0.1 | D6: 0.12 | E6: 0.15 | F6: 0.18 | G6: 0.2 | H6: Improves with product maturity
B7: Premium Users | C7: =C4*C6 -> 2000 | D7: =D4*D6 -> 9000 | E7: =E4*E6 -> 37500 | F7: =F4*F6 -> 135000 | G7: =G4*G6 -> 400000 | H7: Users x Conversion Rate
B8: Annual Churn Rate (Premium) | C8: 0.05 | D8: 0.05 | E8: 0.05 | F8: 0.05 | G8: 0.05 | H8: 5% annual churn assumption
B9: Net Premium Users (after churn) | C9: =C7*(1-C8) -> 1900 | D9: =D7*(1-D8) -> 8550 | E9: =E7*(1-E8) -> 35625 | F9: =F7*(1-F8) -> 128250 | G9: =G7*(1-G8) -> 380000 | H9: Retained paying subscribers
B10: Cities Launched | C10: 2 | D10: 5 | E10: 12 | F10: 25 | G10: 50 | H10: Geographic expansion plan
B12: PRICING & REVENUE
B13: Monthly Subscription Price | C13: 12 | D13: 12 | E13: 12 | F13: 14 | G13: 15 | H13: Price increase Y4-Y5 with features
B14: Annual Subscription (per user) | C14: =C13*12 -> 144 | D14: =D13*12 -> 144 | E14: =E13*12 -> 144 | F14: =F13*12 -> 168 | G14: =G13*12 -> 180 | H14: Monthly x 12
B15: B2B Partners (Businesses) | C15: 10 | D15: 30 | E15: 80 | F15: 175 | G15: 350 | H15: Gyms, cafes, universities, apts
B16: Avg B2B Annual Contract Value | C16: 10000 | D16: 13333 | E16: 15000 | F16: 20000 | G16: 22857 | H16: Featured location packages
B18: COST STRUCTURE
B19: Engineering Headcount | C19: 4 | D19: 8 | E19: 15 | F19: 25 | G19: 40 | H19: iOS, Android, Backend, AI/ML
B20: Avg Engineering Salary | C20: 95000 | D20: 100000 | E20: 110000 | F20: 120000 | G20: 130000 | H20: Fully loaded cost per head
B21: Marketing Spend (% of Rev) | C21: 0.45 | D21: 0.3 | E21: 0.2 | F21: 0.15 | G21: 0.12 | H21: Decreases as organic grows
B22: G&A / Ops Headcount | C22: 3 | D22: 6 | E22: 12 | F22: 20 | G22: 35 | H22: Ops, finance, HR, legal, CS
B23: Avg G&A Salary | C23: 70000 | D23: 75000 | E23: 80000 | F23: 85000 | G23: 90000 | H23: Fully loaded cost per head
B24: Infrastructure Cost / User / Yr | C24: 2.5 | D24: 2 | E24: 1.5 | F24: 1.2 | G24: 1 | H24: AWS/GCP, scales down per user
B25: Customer Acq Cost (CAC) | C25: 8 | D25: 6 | E25: 4.5 | F25: 3.5 | G25: 3 | H25: Declines with virality/brand
B27: VALUATION & EXIT
B28: Revenue Multiple (Exit) | G28: 8 | H28: SaaS/social platform comps
B29: Discount Rate (WACC) | G29: 0.25 | H29: Early-stage risk premium
B30: Tax Rate | C30: 0 | D30: 0 | E30: 0.15 | F30: 0.21 | G30: 0.21 | H30: NOL carryforward Y1-Y2
B31: Potential Acquirers | H31: Meta, Bumble, Snap, Strava, Eventbrite

Sheet Revenue Model
A1: CIRCLES — REVENUE MODEL
B2: Revenue Drivers | C2: Year 1 | D2: Year 2 | E2: Year 3 | F2: Year 4 | G2: Year 5 | H2: 5-Yr Total
B3: SUBSCRIPTION REVENUE (B2C)
B4: Total Users | C4: =Assumptions!C4 -> 20000 | D4: =Assumptions!D4 -> 75000 | E4: =Assumptions!E4 -> 250000 | F4: =Assumptions!F4 -> 750000 | G4: =Assumptions!G4 -> 2000000
B5: Premium Conversion Rate | C5: =Assumptions!C6 -> 0.1 | D5: =Assumptions!D6 -> 0.12 | E5: =Assumptions!E6 -> 0.15 | F5: =Assumptions!F6 -> 0.18 | G5: =Assumptions!G6 -> 0.2
B6: Gross Premium Users | C6: =C4*C5 -> 2000 | D6: =D4*D5 -> 9000 | E6: =E4*E5 -> 37500 | F6: =F4*F5 -> 135000 | G6: =G4*G5 -> 400000
B7: Less: Churn | C7: =Assumptions!C8 -> 0.05 | D7: =Assumptions!D8 -> 0.05 | E7: =Assumptions!E8 -> 0.05 | F7: =Assumptions!F8 -> 0.05 | G7: =Assumptions!G8 -> 0.05
B8: Net Premium Users | C8: =C6*(1-C7) -> 1900 | D8: =D6*(1-D7) -> 8550 | E8: =E6*(1-E7) -> 35625 | F8: =F6*(1-F7) -> 128250 | G8: =G6*(1-G7) -> 380000
B9: Annual Subscription Price | C9: =Assumptions!C14 -> 144 | D9: =Assumptions!D14 -> 144 | E9: =Assumptions!E14 -> 144 | F9: =Assumptions!F14 -> 168 | G9: =Assumptions!G14 -> 180
B10: Total Subscription Revenue | C10: =C8*C9 -> 273600 | D10: =D8*D9 -> 1231200 | E10: =E8*E9 -> 5130000 | F10: =F8*F9 -> 21546000 | G10: =G8*G9 -> 68400000 | H10: =SUM(C10:G10) -> 96580800
B12: B2B REVENUE (FEATURED LOCATIONS)
B13: B2B Partners | C13: =Assumptions!C15 -> 10 | D13: =Assumptions!D15 -> 30 | E13: =Assumptions!E15 -> 80 | F13: =Assumptions!F15 -> 175 | G13: =Assumptions!G15 -> 350
B14: Avg Annual Contract Value | C14: =Assumptions!C16 -> 10000 | D14: =Assumptions!D16 -> 13333 | E14: =Assumptions!E16 -> 15000 | F14: =Assumptions!F16 -> 20000 | G14: =Assumptions!G16 -> 22857
B15: Total B2B Revenue | C15: =C13*C14 -> 100000 | D15: =D13*D14 -> 399990 | E15: =E13*E14 -> 1200000 | F15: =F13*F14 -> 3500000 | G15: =G13*G14 -> 7999950 | H15: =SUM(C15:G15) -> 13199940
B17: TOTAL REVENUE SUMMARY
B18: Subscription Revenue | C18: =C10 -> 273600 | D18: =D10 -> 1231200 | E18: =E10 -> 5130000 | F18: =F10 -> 21546000 | G18: =G10 -> 68400000 | H18: =H10 -> 96580800
B19: B2B Revenue | C19: =C15 -> 100000 | D19: =D15 -> 399990 | E19: =E15 -> 1200000 | F19: =F15 -> 3500000 | G19: =G15 -> 7999950 | H19: =H15 -> 13199940
B20: TOTAL REVENUE | C20: =C18+C19 -> 373600 | D20: =D18+D19 -> 1631190 | E20: =E18+E19 -> 6330000 | F20: =F18+F19 -> 25046000 | G20: =G18+G19 -> 76399950 | H20: =H18+H19 -> 109780740
B21: YoY Revenue Growth | C21: — | D21: =(D20-C20)/C20 -> 3.3661403 | E21: =(E20-D20)/D20 -> 2.8806025 | F21: =(F20-E20)/E20 -> 2.9567141 | G21: =(G20-F20)/F20 -> 2.0503853
B23: REVENUE MIX (%)
B24: Subscription % of Total | C24: =C18/C20 -> 0.73233405 | D24: =D18/D20 -> 0.75478638 | E24: =E18/E20 -> 0.81042654 | F24: =F18/F20 -> 0.86025713 | G24: =G18/G20 -> 0.89528854 | H24: =H18/H20 -> 0.87976088
B25: B2B % of Total | C25: =C19/C20 -> 0.26766595 | D25: =D19/D20 -> 0.24521362 | E25: =E19/E20 -> 0.18957346 | F25: =F19/F20 -> 0.13974287 | G25: =G19/G20 -> 0.10471146 | H25: =H19/H20 -> 0.12023912
B26: Avg Revenue Per User (ARPU) | C26: =C20/C4 -> 18.68 | D26: =D20/D4 -> 21.7492 | E26: =E20/E4 -> 25.32 | F26: =F20/F4 -> 33.394667 | G26: =G20/G4 -> 38.199975

Sheet Cost Structure
A1: CIRCLES — COST STRUCTURE
B2: Cost Category | C2: Year 1 | D2: Year 2 | E2: Year 3 | F2: Year 4 | G2: Year 5 | H2: 5-Yr Total
B3: PERSONNEL COSTS
B4: Engineering | C4: =Assumptions!C19*Assumptions!C20 -> 380000 | D4: =Assumptions!D19*Assumptions!D20 -> 800000 | E4: =Assumptions!E19*Assumptions!E20 -> 1650000 | F4: =Assumptions!F19*Assumptions!F20 -> 3000000 | G4: =Assumptions!G19*Assumptions!G20 -> 5200000 | H4: =SUM(C4:G4) -> 11030000
B5: G&A / Operations | C5: =Assumptions!C22*Assumptions!C23 -> 210000 | D5: =Assumptions!D22*Assumptions!D23 -> 450000 | E5: =Assumptions!E22*Assumptions!E23 -> 960000 | F5: =Assumptions!F22*Assumptions!F23 -> 1700000 | G5: =Assumptions!G22*Assumptions!G23 -> 3150000 | H5: =SUM(C5:G5) -> 6470000
B6: Total Headcount | C6: =Assumptions!C19+Assumptions!C22 -> 7 | D6: =Assumptions!D19+Assumptions!D22 -> 14 | E6: =Assumptions!E19+Assumptions!E22 -> 27 | F6: =Assumptions!F19+Assumptions!F22 -> 45 | G6: =Assumptions!G19+Assumptions!G22 -> 75
B7: Total Personnel Costs | C7: =C4+C5 -> 590000 | D7: =D4+D5 -> 1250000 | E7: =E4+E5 -> 2610000 | F7: =F4+F5 -> 4700000 | G7: =G4+G5 -> 8350000 | H7: =SUM(C7:G7) -> 17500000
B9: MARKETING & GROWTH
B10: Marketing Spend (% Rev) | C10: =Assumptions!C21 -> 0.45 | D10: =Assumptions!D21 -> 0.3 | E10: =Assumptions!E21 -> 0.2 | F10: =Assumptions!F21 -> 0.15 | G10: =Assumptions!G21 -> 0.12
B11: Marketing Spend | C11: ='Revenue Model'!C20*C10 -> 168120 | D11: ='Revenue Model'!D20*D10 -> 489357 | E11: ='Revenue Model'!E20*E10 -> 1266000 | F11: ='Revenue Model'!F20*F10 -> 3756900 | G11: ='Revenue Model'!G20*G10 -> 9167994 | H11: =SUM(C11:G11) -> 14848371
B13: INFRASTRUCTURE & HOSTING
B14: Cost / User / Year | C14: =Assumptions!C24 -> 2.5 | D14: =Assumptions!D24 -> 2 | E14: =Assumptions!E24 -> 1.5 | F14: =Assumptions!F24 -> 1.2 | G14: =Assumptions!G24 -> 1
B15: Infrastructure Cost | C15: ='Revenue Model'!C4*C14 -> 50000 | D15: ='Revenue Model'!D4*D14 -> 150000 | E15: ='Revenue Model'!E4*E14 -> 375000 | F15: ='Revenue Model'!F4*F14 -> 900000 | G15: ='Revenue Model'!G4*G14 -> 2000000 | H15: =SUM(C15:G15) -> 3475000
B17: TOTAL OPERATING EXPENSES
B18: Personnel | C18: =C7 -> 590000 | D18: =D7 -> 1250000 | E18: =E7 -> 2610000 | F18: =F7 -> 4700000 | G18: =G7 -> 8350000 | H18: =H7 -> 17500000
B19: Marketing | C19: =C11 -> 168120 | D19: =D11 -> 489357 | E19: =E11 -> 1266000 | F19: =F11 -> 3756900 | G19: =G11 -> 9167994 | H19: =H11 -> 14848371
B20: Infrastructure | C20: =C15 -> 50000 | D20: =D15 -> 150000 | E20: =E15 -> 375000 | F20: =F15 -> 900000 | G20: =G15 -> 2000000 | H20: =H15 -> 3475000
B21: TOTAL OPERATING EXPENSES | C21: =C18+C19+C20 -> 808120 | D21: =D18+D19+D20 -> 1889357 | E21: =E18+E19+E20 -> 4251000 | F21: =F18+F19+F20 -> 9356900 | G21: =G18+G19+G20 -> 19517994 | H21: =H18+H19+H20 -> 35823371
B22: OpEx as % of Revenue | C22: =C21/'Revenue Model'!C20 -> 2.1630621 | D22: =D21/'Revenue Model'!D20 -> 1.1582691 | E22: =E21/'Revenue Model'!E20 -> 0.67156398 | F22: =F21/'Revenue Model'!F20 -> 0.3735886 | G22: =G21/'Revenue Model'!G20 -> 0.25547129

Sheet P&L
A1: CIRCLES — PROJECTED INCOME STATEMENT
B2: ($) | C2: Year 1 | D2: Year 2 | E2: Year 3 | F2: Year 4 | G2: Year 5 | H2: 5-Yr Total
B3: REVENUE
B4: Subscription Revenue | C4: ='Revenue Model'!C10 -> 273600 | D4: ='Revenue Model'!D10 -> 1231200 | E4: ='Revenue Model'!E10 -> 5130000 | F4: ='Revenue Model'!F10 -> 21546000 | G4: ='Revenue Model'!G10 -> 68400000 | H4: =SUM(C4:G4) -> 96580800
B5: B2B Revenue | C5: ='Revenue Model'!C15 -> 100000 | D5: ='Revenue Model'!D15 -> 399990 | E5: ='Revenue Model'!E15 -> 1200000 | F5: ='Revenue Model'!F15 -> 3500000 | G5: ='Revenue Model'!G15 -> 7999950 | H5: =SUM(C5:G5) -> 13199940
B6: Total Revenue | C6: =C4+C5 -> 373600 | D6: =D4+D5 -> 1631190 | E6: =E4+E5 -> 6330000 | F6: =F4+F5 -> 25046000 | G6: =G4+G5 -> 76399950 | H6: =H4+H5 -> 109780740
B8: OPERATING EXPENSES
B9: Personnel Costs | C9: ='Cost Structure'!C7 -> 590000 | D9: ='Cost Structure'!D7 -> 1250000 | E9: ='Cost Structure'!E7 -> 2610000 | F9: ='Cost Structure'!F7 -> 4700000 | G9: ='Cost Structure'!G7 -> 8350000 | H9: =SUM(C9:G9) -> 17500000
B10: Marketing & Growth | C10: ='Cost Structure'!C11 -> 168120 | D10: ='Cost Structure'!D11 -> 489357 | E10: ='Cost Structure'!E11 -> 1266000 | F10: ='Cost Structure'!F11 -> 3756900 | G10: ='Cost Structure'!G11 -> 9167994 | H10: =SUM(C10:G10) -> 14848371
B11: Infrastructure & Hosting | C11: ='Cost Structure'!C15 -> 50000 | D11: ='Cost Structure'!D15 -> 150000 | E11: ='Cost Structure'!E15 -> 375000 | F11: ='Cost Structure'!F15 -> 900000 | G11: ='Cost Structure'!G15 -> 2000000 | H11: =SUM(C11:G11) -> 3475000
B12: Total Operating Expenses | C12: =SUM(C9:C11) -> 808120 | D12: =SUM(D9:D11) -> 1889357 | E12: =SUM(E9:E11) -> 4251000 | F12: =SUM(F9:F11) -> 9356900 | G12: =SUM(G9:G11) -> 19517994 | H12: =SUM(H9:H11) -> 35823371
B14: PROFITABILITY
B15: EBITDA | C15: =C6-C12 -> -434520 | D15: =D6-D12 -> -258167 | E15: =E6-E12 -> 2079000 | F15: =F6-F12 -> 15689100 | G15: =G6-G12 -> 56881956 | H15: =H6-H12 -> 73957369
B16: EBITDA Margin | C16: =IF(C6=0,0,C15/C6) -> -1.1630621 | D16: =IF(D6=0,0,D15/D6) -> -0.15826912 | E16: =IF(E6=0,0,E15/E6) -> 0.32843602 | F16: =IF(F6=0,0,F15/F6) -> 0.6264114 | G16: =IF(G6=0,0,G15/G6) -> 0.74452871
B18: Tax Rate | C18: =Assumptions!C30 -> 0 | D18: =Assumptions!D30 -> 0 | E18: =Assumptions!E30 -> 0.15 | F18: =Assumptions!F30 -> 0.21 | G18: =Assumptions!G30 -> 0.21
B19: Taxes | C19: =IF(C15>0,C15*C18,0) -> 0 | D19: =IF(D15>0,D15*D18,0) -> 0 | E19: =IF(E15>0,E15*E18,0) -> 311850 | F19: =IF(F15>0,F15*F18,0) -> 3294711 | G19: =IF(G15>0,G15*G18,0) -> 11945211 | H19: =SUM(C19:G19) -> 15551772
B20: NET INCOME | C20: =C15-C19 -> -434520 | D20: =D15-D19 -> -258167 | E20: =E15-E19 -> 1767150 | F20: =F15-F19 -> 12394389 | G20: =G15-G19 -> 44936745 | H20: =H15-H19 -> 58405597
B21: Net Margin | C21: =IF(C6=0,0,C20/C6) -> -1.1630621 | D21: =IF(D6=0,0,D20/D6) -> -0.15826912 | E21: =IF(E6=0,0,E20/E6) -> 0.27917062 | F21: =IF(F6=0,0,F20/F6) -> 0.49486501 | G21: =IF(G6=0,0,G20/G6) -> 0.58817768
B22: Cumulative Net Income | C22: =C20 -> -434520 | D22: =C22+D20 -> -692687 | E22: =D22+E20 -> 1074463 | F22: =E22+F20 -> 13468852 | G22: =F22+G20 -> 58405597

Sheet Unit Economics
A1: CIRCLES — UNIT ECONOMICS
B2: Metric | C2: Year 1 | D2: Year 2 | E2: Year 3 | F2: Year 4 | G2: Year 5
B3: CUSTOMER ACQUISITION
B4: New Users Acquired | C4: =Assumptions!C4 -> 20000 | D4: =Assumptions!D4-Assumptions!C4 -> 55000 | E4: =Assumptions!E4-Assumptions!D4 -> 175000 | F4: =Assumptions!F4-Assumptions!E4 -> 500000 | G4: =Assumptions!G4-Assumptions!F4 -> 1250000
B5: Customer Acquisition Cost (CAC) | C5: =Assumptions!C25 -> 8 | D5: =Assumptions!D25 -> 6 | E5: =Assumptions!E25 -> 4.5 | F5: =Assumptions!F25 -> 3.5 | G5: =Assumptions!G25 -> 3
B6: Total Acquisition Spend | C6: =C4*C5 -> 160000 | D6: =D4*D5 -> 330000 | E6: =E4*E5 -> 787500 | F6: =F4*F5 -> 1750000 | G6: =G4*G5 -> 3750000
B8: LIFETIME VALUE (LTV)
B9: ARPU (Annual) | C9: ='Revenue Model'!C26 -> 18.68 | D9: ='Revenue Model'!D26 -> 21.7492 | E9: ='Revenue Model'!E26 -> 25.32 | F9: ='Revenue Model'!F26 -> 33.394667 | G9: ='Revenue Model'!G26 -> 38.199975
B10: Annual Churn Rate | C10: =Assumptions!C8 -> 0.05 | D10: =Assumptions!D8 -> 0.05 | E10: =Assumptions!E8 -> 0.05 | F10: =Assumptions!F8 -> 0.05 | G10: =Assumptions!G8 -> 0.05
B11: Avg Customer Lifespan (yrs) | C11: =1/C10 -> 20 | D11: =1/D10 -> 20 | E11: =1/E10 -> 20 | F11: =1/F10 -> 20 | G11: =1/G10 -> 20
B12: LTV per User | C12: =C9*C11 -> 373.6 | D12: =D9*D11 -> 434.984 | E12: =E9*E11 -> 506.4 | F12: =F9*F11 -> 667.89333 | G12: =G9*G11 -> 763.9995
B14: KEY RATIOS & PAYBACK
B15: LTV / CAC Ratio | C15: =C12/C5 -> 46.7 | D15: =D12/D5 -> 72.497333 | E15: =E12/E5 -> 112.53333 | F15: =F12/F5 -> 190.82667 | G15: =G12/G5 -> 254.6665
B16: Benchmark (healthy > 3.0x) | C16: =IF(C15>=3,"Healthy","Below Target") -> Healthy | D16: =IF(D15>=3,"Healthy","Below Target") -> Healthy | E16: =IF(E15>=3,"Healthy","Below Target") -> Healthy | F16: =IF(F15>=3,"Healthy","Below Target") -> Healthy | G16: =IF(G15>=3,"Healthy","Below Target") -> Healthy
B17: CAC Payback Period (months) | C17: =C5/(C9/12) -> 5.1391863 | D17: =D5/(D9/12) -> 3.3104666 | E17: =E5/(E9/12) -> 2.1327014 | F17: =F5/(F9/12) -> 1.2576859 | G17: =G5/(G9/12) -> 0.94240899
B19: PER-USER ECONOMICS
B20: Revenue per User | C20: =C9 -> 18.68 | D20: =D9 -> 21.7492 | E20: =E9 -> 25.32 | F20: =F9 -> 33.394667 | G20: =G9 -> 38.199975
B21: Cost per User | C21: ='Cost Structure'!C21/Assumptions!C4 -> 40.406 | D21: ='Cost Structure'!D21/Assumptions!D4 -> 25.191427 | E21: ='Cost Structure'!E21/Assumptions!E4 -> 17.004 | F21: ='Cost Structure'!F21/Assumptions!F4 -> 12.475867 | G21: ='Cost Structure'!G21/Assumptions!G4 -> 9.758997
B22: Contribution per User | C22: =C20-C21 -> -21.726 | D22: =D20-D21 -> -3.4422267 | E22: =E20-E21 -> 8.316 | F22: =F20-F21 -> 20.9188 | G22: =G20-G21 -> 28.440978
B23: Contribution Margin % | C23: =C22/C20 -> -1.1630621 | D23: =D22/D20 -> -0.15826912 | E23: =E22/E20 -> 0.32843602 | F23: =F22/F20 -> 0.6264114 | G23: =G22/G20 -> 0.74452871
