Workbook

Sheet Cover & Summary
A1: PHILADELPHIA PGA SECTION
A2: Growth Strategy Financial Model — Investment Committee Overview
A3: "We Built the Game. It's Time Philadelphia Knew It."
A5: REVENUE SUMMARY BY YEAR
B6: Year 1 | C6: Year 2 | D6: Year 3 | E6: Year 4 | F6: Year 5 | G6: Year 6 | H6: Year 7 | I6: Year 8 | J6: Year 9 | K6: Year 10
A7: Platform Revenue | B7: ='Revenue Build'!B20 -> 265097.45 | C7: ='Revenue Build'!C20 -> 460846.94 | D7: ='Revenue Build'!D20 -> 768382.19 | E7: ='Revenue Build'!E20 -> 1000032.2 | F7: ='Revenue Build'!F20 -> 1352494.4 | G7: ='Revenue Build'!G20 -> 1503162.3 | H7: ='Revenue Build'!H20 -> 1665684 | I7: ='Revenue Build'!I20 -> 1832755.8 | ... K7: ='Revenue Build'!K20 -> 2066507
A8: Creator Revenue | B8: ='Revenue Build'!B38 -> 979.2 | C8: ='Revenue Build'!C38 -> 1815.4368 | D8: ='Revenue Build'!D38 -> 63116.5 | E8: ='Revenue Build'!E38 -> 118065.99 | F8: ='Revenue Build'!F38 -> 205510.49 | G8: ='Revenue Build'!G38 -> 281243.39 | H8: ='Revenue Build'!H38 -> 367015.3 | I8: ='Revenue Build'!I38 -> 462827.9 | ... K8: ='Revenue Build'!K38 -> 708943.44
A9: Venue Revenue | B9: ='Revenue Build'!B56 -> 131224 | C9: ='Revenue Build'!C56 -> 196891.08 | D9: ='Revenue Build'!D56 -> 328246.35 | E9: ='Revenue Build'!E56 -> 394012.49 | F9: ='Revenue Build'!F56 -> 525510.49 | G9: ='Revenue Build'!G56 -> 525675.81 | H9: ='Revenue Build'!H56 -> 525846.08 | I9: ='Revenue Build'!I56 -> 526021.46 | ... K9: ='Revenue Build'!K56 -> 526388.17
A10: Corporate Revenue | B10: ='Revenue Build'!B71 -> 187500 | C10: ='Revenue Build'!C71 -> 546000 | D10: ='Revenue Build'!D71 -> 910000 | E10: ='Revenue Build'!E71 -> 1365000 | F10: ='Revenue Build'!F71 -> 2047500 | G10: ='Revenue Build'!G71 -> 2366000 | H10: ='Revenue Build'!H71 -> 2639000 | I10: ='Revenue Build'!I71 -> 2957500 | ... K10: ='Revenue Build'!K71 -> 3640000
A11: TOTAL REVENUE | B11: ='Revenue Build'!B78 -> 584800.65 | C11: ='Revenue Build'!C78 -> 1205553.5 | D11: ='Revenue Build'!D78 -> 2069745 | E11: ='Revenue Build'!E78 -> 2877110.7 | F11: ='Revenue Build'!F78 -> 4131015.4 | G11: ='Revenue Build'!G78 -> 4676081.5 | H11: ='Revenue Build'!H78 -> 5197545.4 | I11: ='Revenue Build'!I78 -> 5779105.2 | ... K11: ='Revenue Build'!K78 -> 6941838.6
A13: EBITDA | B13: ='Margin Analysis'!B47 -> -715646.6 | C13: ='Margin Analysis'!C47 -> -651336.82 | D13: ='Margin Analysis'!D47 -> -219866.69 | E13: ='Margin Analysis'!E47 -> -5610.34 | F13: ='Margin Analysis'!F47 -> 652175.49 | G13: ='Margin Analysis'!G47 -> 911168.83 | H13: ='Margin Analysis'!H47 -> 954215.76 | I13: ='Margin Analysis'!I47 -> 1235087.3 | ... K13: ='Margin Analysis'!K47 -> 1609199.4
A14: EBITDA Margin % | B14: ='Margin Analysis'!B48 -> -1.2237445 | C14: ='Margin Analysis'!C48 -> -0.54028033 | D14: ='Margin Analysis'!D48 -> -0.10622888 | E14: ='Margin Analysis'!E48 -> -0.001949991 | F14: ='Margin Analysis'!F48 -> 0.15787292 | G14: ='Margin Analysis'!G48 -> 0.19485735 | H14: ='Margin Analysis'!H48 -> 0.18358969 | I14: ='Margin Analysis'!I48 -> 0.21371601 | ... K14: ='Margin Analysis'!K48 -> 0.2318117
A15: Free Cash Flow | B15: ='Margin Analysis'!B59 -> -791670.69 | C15: ='Margin Analysis'!C59 -> -761274.72 | D15: ='Margin Analysis'!D59 -> -392489.27 | E15: ='Margin Analysis'!E59 -> -214055.12 | F15: ='Margin Analysis'!F59 -> 213251.08 | G15: ='Margin Analysis'!G59 -> 441037.87 | H15: ='Margin Analysis'!H59 -> 453049.04 | I15: ='Margin Analysis'!I59 -> 634178.73 | ... K15: ='Margin Analysis'!K59 -> 859548.95
A16: FCF Margin % | B16: ='Margin Analysis'!B60 -> -1.3537445 | C16: ='Margin Analysis'!C60 -> -0.63147322 | D16: ='Margin Analysis'!D60 -> -0.1896317 | E16: ='Margin Analysis'!E60 -> -0.074399336 | F16: ='Margin Analysis'!F60 -> 0.051621952 | G16: ='Margin Analysis'!G60 -> 0.094317832 | H16: ='Margin Analysis'!H60 -> 0.087165961 | I16: ='Margin Analysis'!I60 -> 0.10973649 | ... K16: ='Margin Analysis'!K60 -> 0.12382151
A18: VALUATION & INVESTMENT RETURNS
A19: DCF Enterprise Value (Perpetuity Growth) | B19: ='DCF Valuation'!B43 -> 1245555.5
A20: DCF Enterprise Value (Exit Multiple) | B20: ='DCF Valuation'!B44 -> 4195111.3
A21: DCF Enterprise Value (Average) | B21: ='DCF Valuation'!B45 -> 2720333.4
A22: LBO Sponsor MOIC | B22: ='LBO Analysis'!B53 -> 5.2400756
A23: LBO Sponsor IRR (5-yr hold) | B23: ='LBO Analysis'!B54 -> 0.39273186
A24: EV / Year 5 EBITDA | B24: ='DCF Valuation'!B51 -> 4.1711678
A25: EV / Year 10 EBITDA | B25: ='DCF Valuation'!B52 -> 1.6904886
A27: KEY OPERATING KPIs — YEAR 5 SNAPSHOT
A28: Active Pros on Platform | B28: ='Revenue Build'!F9 -> 286.65
A29: Total Annual Lesson Bookings | B29: ='Revenue Build'!F12 -> 100900.8
A30: Gross Marketplace Volume | B30: ='Revenue Build'!F14 -> 9653002.8
A31: Active Creators | B31: ='Revenue Build'!F23 -> 50
A32: Active Venue Partners | B32: ='Revenue Build'!F41 -> 8
A33: Active Corporate Clients | B33: ='Revenue Build'!F59 -> 45
A34: Consumer LTV / CAC | B34: ='Unit Economics'!F14 -> 10.723359
A35: Corporate LTV / CAC | B35: ='Unit Economics'!F43 -> 91
A37: SCENARIO COMPARISON — YEAR 5 EBITDA & VALUATION
B38: Base | C38: Upside | D38: Downside | E38: Stress
A39: Year 5 EBITDA | B39: ='Scenario Analysis'!B34 -> 652175.49 | C39: ='Scenario Analysis'!C34 -> 1619358 | D39: ='Scenario Analysis'!D34 -> 123930.46 | E39: ='Scenario Analysis'!E34 -> -144585.54
A40: Implied EV | B40: ='Scenario Analysis'!B35 -> 7826105.8 | C40: ='Scenario Analysis'!C35 -> 22671013 | D40: ='Scenario Analysis'!D35 -> 991443.7 | E40: ='Scenario Analysis'!E35 -> 0
A41: LBO IRR | B41: ='Scenario Analysis'!B37 -> 0.28 | C41: ='Scenario Analysis'!C37 -> 0.42 | D41: ='Scenario Analysis'!D37 -> 0.05 | E41: ='Scenario Analysis'!E37 -> -0.15
A43: INVESTMENT THESIS — KEY TAKEAWAYS
A44: BIGGEST VALUE DRIVERS: Platform transaction revenue scales with pro onboarding; corporate program offers highest absolute $ per client; venue partnerships provide low-CAC top-of-funnel.
A45: MOST IMPORTANT RISKS: Pro adoption speed is the critical gate; brand confusion with PGA Tour must be addressed before marketing spend scales; corporate sales cycle length determines cash flow timing.
A46: MARGIN INFLECTION POINTS: Y2-3 transition from investment to contribution-positive; Y5 operating leverage kicks in as fixed costs are absorbed; Y7+ mature margins approach 25-35% EBITDA.
A47: UPSIDE CASE: Requires 80% pro onboarding, 12 venue partners, 70 corporate clients. Golf participation continues post-COVID growth. Creator network generates earned media multiplier.
A48: DOWNSIDE BREAKS: If pro adoption stays below 40% by Y3, platform economics do not work. If corporate sales cycle exceeds 6 months, cash burn extends. If venue conversion <2%, channel is unprofitable.
A49: CAPITAL EFFICIENCY: Low capex model (5% of rev). Primary investment is people. Break-even at ~Y3 EBITDA. Cumulative FCF turns positive by Y4-5 in base case.

Sheet Assumptions
A1: PHILADELPHIA PGA SECTION — MASTER ASSUMPTIONS
A3: A. MARKET & DEMAND ASSUMPTIONS
A4: Assumption | B4: Value | C4: Unit | D4: Notes / Source
A5: Total PGA Professionals in Phila Section | B5: 900 | C5: # | D5: Per Philadelphia PGA brief
A6: % of Pros Addressable — Platform | B6: 0.7 | C6: % | D6: Excludes retired / inactive
A7: % of Pros Addressable — Creator | B7: 0.05 | C7: % | D7: Top content-capable pros
A8: Total Golfer Population in Region | B8: 2000000 | C8: # | D8: 2M+ rounds managed annually
A9: Beginner / Casual Golfer Population | B9: 500000 | C9: # | D9: ~25% of total golfer base
A10: Annual Golf Participation Growth | B10: 0.03 | C10: % | D10: National avg ~3% post-COVID
A11: Corporate Prospects in Phila DMA | B11: 200 | C11: # | D11: Finance, law, healthcare, tech
A12: Venue Partnership Prospects | B12: 8 | C12: # | D12: Topgolf + regional off-course
A13: Regional Golf Spending ($M) | B13: 200 | C13: $M | D13: Per brief — $200M+
A14: Phila DMA Households | B14: 2900000 | C14: # | D14: Census estimate
A15: % HH with Golf Interest | B15: 0.08 | C15: % | D15: National avg ~7-9%
A16: Non-Golfers Interested Nationally | B16: 21000000 | C16: # | D16: Per NGF data
A17: Phila DMA Share of National Pool | B17: 0.025 | C17: % | D17: ~2.5% of national pop
A19: B. LEARN GOLF PLATFORM ASSUMPTIONS
A20: Assumption | B20: Value | C20: Unit | D20: Notes / Source
A21: Year 1 Pro Onboarding Rate | B21: 0.15 | C21: % | D21: Conservative — 15% of addressable
A22: Year 3 Pro Onboarding Rate | B22: 0.4 | C22: % | D22: Mid-maturity target
A23: Year 5 Pro Onboarding Rate | B23: 0.65 | C23: % | D23: Scale target
A24: Year 10 Pro Onboarding Rate | B24: 0.85 | C24: % | D24: Mature platform
A25: Active Pro Rate (% of onboarded) | B25: 0.7 | C25: % | D25: Pros actively taking bookings
A26: Lessons per Active Pro per Week | B26: 8 | C26: #/wk | D26: Avg across all active pros
A27: Avg Lesson Price ($) | B27: 85 | C27: $ | D27: Phila market avg
A28: Annual Lesson Price Escalation | B28: 0.03 | C28: % | D28: Inflation + quality premium
A29: Platform Take Rate | B29: 0.12 | C29: % | D29: 12% of gross lesson value
A30: Premium Listing Price ($/month) | B30: 99 | C30: $/mo | D30: Enhanced profile + visibility
A31: % of Active Pros Buying Premium | B31: 0.25 | C31: % | D31: Year 1 estimate
A32: Lesson Package Attach Rate | B32: 0.15 | C32: % | D32: % of lessons as bundles
... A35: Teaching Weeks per Year | B35: 44 | C35: wks | D35: Excludes holidays / weather
A37: C. CREATOR NETWORK ASSUMPTIONS
A38: Assumption | B38: Value | C38: Unit | D38: Notes / Source
A39: Year 1 Creators Onboarded | B39: 10 | C39: # | D39: Pilot cohort of top pros
A40: Year 3 Creators Active | B40: 30 | C40: # | D40: Expanded network
A41: Year 5 Creators Active | B41: 50 | C41: # | D41: Mature creator program
A42: Avg Monthly Impressions per Creator | B42: 50000 | C42: # | D42: Social media reach
A43: Engagement Rate | B43: 0.04 | C43: % | D43: Industry avg 3-5% for niche
A44: Clickthrough Rate (to website) | B44: 0.02 | C44: % | D44: Standard social CTR
A45: Conversion Rate — Click to Inquiry | B45: 0.08 | C45: % | D45: Landing page conversion
A46: Conversion Rate — Inquiry to Booking | B46: 0.25 | C46: % | D46: Sales funnel close rate
A47: Creator Monthly Compensation ($) | B47: 500 | C47: $ | D47: Stipend + content support
A48: Content Production Support ($/creator/mo) | B48: 200 | C48: $ | D48: Editing, assets, tools
A49: Platform Mgmt Cost ($/creator/mo) | B49: 100 | C49: $ | D49: Coordination overhead
A50: Brand Partnership Rev per Creator ($/yr) | B50: 2000 | C50: $ | D50: Sponsorship rev share Y3+
A52: D. TOPGOLF / VENUE PARTNERSHIP ASSUMPTIONS
A53: Assumption | B53: Value | C53: Unit | D53: Notes / Source
A54: Year 1 Venue Partners | B54: 2 | C54: # | D54: Topgolf KoP + Bridgewater
A55: Year 3 Venue Partners | B55: 5 | C55: # | D55: Add regional entertainment venues
A56: Year 5 Venue Partners | B56: 8 | C56: # | D56: Full regional coverage
A57: Annual Foot Traffic per Venue | B57: 500000 | C57: # | D57: Topgolf avg ~500K visits/yr
A58: % Traffic Exposed to PGA Content | B58: 0.3 | C58: % | D58: In-venue signage / digital
A59: QR Scan / Digital Engagement Rate | B59: 0.02 | C59: % | D59: 2% of exposed traffic
A60: Site Visit Rate (from scan) | B60: 0.4 | C60: % | D60: 40% of scanners visit site
A61: Booking Conversion (from site visit) | B61: 0.05 | C61: % | D61: 5% of visitors book
A62: Annual Partnership Fee per Venue ($) | B62: 25000 | C62: $ | D62: Co-marketing investment
A63: Event Revenue per Venue ($/yr) | B63: 40000 | C63: $ | D63: PGA-branded events at venue
A64: Co-Branded Activation Cost ($/venue/yr) | B64: 15000 | C64: $ | D64: Signage, digital, materials
A65: Avg Lesson Revenue per Venue Referral ($) | B65: 85 | C65: $ | D65: Same as platform avg
A67: E. CORPORATE GOLF PROGRAM ASSUMPTIONS
A68: Assumption | B68: Value | C68: Unit | D68: Notes / Source
A69: Year 1 Corporate Clients | B69: 5 | C69: # | D69: Pilot clients
A70: Year 3 Corporate Clients | B70: 20 | C70: # | D70: Growth phase
A71: Year 5 Corporate Clients | B71: 45 | C71: # | D71: Scaled program
A72: Year 10 Corporate Clients | B72: 80 | C72: # | D72: Mature state
A73: Events per Client per Year | B73: 4 | C73: #/yr | D73: Quarterly engagement avg
A74: Avg Revenue per Event ($) | B74: 8000 | C74: $ | D74: Instruction + venue + F&B
A75: Annual Corporate Retainer ($) | B75: 15000 | C75: $/yr | D75: Premium clients
A76: % of Clients on Retainer | B76: 0.3 | C76: % | D76: Top-tier engagement
A77: Sponsorship Revenue per Client ($/yr) | B77: 5000 | C77: $ | D77: Logo, branding, naming
A78: % of Clients Sponsoring | B78: 0.2 | C78: % | D78: Subset of total clients
A79: Client Renewal Rate | B79: 0.8 | C79: % | D79: Annual retention
A80: Event Delivery Cost (% of Event Rev) | B80: 0.55 | C80: % | D80: Pro fees, venue, logistics
... A82: Upsell Rate (clients adding services) | B82: 0.25 | C82: % | D82: Year-over-year expansion
A84: F. COST STRUCTURE ASSUMPTIONS
A85: Assumption | B85: Value | C85: Unit | D85: Notes / Source
A86: CEO / Executive Director (Salary + Ben) | B86: 150000 | C86: $ | D86: Full-time leadership
A87: VP Marketing / Growth | B87: 120000 | C87: $ | D87: Full-time hire Y1
A88: Partnership Sales Director | B88: 110000 | C88: $ | D88: Full-time Y1
A89: Content & Social Media Manager | B89: 75000 | C89: $ | D89: Full-time Y1
A90: Platform / Website Manager | B90: 85000 | C90: $ | D90: Full-time Y1
A91: Customer Support Specialist | B91: 55000 | C91: $ | D91: Full-time Y2
A92: Event Coordinator | B92: 60000 | C92: $ | D92: Full-time Y2
A93: Sales Associate (Corporate) | B93: 65000 | C93: $ | D93: Full-time Y2
A94: Benefits Load Factor (% of salary) | B94: 0.25 | C94: % | D94: Health, 401k, payroll taxes
A95: Annual Salary Escalation | B95: 0.03 | C95: % | D95: Cost of living adjustments
A96: Software / Platform Costs ($/yr) | B96: 60000 | C96: $ | D96: Website, CRM, analytics, tools
A97: Hosting & Maintenance ($/yr) | B97: 18000 | C97: $ | D97: Cloud hosting, SSL, CDN
... A104: Customer Support Costs ($/yr) | B104: 15000 | C104: $ | D104: Tools, escalation handling
A106: G. FINANCIAL ASSUMPTIONS
A107: Assumption | B107: Value | C107: Unit | D107: Notes / Source
A108: Federal + State Effective Tax Rate | B108: 0.25 | C108: % | D108: Blended effective rate
A109: WACC / Discount Rate | B109: 0.15 | C109: % | D109: Growth-stage appropriate
A110: Terminal Growth Rate | B110: 0.03 | C110: % | D110: Long-run GDP growth
A111: Exit EV/EBITDA Multiple | B111: 12 | C111: x | D111: Growth-stage platform comp
A112: Entry EV/EBITDA Multiple (LBO) | B112: 10 | C112: x | D112: Sponsor entry price
A113: Debt / Total Capital (LBO) | B113: 0.5 | C113: % | D113: 50% leverage
A114: Senior Debt Interest Rate | B114: 0.08 | C114: % | D114: Term loan rate
A115: Mezzanine Debt Interest Rate | B115: 0.12 | C115: % | D115: Subordinated debt
A116: Senior Debt as % of Total Debt | B116: 0.7 | C116: % | D116: 70/30 Sr/Mezz split
...

Sheet Revenue Build
A1: REVENUE BUILD BY SEGMENT — 10 YEAR FORECAST
B2: Year 1 | C2: Year 2 | D2: Year 3 | E2: Year 4 | F2: Year 5 | G2: Year 6 | H2: Year 7 | I2: Year 8 | J2: Year 9 | K2: Year 10
A4: A. LEARN GOLF PLATFORM
A5: Total Addressable Pros | B5: =Assumptions!B5*Assumptions!B6 -> 630 | C5: =Assumptions!B5*Assumptions!B6 -> 630 | D5: =Assumptions!B5*Assumptions!B6 -> 630 | E5: =Assumptions!B5*Assumptions!B6 -> 630 | F5: =Assumptions!B5*Assumptions!B6 -> 630 | G5: =Assumptions!B5*Assumptions!B6 -> 630 | H5: =Assumptions!B5*Assumptions!B6 -> 630 | I5: =Assumptions!B5*Assumptions!B6 -> 630 | J5: =Assumptions!B5*Assumptions!B6 -> 630 | K5: =Assumptions!B5*Assumptions!B6 -> 630
A6: Pro Onboarding Rate | B6: 0.15 | C6: 0.25 | D6: 0.4 | E6: 0.5 | F6: 0.65 | G6: 0.7 | H6: 0.75 | I6: 0.8 | J6: 0.82 | K6: 0.85
A7: Onboarded Pros | B7: =B5*B6 -> 94.5 | C7: =C5*C6 -> 157.5 | D7: =D5*D6 -> 252 | E7: =E5*E6 -> 315 | F7: =F5*F6 -> 409.5 | G7: =G5*G6 -> 441 | H7: =H5*H6 -> 472.5 | I7: =I5*I6 -> 504 | ... K7: =K5*K6 -> 535.5
A8: Active Pro Rate | B8: =Assumptions!B25 -> 0.7 | C8: =Assumptions!B25 -> 0.7 | D8: =Assumptions!B25 -> 0.7 | E8: =Assumptions!B25 -> 0.7 | F8: =Assumptions!B25 -> 0.7 | G8: =Assumptions!B25 -> 0.7 | H8: =Assumptions!B25 -> 0.7 | I8: =Assumptions!B25 -> 0.7 | J8: =Assumptions!B25 -> 0.7 | K8: =Assumptions!B25 -> 0.7
A9: Active Pros | B9: =B7*B8 -> 66.15 | C9: =C7*C8 -> 110.25 | D9: =D7*D8 -> 176.4 | E9: =E7*E8 -> 220.5 | F9: =F7*F8 -> 286.65 | G9: =G7*G8 -> 308.7 | H9: =H7*H8 -> 330.75 | I9: =I7*I8 -> 352.8 | ... K9: =K7*K8 -> 374.85
A10: Lessons per Pro per Week | B10: =Assumptions!B26 -> 8 | C10: =Assumptions!B26 -> 8 | D10: =Assumptions!B26 -> 8 | E10: =Assumptions!B26 -> 8 | F10: =Assumptions!B26 -> 8 | G10: =Assumptions!B26 -> 8 | H10: =Assumptions!B26 -> 8 | I10: =Assumptions!B26 -> 8 | J10: =Assumptions!B26 -> 8 | K10: =Assumptions!B26 -> 8
A11: Teaching Weeks per Year | B11: =Assumptions!B35 -> 44 | C11: =Assumptions!B35 -> 44 | D11: =Assumptions!B35 -> 44 | E11: =Assumptions!B35 -> 44 | F11: =Assumptions!B35 -> 44 | G11: =Assumptions!B35 -> 44 | H11: =Assumptions!B35 -> 44 | I11: =Assumptions!B35 -> 44 | J11: =Assumptions!B35 -> 44 | K11: =Assumptions!B35 -> 44
A12: Total Annual Lessons | B12: =B9*B10*B11 -> 23284.8 | C12: =C9*C10*C11 -> 38808 | D12: =D9*D10*D11 -> 62092.8 | E12: =E9*E10*E11 -> 77616 | F12: =F9*F10*F11 -> 100900.8 | G12: =G9*G10*G11 -> 108662.4 | H12: =H9*H10*H11 -> 116424 | I12: =I9*I10*I11 -> 124185.6 | ... K12: =K9*K10*K11 -> 131947.2
A13: Avg Lesson Price ($) | B13: =Assumptions!B27 -> 85 | C13: =B13*(1+Assumptions!B28) -> 87.55 | D13: =C13*(1+Assumptions!B28) -> 90.1765 | E13: =D13*(1+Assumptions!B28) -> 92.881795 | F13: =E13*(1+Assumptions!B28) -> 95.668249 | G13: =F13*(1+Assumptions!B28) -> 98.538296 | H13: =G13*(1+Assumptions!B28) -> 101.49445 | I13: =H13*(1+Assumptions!B28) -> 104.53928 | J13: =I13*(1+Assumptions!B28) -> 107.67546 | K13: =J13*(1+Assumptions!B28) -> 110.90572
A14: Gross Marketplace Volume ($) | B14: =B12*B13 -> 1979208 | C14: =C12*C13 -> 3397640.4 | D14: =D12*D13 -> 5599311.4 | E14: =E12*E13 -> 7209113.4 | F14: =F12*F13 -> 9653002.8 | G14: =G12*G13 -> 10707408 | H14: =H12*H13 -> 11816389 | I14: =I12*I13 -> 12982273 | ... K14: =K12*K13 -> 14633699
A15: Platform Take Rate | B15: =Assumptions!B29 -> 0.12 | C15: =Assumptions!B29 -> 0.12 | D15: =Assumptions!B29 -> 0.12 | E15: =Assumptions!B29 -> 0.12 | F15: =Assumptions!B29 -> 0.12 | G15: =Assumptions!B29 -> 0.12 | H15: =Assumptions!B29 -> 0.12 | I15: =Assumptions!B29 -> 0.12 | J15: =Assumptions!B29 -> 0.12 | K15: =Assumptions!B29 -> 0.12
A16: Transaction Revenue ($) | B16: =B14*B15 -> 237504.96 | C16: =C14*C15 -> 407716.85 | D16: =D14*D15 -> 671917.37 | E16: =E14*E15 -> 865093.61 | F16: =F14*F15 -> 1158360.3 | G16: =G14*G15 -> 1284888.9 | H16: =H14*H15 -> 1417966.7 | I16: =I14*I15 -> 1557872.8 | ... K16: =K14*K15 -> 1756043.9
A17: Active Pros on Premium | B17: 0.2 | C17: 0.25 | D17: 0.3 | E17: 0.35 | F17: 0.4 | G17: 0.42 | H17: 0.45 | I17: 0.47 | J17: 0.48 | K17: 0.5
A18: Premium Listing Revenue ($) | B18: =B9*B17*Assumptions!B30*12 -> 15717.24 | C18: =C9*C17*Assumptions!B30*12 -> 32744.25 | D18: =D9*D17*Assumptions!B30*12 -> 62868.96 | E18: =E9*E17*Assumptions!B30*12 -> 91683.9 | F18: =F9*F17*Assumptions!B30*12 -> 136216.08 | G18: =G9*G17*Assumptions!B30*12 -> 154028.95 | H18: =H9*H17*Assumptions!B30*12 -> 176818.95 | I18: =I9*I17*Assumptions!B30*12 -> 196989.41 | J18: =J9*J17*Assumptions!B30*12 -> 206210.19 | K18: =K9*K17*Assumptions!B30*12 -> 222660.9
A19: Bundle Attach Uplift ($) | B19: =B16*Assumptions!B34 -> 11875.248 | C19: =C16*Assumptions!B34 -> 20385.842 | D19: =D16*Assumptions!B34 -> 33595.868 | E19: =E16*Assumptions!B34 -> 43254.68 | F19: =F16*Assumptions!B34 -> 57918.017 | G19: =G16*Assumptions!B34 -> 64244.447 | H19: =H16*Assumptions!B34 -> 70898.336 | I19: =I16*Assumptions!B34 -> 77893.638 | J19: =J16*Assumptions!B34 -> 82236.209 | K19: =K16*Assumptions!B34 -> 87802.196
A20: TOTAL PLATFORM REVENUE ($) | B20: =B16+B18+B19 -> 265097.45 | C20: =C16+C18+C19 -> 460846.94 | D20: =D16+D18+D19 -> 768382.19 | E20: =E16+E18+E19 -> 1000032.2 | F20: =F16+F18+F19 -> 1352494.4 | G20: =G16+G18+G19 -> 1503162.3 | H20: =H16+H18+H19 -> 1665684 | I20: =I16+I18+I19 -> 1832755.8 | ... K20: =K16+K18+K19 -> 2066507
A22: B. CREATOR / INFLUENCER NETWORK
A23: Active Creators | B23: 10 | C23: 18 | D23: 30 | E23: 38 | F23: 50 | G23: 55 | H23: 60 | I23: 65 | J23: 68 | K23: 70
A24: Avg Monthly Impressions per Creator | B24: =Assumptions!B42 -> 50000 | C24: =Assumptions!B42 -> 50000 | D24: =Assumptions!B42 -> 50000 | E24: =Assumptions!B42 -> 50000 | F24: =Assumptions!B42 -> 50000 | G24: =Assumptions!B42 -> 50000 | H24: =Assumptions!B42 -> 50000 | I24: =Assumptions!B42 -> 50000 | J24: =Assumptions!B42 -> 50000 | K24: =Assumptions!B42 -> 50000
A25: Total Monthly Impressions | B25: =B23*B24 -> 500000 | C25: =C23*C24 -> 900000 | D25: =D23*D24 -> 1500000 | E25: =E23*E24 -> 1900000 | F25: =F23*F24 -> 2500000 | G25: =G23*G24 -> 2750000 | H25: =H23*H24 -> 3000000 | I25: =I23*I24 -> 3250000 | ... K25: =K23*K24 -> 3500000
A26: Engagement Rate | B26: =Assumptions!B43 -> 0.04 | C26: =Assumptions!B43 -> 0.04 | D26: =Assumptions!B43 -> 0.04 | E26: =Assumptions!B43 -> 0.04 | F26: =Assumptions!B43 -> 0.04 | G26: =Assumptions!B43 -> 0.04 | H26: =Assumptions!B43 -> 0.04 | I26: =Assumptions!B43 -> 0.04 | J26: =Assumptions!B43 -> 0.04 | K26: =Assumptions!B43 -> 0.04
A27: Engaged Users / Month | B27: =B25*B26 -> 20000 | C27: =C25*C26 -> 36000 | D27: =D25*D26 -> 60000 | E27: =E25*E26 -> 76000 | F27: =F25*F26 -> 100000 | G27: =G25*G26 -> 110000 | H27: =H25*H26 -> 120000 | I27: =I25*I26 -> 130000 | ... K27: =K25*K26 -> 140000
A28: Clickthrough Rate | B28: =Assumptions!B44 -> 0.02 | C28: =Assumptions!B44 -> 0.02 | D28: =Assumptions!B44 -> 0.02 | E28: =Assumptions!B44 -> 0.02 | F28: =Assumptions!B44 -> 0.02 | G28: =Assumptions!B44 -> 0.02 | H28: =Assumptions!B44 -> 0.02 | I28: =Assumptions!B44 -> 0.02 | J28: =Assumptions!B44 -> 0.02 | K28: =Assumptions!B44 -> 0.02
A29: Monthly Clicks to Website | B29: =B27*B28 -> 400 | C29: =C27*C28 -> 720 | D29: =D27*D28 -> 1200 | E29: =E27*E28 -> 1520 | F29: =F27*F28 -> 2000 | G29: =G27*G28 -> 2200 | H29: =H27*H28 -> 2400 | I29: =I27*I28 -> 2600 | ... K29: =K27*K28 -> 2800
A30: Inquiry Conversion Rate | B30: =Assumptions!B45 -> 0.08 | C30: =Assumptions!B45 -> 0.08 | D30: =Assumptions!B45 -> 0.08 | E30: =Assumptions!B45 -> 0.08 | F30: =Assumptions!B45 -> 0.08 | G30: =Assumptions!B45 -> 0.08 | H30: =Assumptions!B45 -> 0.08 | I30: =Assumptions!B45 -> 0.08 | J30: =Assumptions!B45 -> 0.08 | K30: =Assumptions!B45 -> 0.08
A31: Monthly Inquiries | B31: =B29*B30 -> 32 | C31: =C29*C30 -> 57.6 | D31: =D29*D30 -> 96 | E31: =E29*E30 -> 121.6 | F31: =F29*F30 -> 160 | G31: =G29*G30 -> 176 | H31: =H29*H30 -> 192 | I31: =I29*I30 -> 208 | ... K31: =K29*K30 -> 224
A32: Booking Conversion Rate | B32: =Assumptions!B46 -> 0.25 | C32: =Assumptions!B46 -> 0.25 | D32: =Assumptions!B46 -> 0.25 | E32: =Assumptions!B46 -> 0.25 | F32: =Assumptions!B46 -> 0.25 | G32: =Assumptions!B46 -> 0.25 | H32: =Assumptions!B46 -> 0.25 | I32: =Assumptions!B46 -> 0.25 | J32: =Assumptions!B46 -> 0.25 | K32: =Assumptions!B46 -> 0.25
A33: Monthly Bookings from Creators | B33: =B31*B32 -> 8 | C33: =C31*C32 -> 14.4 | D33: =D31*D32 -> 24 | E33: =E31*E32 -> 30.4 | F33: =F31*F32 -> 40 | G33: =G31*G32 -> 44 | H33: =H31*H32 -> 48 | I33: =I31*I32 -> 52 | ... K33: =K31*K32 -> 56
A34: Annual Bookings from Creators | B34: =B33*12 -> 96 | C34: =C33*12 -> 172.8 | D34: =D33*12 -> 288 | E34: =E33*12 -> 364.8 | F34: =F33*12 -> 480 | G34: =G33*12 -> 528 | H34: =H33*12 -> 576 | I34: =I33*12 -> 624 | ... K34: =K33*12 -> 672
A35: Avg Lesson Revenue per Booking ($) | B35: =B13 -> 85 | C35: =C13 -> 87.55 | D35: =D13 -> 90.1765 | E35: =E13 -> 92.881795 | F35: =F13 -> 95.668249 | G35: =G13 -> 98.538296 | H35: =H13 -> 101.49445 | I35: =I13 -> 104.53928 | ... K35: =K13 -> 110.90572
A36: Platform Rev from Creator Bookings ($) | B36: =B34*B35*Assumptions!B29 -> 979.2 | C36: =C34*C35*Assumptions!B29 -> 1815.4368 | D36: =D34*D35*Assumptions!B29 -> 3116.4998 | E36: =E34*E35*Assumptions!B29 -> 4065.9935 | F36: =F34*F35*Assumptions!B29 -> 5510.4911 | G36: =G34*G35*Assumptions!B29 -> 6243.3865 | H36: =H34*H35*Assumptions!B29 -> 7015.2961 | I36: =I34*I35*Assumptions!B29 -> 7827.9012 | J36: =J34*J35*Assumptions!B29 -> 8434.8646 | K36: =K34*K35*Assumptions!B29 -> 8943.4373
A37: Brand Partnership Rev ($) | B37: =0 -> 0 | C37: =0 -> 0 | D37: =D23*2000 -> 60000 | E37: =E23*3000 -> 114000 | F37: =F23*4000 -> 200000 | G37: =G23*5000 -> 275000 | H37: =H23*6000 -> 360000 | I37: =I23*7000 -> 455000 | J37: =J23*8000 -> 544000 | K37: =K23*10000 -> 700000
A38: TOTAL CREATOR NETWORK REVENUE ($) | B38: =B36+B37 -> 979.2 | C38: =C36+C37 -> 1815.4368 | D38: =D36+D37 -> 63116.5 | E38: =E36+E37 -> 118065.99 | F38: =F36+F37 -> 205510.49 | G38: =G36+G37 -> 281243.39 | H38: =H36+H37 -> 367015.3 | I38: =I36+I37 -> 462827.9 | ... K38: =K36+K37 -> 708943.44
A40: C. TOPGOLF / VENUE PARTNERSHIPS
A41: Active Venue Partners | B41: 2 | C41: 3 | D41: 5 | E41: 6 | F41: 8 | G41: 8 | H41: 8 | I41: 8 | J41: 8 | K41: 8
A42: Avg Annual Foot Traffic per Venue | B42: =Assumptions!B57 -> 500000 | C42: =Assumptions!B57 -> 500000 | D42: =Assumptions!B57 -> 500000 | E42: =Assumptions!B57 -> 500000 | F42: =Assumptions!B57 -> 500000 | G42: =Assumptions!B57 -> 500000 | H42: =Assumptions!B57 -> 500000 | I42: =Assumptions!B57 -> 500000 | J42: =Assumptions!B57 -> 500000 | K42: =Assumptions!B57 -> 500000
A43: Total Venue Traffic | B43: =B41*B42 -> 1000000 | C43: =C41*C42 -> 1500000 | D43: =D41*D42 -> 2500000 | E43: =E41*E42 -> 3000000 | F43: =F41*F42 -> 4000000 | G43: =G41*G42 -> 4000000 | H43: =H41*H42 -> 4000000 | I43: =I41*I42 -> 4000000 | ... K43: =K41*K42 -> 4000000
A44: % Exposed to PGA Content | B44: =Assumptions!B58 -> 0.3 | C44: =Assumptions!B58 -> 0.3 | D44: =Assumptions!B58 -> 0.3 | E44: =Assumptions!B58 -> 0.3 | F44: =Assumptions!B58 -> 0.3 | G44: =Assumptions!B58 -> 0.3 | H44: =Assumptions!B58 -> 0.3 | I44: =Assumptions!B58 -> 0.3 | J44: =Assumptions!B58 -> 0.3 | K44: =Assumptions!B58 -> 0.3
A45: Exposed Users | B45: =B43*B44 -> 300000 | C45: =C43*C44 -> 450000 | D45: =D43*D44 -> 750000 | E45: =E43*E44 -> 900000 | F45: =F43*F44 -> 1200000 | G45: =G43*G44 -> 1200000 | H45: =H43*H44 -> 1200000 | I45: =I43*I44 -> 1200000 | ... K45: =K43*K44 -> 1200000
A46: QR Scan / Engagement Rate | B46: =Assumptions!B59 -> 0.02 | C46: =Assumptions!B59 -> 0.02 | D46: =Assumptions!B59 -> 0.02 | E46: =Assumptions!B59 -> 0.02 | F46: =Assumptions!B59 -> 0.02 | G46: =Assumptions!B59 -> 0.02 | H46: =Assumptions!B59 -> 0.02 | I46: =Assumptions!B59 -> 0.02 | J46: =Assumptions!B59 -> 0.02 | K46: =Assumptions!B59 -> 0.02
A47: Scans / Engagements | B47: =B45*B46 -> 6000 | C47: =C45*C46 -> 9000 | D47: =D45*D46 -> 15000 | E47: =E45*E46 -> 18000 | F47: =F45*F46 -> 24000 | G47: =G45*G46 -> 24000 | H47: =H45*H46 -> 24000 | I47: =I45*I46 -> 24000 | ... K47: =K45*K46 -> 24000
A48: Site Visit Rate (from scan) | B48: =Assumptions!B60 -> 0.4 | C48: =Assumptions!B60 -> 0.4 | D48: =Assumptions!B60 -> 0.4 | E48: =Assumptions!B60 -> 0.4 | F48: =Assumptions!B60 -> 0.4 | G48: =Assumptions!B60 -> 0.4 | H48: =Assumptions!B60 -> 0.4 | I48: =Assumptions!B60 -> 0.4 | J48: =Assumptions!B60 -> 0.4 | K48: =Assumptions!B60 -> 0.4
A49: Site Visits from Venues | B49: =B47*B48 -> 2400 | C49: =C47*C48 -> 3600 | D49: =D47*D48 -> 6000 | E49: =E47*E48 -> 7200 | F49: =F47*F48 -> 9600 | G49: =G47*G48 -> 9600 | H49: =H47*H48 -> 9600 | I49: =I47*I48 -> 9600 | ... K49: =K47*K48 -> 9600
A50: Booking Conversion Rate | B50: =Assumptions!B61 -> 0.05 | C50: =Assumptions!B61 -> 0.05 | D50: =Assumptions!B61 -> 0.05 | E50: =Assumptions!B61 -> 0.05 | F50: =Assumptions!B61 -> 0.05 | G50: =Assumptions!B61 -> 0.05 | H50: =Assumptions!B61 -> 0.05 | I50: =Assumptions!B61 -> 0.05 | J50: =Assumptions!B61 -> 0.05 | K50: =Assumptions!B61 -> 0.05
A51: Annual Bookings from Venues | B51: =B49*B50 -> 120 | C51: =C49*C50 -> 180 | D51: =D49*D50 -> 300 | E51: =E49*E50 -> 360 | F51: =F49*F50 -> 480 | G51: =G49*G50 -> 480 | H51: =H49*H50 -> 480 | I51: =I49*I50 -> 480 | ... K51: =K49*K50 -> 480
A52: Avg Lesson Rev per Booking ($) | B52: =B13 -> 85 | C52: =C13 -> 87.55 | D52: =D13 -> 90.1765 | E52: =E13 -> 92.881795 | F52: =F13 -> 95.668249 | G52: =G13 -> 98.538296 | H52: =H13 -> 101.49445 | I52: =I13 -> 104.53928 | ... K52: =K13 -> 110.90572
A53: Platform Rev from Venue Bookings ($) | B53: =B51*B52*Assumptions!B29 -> 1224 | C53: =C51*C52*Assumptions!B29 -> 1891.08 | D53: =D51*D52*Assumptions!B29 -> 3246.354 | E53: =E51*E52*Assumptions!B29 -> 4012.4935 | F53: =F51*F52*Assumptions!B29 -> 5510.4911 | G53: =G51*G52*Assumptions!B29 -> 5675.8059 | H53: =H51*H52*Assumptions!B29 -> 5846.08 | I53: =I51*I52*Assumptions!B29 -> 6021.4624 | J53: =J51*J52*Assumptions!B29 -> 6202.1063 | K53: =K51*K52*Assumptions!B29 -> 6388.1695
A54: Partnership Fee Revenue ($) | B54: =B41*Assumptions!B62 -> 50000 | C54: =C41*Assumptions!B62 -> 75000 | D54: =D41*Assumptions!B62 -> 125000 | E54: =E41*Assumptions!B62 -> 150000 | F54: =F41*Assumptions!B62 -> 200000 | G54: =G41*Assumptions!B62 -> 200000 | H54: =H41*Assumptions!B62 -> 200000 | I54: =I41*Assumptions!B62 -> 200000 | J54: =J41*Assumptions!B62 -> 200000 | K54: =K41*Assumptions!B62 -> 200000
A55: Event Revenue at Venues ($) | B55: =B41*Assumptions!B63 -> 80000 | C55: =C41*Assumptions!B63 -> 120000 | D55: =D41*Assumptions!B63 -> 200000 | E55: =E41*Assumptions!B63 -> 240000 | F55: =F41*Assumptions!B63 -> 320000 | G55: =G41*Assumptions!B63 -> 320000 | H55: =H41*Assumptions!B63 -> 320000 | I55: =I41*Assumptions!B63 -> 320000 | J55: =J41*Assumptions!B63 -> 320000 | K55: =K41*Assumptions!B63 -> 320000
A56: TOTAL VENUE PARTNERSHIP REVENUE ($) | B56: =B53+B54+B55 -> 131224 | C56: =C53+C54+C55 -> 196891.08 | D56: =D53+D54+D55 -> 328246.35 | E56: =E53+E54+E55 -> 394012.49 | F56: =F53+F54+F55 -> 525510.49 | G56: =G53+G54+G55 -> 525675.81 | H56: =H53+H54+H55 -> 525846.08 | I56: =I53+I54+I55 -> 526021.46 | ... K56: =K53+K54+K55 -> 526388.17
A58: D. CORPORATE GOLF PROGRAMS
A59: Active Corporate Clients | B59: 5 | C59: 12 | D59: 20 | E59: 30 | F59: 45 | G59: 52 | H59: 58 | I59: 65 | J59: 72 | K59: 80
A60: Events per Client per Year | B60: =Assumptions!B73 -> 4 | C60: =Assumptions!B73 -> 4 | D60: =Assumptions!B73 -> 4 | E60: =Assumptions!B73 -> 4 | F60: =Assumptions!B73 -> 4 | G60: =Assumptions!B73 -> 4 | H60: =Assumptions!B73 -> 4 | I60: =Assumptions!B73 -> 4 | J60: =Assumptions!B73 -> 4 | K60: =Assumptions!B73 -> 4
A61: Total Annual Events | B61: =B59*B60 -> 20 | C61: =C59*C60 -> 48 | D61: =D59*D60 -> 80 | E61: =E59*E60 -> 120 | F61: =F59*F60 -> 180 | G61: =G59*G60 -> 208 | H61: =H59*H60 -> 232 | I61: =I59*I60 -> 260 | ... K61: =K59*K60 -> 320
A62: Avg Revenue per Event ($) | B62: =Assumptions!B74 -> 8000 | C62: =Assumptions!B74 -> 8000 | D62: =Assumptions!B74 -> 8000 | E62: =Assumptions!B74 -> 8000 | F62: =Assumptions!B74 -> 8000 | G62: =Assumptions!B74 -> 8000 | H62: =Assumptions!B74 -> 8000 | I62: =Assumptions!B74 -> 8000 | J62: =Assumptions!B74 -> 8000 | K62: =Assumptions!B74 -> 8000
A63: Total Event Revenue ($) | B63: =B61*B62 -> 160000 | C63: =C61*C62 -> 384000 | D63: =D61*D62 -> 640000 | E63: =E61*E62 -> 960000 | F63: =F61*F62 -> 1440000 | G63: =G61*G62 -> 1664000 | H63: =H61*H62 -> 1856000 | I63: =I61*I62 -> 2080000 | ... K63: =K61*K62 -> 2560000
A64: % Clients on Retainer | B64: =Assumptions!B76 -> 0.3 | C64: =Assumptions!B76 -> 0.3 | D64: =Assumptions!B76 -> 0.3 | E64: =Assumptions!B76 -> 0.3 | F64: =Assumptions!B76 -> 0.3 | G64: =Assumptions!B76 -> 0.3 | H64: =Assumptions!B76 -> 0.3 | I64: =Assumptions!B76 -> 0.3 | J64: =Assumptions!B76 -> 0.3 | K64: =Assumptions!B76 -> 0.3
A65: Retainer Clients | B65: =B59*B64 -> 1.5 | C65: =C59*C64 -> 3.6 | D65: =D59*D64 -> 6 | E65: =E59*E64 -> 9 | F65: =F59*F64 -> 13.5 | G65: =G59*G64 -> 15.6 | H65: =H59*H64 -> 17.4 | I65: =I59*I64 -> 19.5 | ... K65: =K59*K64 -> 24
A66: Annual Retainer Revenue ($) | B66: =B65*Assumptions!B75 -> 22500 | C66: =C65*Assumptions!B75 -> 54000 | D66: =D65*Assumptions!B75 -> 90000 | E66: =E65*Assumptions!B75 -> 135000 | F66: =F65*Assumptions!B75 -> 202500 | G66: =G65*Assumptions!B75 -> 234000 | H66: =H65*Assumptions!B75 -> 261000 | I66: =I65*Assumptions!B75 -> 292500 | J66: =J65*Assumptions!B75 -> 324000 | K66: =K65*Assumptions!B75 -> 360000
A67: % Clients Sponsoring | B67: =Assumptions!B78 -> 0.2 | C67: =Assumptions!B78 -> 0.2 | D67: =Assumptions!B78 -> 0.2 | E67: =Assumptions!B78 -> 0.2 | F67: =Assumptions!B78 -> 0.2 | G67: =Assumptions!B78 -> 0.2 | H67: =Assumptions!B78 -> 0.2 | I67: =Assumptions!B78 -> 0.2 | J67: =Assumptions!B78 -> 0.2 | K67: =Assumptions!B78 -> 0.2
A68: Sponsoring Clients | B68: =B59*B67 -> 1 | C68: =C59*C67 -> 2.4 | D68: =D59*D67 -> 4 | E68: =E59*E67 -> 6 | F68: =F59*F67 -> 9 | G68: =G59*G67 -> 10.4 | H68: =H59*H67 -> 11.6 | I68: =I59*I67 -> 13 | ... K68: =K59*K67 -> 16
A69: Sponsorship Revenue ($) | B69: =B68*Assumptions!B77 -> 5000 | C69: =C68*Assumptions!B77 -> 12000 | D69: =D68*Assumptions!B77 -> 20000 | E69: =E68*Assumptions!B77 -> 30000 | F69: =F68*Assumptions!B77 -> 45000 | G69: =G68*Assumptions!B77 -> 52000 | H69: =H68*Assumptions!B77 -> 58000 | I69: =I68*Assumptions!B77 -> 65000 | J69: =J68*Assumptions!B77 -> 72000 | K69: =K68*Assumptions!B77 -> 80000
A70: Upsell Revenue (25% of event rev, Y2+) ($) | B70: =0 -> 0 | C70: =C63*Assumptions!B82 -> 96000 | D70: =D63*Assumptions!B82 -> 160000 | E70: =E63*Assumptions!B82 -> 240000 | F70: =F63*Assumptions!B82 -> 360000 | G70: =G63*Assumptions!B82 -> 416000 | H70: =H63*Assumptions!B82 -> 464000 | I70: =I63*Assumptions!B82 -> 520000 | J70: =J63*Assumptions!B82 -> 576000 | K70: =K63*Assumptions!B82 -> 640000
A71: TOTAL CORPORATE REVENUE ($) | B71: =B63+B66+B69+B70 -> 187500 | C71: =C63+C66+C69+C70 -> 546000 | D71: =D63+D66+D69+D70 -> 910000 | E71: =E63+E66+E69+E70 -> 1365000 | F71: =F63+F66+F69+F70 -> 2047500 | G71: =G63+G66+G69+G70 -> 2366000 | H71: =H63+H66+H69+H70 -> 2639000 | I71: =I63+I66+I69+I70 -> 2957500 | ... K71: =K63+K66+K69+K70 -> 3640000
A73: CONSOLIDATED REVENUE SUMMARY
A74: Learn Golf Platform Revenue | B74: =B20 -> 265097.45 | C74: =C20 -> 460846.94 | D74: =D20 -> 768382.19 | E74: =E20 -> 1000032.2 | F74: =F20 -> 1352494.4 | G74: =G20 -> 1503162.3 | H74: =H20 -> 1665684 | I74: =I20 -> 1832755.8 | ... K74: =K20 -> 2066507
A75: Creator Network Revenue | B75: =B38 -> 979.2 | C75: =C38 -> 1815.4368 | D75: =D38 -> 63116.5 | E75: =E38 -> 118065.99 | F75: =F38 -> 205510.49 | G75: =G38 -> 281243.39 | H75: =H38 -> 367015.3 | I75: =I38 -> 462827.9 | ... K75: =K38 -> 708943.44
A76: Venue Partnership Revenue | B76: =B56 -> 131224 | C76: =C56 -> 196891.08 | D76: =D56 -> 328246.35 | E76: =E56 -> 394012.49 | F76: =F56 -> 525510.49 | G76: =G56 -> 525675.81 | H76: =H56 -> 525846.08 | I76: =I56 -> 526021.46 | ... K76: =K56 -> 526388.17
A77: Corporate Program Revenue | B77: =B71 -> 187500 | C77: =C71 -> 546000 | D77: =D71 -> 910000 | E77: =E71 -> 1365000 | F77: =F71 -> 2047500 | G77: =G71 -> 2366000 | H77: =H71 -> 2639000 | I77: =I71 -> 2957500 | ... K77: =K71 -> 3640000
A78: TOTAL REVENUE | B78: =B74+B75+B76+B77 -> 584800.65 | C78: =C74+C75+C76+C77 -> 1205553.5 | D78: =D74+D75+D76+D77 -> 2069745 | E78: =E74+E75+E76+E77 -> 2877110.7 | F78: =F74+F75+F76+F77 -> 4131015.4 | G78: =G74+G75+G76+G77 -> 4676081.5 | H78: =H74+H75+H76+H77 -> 5197545.4 | I78: =I74+I75+I76+I77 -> 5779105.2 | ... K78: =K74+K75+K76+K77 -> 6941838.6
A80: Revenue Mix — Platform | B80: =IF(B78=0,0,B74/B78) -> 0.45331251 | C80: =IF(C78=0,0,C74/C78) -> 0.38227002 | D80: =IF(D78=0,0,D74/D78) -> 0.37124485 | E80: =IF(E78=0,0,E74/E78) -> 0.34758211 | F80: =IF(F78=0,0,F74/F78) -> 0.3274 | G80: =IF(G78=0,0,G74/G78) -> 0.32145768 | H80: =IF(H78=0,0,H74/H78) -> 0.32047512 | I80: =IF(I78=0,0,I74/I78) -> 0.31713488 | ... K80: =IF(K78=0,0,K74/K78) -> 0.29768871
A81: Revenue Mix — Creator | B81: =IF(B78=0,0,B75/B78) -> 0.0016744167 | C81: =IF(C78=0,0,C75/C78) -> 0.0015058949 | D81: =IF(D78=0,0,D75/D78) -> 0.030494819 | E81: =IF(E78=0,0,E75/E78) -> 0.041036306 | F81: =IF(F78=0,0,F75/F78) -> 0.049748178 | G81: =IF(G78=0,0,G75/G78) -> 0.060145099 | H81: =IF(H78=0,0,H75/H78) -> 0.070613197 | I81: =IF(I78=0,0,I75/I78) -> 0.08008643 | ... K81: =IF(K78=0,0,K75/K78) -> 0.10212618
A82: Revenue Mix — Venue | B82: =IF(B78=0,0,B76/B78) -> 0.224391 | C82: =IF(C78=0,0,C76/C78) -> 0.16332007 | D82: =IF(D78=0,0,D76/D78) -> 0.15859265 | E82: =IF(E78=0,0,E76/E78) -> 0.13694728 | F82: =IF(F78=0,0,F76/F78) -> 0.12721097 | G82: =IF(G78=0,0,G76/G78) -> 0.11241802 | H82: =IF(H78=0,0,H76/H78) -> 0.101172 | I82: =IF(I78=0,0,I76/I78) -> 0.091021265 | ... K82: =IF(K78=0,0,K76/K78) -> 0.07582835
A83: Revenue Mix — Corporate | B83: =IF(B78=0,0,B77/B78) -> 0.32062208 | C83: =IF(C78=0,0,C77/C78) -> 0.45290401 | D83: =IF(D78=0,0,D77/D78) -> 0.43966768 | E83: =IF(E78=0,0,E77/E78) -> 0.4744343 | F83: =IF(F78=0,0,F77/F78) -> 0.49564085 | G83: =IF(G78=0,0,G77/G78) -> 0.5059792 | H83: =IF(H78=0,0,H77/H78) -> 0.50773967 | I83: =IF(I78=0,0,I77/I78) -> 0.51175743 | ... K83: =IF(K78=0,0,K77/K78) -> 0.52435676
A85: YoY Revenue Growth | B85: N/A | C85: =IF(B78=0,0,(C78-B78)/B78) -> 1.0614776 | D85: =IF(C78=0,0,(D78-C78)/C78) -> 0.7168422 | E85: =IF(D78=0,0,(E78-D78)/D78) -> 0.39007975 | F85: =IF(E78=0,0,(F78-E78)/E78) -> 0.43582082 | G85: =IF(F78=0,0,(G78-F78)/F78) -> 0.13194482 | H85: =IF(G78=0,0,(H78-G78)/G78) -> 0.11151727 | I85: =IF(H78=0,0,(I78-H78)/H78) -> 0.11189124 | J85: =IF(I78=0,0,(J78-I78)/I78) -> 0.088024417 | K85: =IF(J78=0,0,(K78-J78)/J78) -> 0.10401576
A130: E. CUSTOMER COUNT & NET RETENTION MODEL
A131: CONSUMER CUSTOMERS (Lesson Buyers)
A132: Beginning Customers | B132: 0 | C132: =B138 -> 4096.8 | D132: =C138 -> 9688.56 | E132: =D138 -> 17718.792 | F132: =E138 -> 26063.954 | G132: =F138 -> 36021.568 | H132: =G138 -> 44333.498 | I132: =H138 -> 51493.448 | J132: =I138 -> 57847.014 | K132: =J138 -> 62840.75
A133: New Customers — Platform Direct | B133: =B12/6 -> 3880.8 | C133: =C12/6 -> 6468 | D133: =D12/6 -> 10348.8 | E133: =E12/6 -> 12936 | F133: =F12/6 -> 16816.8 | G133: =G12/6 -> 18110.4 | H133: =H12/6 -> 19404 | I133: =I12/6 -> 20697.6 | ... K133: =K12/6 -> 21991.2
A134: New Customers — Creator Channel | B134: =B34 -> 96 | C134: =C34 -> 172.8 | D134: =D34 -> 288 | E134: =E34 -> 364.8 | F134: =F34 -> 480 | G134: =G34 -> 528 | H134: =H34 -> 576 | I134: =I34 -> 624 | ... K134: =K34 -> 672
A135: New Customers — Venue Channel | B135: =B51 -> 120 | C135: =C51 -> 180 | D135: =D51 -> 300 | E135: =E51 -> 360 | F135: =F51 -> 480 | G135: =G51 -> 480 | H135: =H51 -> 480 | I135: =I51 -> 480 | ... K135: =K51 -> 480
A136: Total New Customers | B136: =B133+B134+B135 -> 4096.8 | C136: =C133+C134+C135 -> 6820.8 | D136: =D133+D134+D135 -> 10936.8 | E136: =E133+E134+E135 -> 13660.8 | F136: =F133+F134+F135 -> 17776.8 | G136: =G133+G134+G135 -> 19118.4 | H136: =H133+H134+H135 -> 20460 | I136: =I133+I134+I135 -> 21801.6 | ... K136: =K133+K134+K135 -> 23143.2
A137: Churned Customers (30% annual churn) | B137: =-B132*Assumptions!B139 -> 0 | C137: =-C132*Assumptions!B139 -> -1229.04 | D137: =-D132*Assumptions!B139 -> -2906.568 | E137: =-E132*Assumptions!B139 -> -5315.6376 | F137: =-F132*Assumptions!B139 -> -7819.1863 | G137: =-G132*Assumptions!B139 -> -10806.47 | H137: =-H132*Assumptions!B139 -> -13300.049 | I137: =-I132*Assumptions!B139 -> -15448.035 | J137: =-J132*Assumptions!B139 -> -17354.104 | K137: =-K132*Assumptions!B139 -> -18852.225
A138: Ending Customers | B138: =B132+B136+B137 -> 4096.8 | C138: =C132+C136+C137 -> 9688.56 | D138: =D132+D136+D137 -> 17718.792 | E138: =E132+E136+E137 -> 26063.954 | F138: =F132+F136+F137 -> 36021.568 | G138: =G132+G136+G137 -> 44333.498 | H138: =H132+H136+H137 -> 51493.448 | I138: =I132+I136+I137 -> 57847.014 | ... K138: =K132+K136+K137 -> 67131.725
A139: Net Customer Growth | B139: =B138-B132 -> 4096.8 | C139: =C138-C132 -> 5591.76 | D139: =D138-D132 -> 8030.232 | E139: =E138-E132 -> 8345.1624 | F139: =F138-F132 -> 9957.6137 | G139: =G138-G132 -> 8311.9296 | H139: =H138-H132 -> 7159.9507 | I139: =I138-I132 -> 6353.5655 | ... K139: =K138-K132 -> 4290.9751
A140: Avg Lessons per Customer | B140: =IF(B138=0,0,B12/B138) -> 5.6836555 | C140: =IF(C138=0,0,C12/C138) -> 4.0055488 | D140: =IF(D138=0,0,D12/D138) -> 3.5043472 | E140: =IF(E138=0,0,E12/E138) -> 2.9779058 | F140: =IF(F138=0,0,F12/F138) -> 2.8011218 | G140: =IF(G138=0,0,G12/G138) -> 2.4510225 | H140: =IF(H138=0,0,H12/H138) -> 2.2609478 | I140: =IF(I138=0,0,I12/I138) -> 2.1467936 | ... K140: =IF(K138=0,0,K12/K138) -> 1.9654969
A141: Total Customer-Driven Lessons | B141: =B12 -> 23284.8 | C141: =C12 -> 38808 | D141: =D12 -> 62092.8 | E141: =E12 -> 77616 | F141: =F12 -> 100900.8 | G141: =G12 -> 108662.4 | H141: =H12 -> 116424 | I141: =I12 -> 124185.6 | ... K141: =K12 -> 131947.2
A143: CORPORATE CLIENTS
A144: Beginning Clients | B144: 0 | C144: =B147 -> 5 | D144: =C147 -> 12 | E144: =D147 -> 20 | F144: =E147 -> 30 | G144: =F147 -> 45 | H144: =G147 -> 52 | I144: =H147 -> 58 | J144: =I147 -> 65 | K144: =J147 -> 72
A145: New Clients Won | B145: =B59-B144+B144*Assumptions!B140 -> 5 | C145: =C59-C144+C144*Assumptions!B140 -> 8 | D145: =D59-D144+D144*Assumptions!B140 -> 10.4 | E145: =E59-E144+E144*Assumptions!B140 -> 14 | F145: =F59-F144+F144*Assumptions!B140 -> 21 | G145: =G59-G144+G144*Assumptions!B140 -> 16 | H145: =H59-H144+H144*Assumptions!B140 -> 16.4 | I145: =I59-I144+I144*Assumptions!B140 -> 18.6 | J145: =J59-J144+J144*Assumptions!B140 -> 20 | K145: =K59-K144+K144*Assumptions!B140 -> 22.4
A146: Churned Clients (20% annual) | B146: =-B144*Assumptions!B140 -> 0 | C146: =-C144*Assumptions!B140 -> -1 | D146: =-D144*Assumptions!B140 -> -2.4 | E146: =-E144*Assumptions!B140 -> -4 | F146: =-F144*Assumptions!B140 -> -6 | G146: =-G144*Assumptions!B140 -> -9 | H146: =-H144*Assumptions!B140 -> -10.4 | I146: =-I144*Assumptions!B140 -> -11.6 | J146: =-J144*Assumptions!B140 -> -13 | K146: =-K144*Assumptions!B140 -> -14.4
A147: Ending Clients | B147: =B144+B145+B146 -> 5 | C147: =C144+C145+C146 -> 12 | D147: =D144+D145+D146 -> 20 | E147: =E144+E145+E146 -> 30 | F147: =F144+F145+F146 -> 45 | G147: =G144+G145+G146 -> 52 | H147: =H144+H145+H146 -> 58 | I147: =I144+I145+I146 -> 65 | ... K147: =K144+K145+K146 -> 80
A148: Net New Clients | B148: =B147-B144 -> 5 | C148: =C147-C144 -> 7 | D148: =D147-D144 -> 8 | E148: =E147-E144 -> 10 | F148: =F147-F144 -> 15 | G148: =G147-G144 -> 7 | H148: =H147-H144 -> 6 | I148: =I147-I144 -> 7 | ... K148: =K147-K144 -> 8
A149: Revenue per Client ($) | B149: =IF(B59=0,0,B71/B59) -> 37500 | C149: =IF(C59=0,0,C71/C59) -> 45500 | D149: =IF(D59=0,0,D71/D59) -> 45500 | E149: =IF(E59=0,0,E71/E59) -> 45500 | F149: =IF(F59=0,0,F71/F59) -> 45500 | G149: =IF(G59=0,0,G71/G59) -> 45500 | H149: =IF(H59=0,0,H71/H59) -> 45500 | I149: =IF(I59=0,0,I71/I59) -> 45500 | ... K149: =IF(K59=0,0,K71/K59) -> 45500

Sheet Cost Build
A1: OPERATING COST BUILD — 10 YEAR FORECAST
B2: Year 1 | C2: Year 2 | D2: Year 3 | E2: Year 4 | F2: Year 5 | G2: Year 6 | H2: Year 7 | I2: Year 8 | J2: Year 9 | K2: Year 10
A4: 1. COST OF REVENUE / DIRECT COSTS
A5: Platform Transaction Processing (3% of GMV) | B5: ='Revenue Build'!B14*0.03 -> 59376.24 | C5: ='Revenue Build'!C14*0.03 -> 101929.21 | D5: ='Revenue Build'!D14*0.03 -> 167979.34 | E5: ='Revenue Build'!E14*0.03 -> 216273.4 | F5: ='Revenue Build'!F14*0.03 -> 289590.09 | G5: ='Revenue Build'!G14*0.03 -> 321222.23 | H5: ='Revenue Build'!H14*0.03 -> 354491.68 | I5: ='Revenue Build'!I14*0.03 -> 389468.19 | ... K5: ='Revenue Build'!K14*0.03 -> 439010.98
A6: Creator Compensation | B6: ='Revenue Build'!B23*Assumptions!B47*12 -> 60000 | C6: ='Revenue Build'!C23*Assumptions!B47*12 -> 108000 | D6: ='Revenue Build'!D23*Assumptions!B47*12 -> 180000 | E6: ='Revenue Build'!E23*Assumptions!B47*12 -> 228000 | F6: ='Revenue Build'!F23*Assumptions!B47*12 -> 300000 | G6: ='Revenue Build'!G23*Assumptions!B47*12 -> 330000 | H6: ='Revenue Build'!H23*Assumptions!B47*12 -> 360000 | I6: ='Revenue Build'!I23*Assumptions!B47*12 -> 390000 | J6: ='Revenue Build'!J23*Assumptions!B47*12 -> 408000 | K6: ='Revenue Build'!K23*Assumptions!B47*12 -> 420000
A7: Creator Content Production Support | B7: ='Revenue Build'!B23*Assumptions!B48*12 -> 24000 | C7: ='Revenue Build'!C23*Assumptions!B48*12 -> 43200 | D7: ='Revenue Build'!D23*Assumptions!B48*12 -> 72000 | E7: ='Revenue Build'!E23*Assumptions!B48*12 -> 91200 | F7: ='Revenue Build'!F23*Assumptions!B48*12 -> 120000 | G7: ='Revenue Build'!G23*Assumptions!B48*12 -> 132000 | H7: ='Revenue Build'!H23*Assumptions!B48*12 -> 144000 | I7: ='Revenue Build'!I23*Assumptions!B48*12 -> 156000 | J7: ='Revenue Build'!J23*Assumptions!B48*12 -> 163200 | K7: ='Revenue Build'!K23*Assumptions!B48*12 -> 168000
A8: Creator Platform Management | B8: ='Revenue Build'!B23*Assumptions!B49*12 -> 12000 | C8: ='Revenue Build'!C23*Assumptions!B49*12 -> 21600 | D8: ='Revenue Build'!D23*Assumptions!B49*12 -> 36000 | E8: ='Revenue Build'!E23*Assumptions!B49*12 -> 45600 | F8: ='Revenue Build'!F23*Assumptions!B49*12 -> 60000 | G8: ='Revenue Build'!G23*Assumptions!B49*12 -> 66000 | H8: ='Revenue Build'!H23*Assumptions!B49*12 -> 72000 | I8: ='Revenue Build'!I23*Assumptions!B49*12 -> 78000 | J8: ='Revenue Build'!J23*Assumptions!B49*12 -> 81600 | K8: ='Revenue Build'!K23*Assumptions!B49*12 -> 84000
A9: Venue Activation Costs | B9: ='Revenue Build'!B41*Assumptions!B64 -> 30000 | C9: ='Revenue Build'!C41*Assumptions!B64 -> 45000 | D9: ='Revenue Build'!D41*Assumptions!B64 -> 75000 | E9: ='Revenue Build'!E41*Assumptions!B64 -> 90000 | F9: ='Revenue Build'!F41*Assumptions!B64 -> 120000 | G9: ='Revenue Build'!G41*Assumptions!B64 -> 120000 | H9: ='Revenue Build'!H41*Assumptions!B64 -> 120000 | I9: ='Revenue Build'!I41*Assumptions!B64 -> 120000 | J9: ='Revenue Build'!J41*Assumptions!B64 -> 120000 | K9: ='Revenue Build'!K41*Assumptions!B64 -> 120000
A10: Corporate Event Delivery (55% of event rev) | B10: ='Revenue Build'!B63*Assumptions!B80 -> 88000 | C10: ='Revenue Build'!C63*Assumptions!B80 -> 211200 | D10: ='Revenue Build'!D63*Assumptions!B80 -> 352000 | E10: ='Revenue Build'!E63*Assumptions!B80 -> 528000 | F10: ='Revenue Build'!F63*Assumptions!B80 -> 792000 | G10: ='Revenue Build'!G63*Assumptions!B80 -> 915200 | H10: ='Revenue Build'!H63*Assumptions!B80 -> 1020800 | I10: ='Revenue Build'!I63*Assumptions!B80 -> 1144000 | J10: ='Revenue Build'!J63*Assumptions!B80 -> 1267200 | K10: ='Revenue Build'!K63*Assumptions!B80 -> 1408000
A11: Direct Sales Commissions (5% of corp rev) | B11: ='Revenue Build'!B71*0.05 -> 9375 | C11: ='Revenue Build'!C71*0.05 -> 27300 | D11: ='Revenue Build'!D71*0.05 -> 45500 | E11: ='Revenue Build'!E71*0.05 -> 68250 | F11: ='Revenue Build'!F71*0.05 -> 102375 | G11: ='Revenue Build'!G71*0.05 -> 118300 | H11: ='Revenue Build'!H71*0.05 -> 131950 | I11: ='Revenue Build'!I71*0.05 -> 147875 | ... K11: ='Revenue Build'!K71*0.05 -> 182000
A12: Customer Service (volume-driven) | B12: ='Revenue Build'!B78*0.02 -> 11696.013 | C12: ='Revenue Build'!C78*0.02 -> 24111.069 | D12: ='Revenue Build'!D78*0.02 -> 41394.901 | E12: ='Revenue Build'!E78*0.02 -> 57542.214 | F12: ='Revenue Build'!F78*0.02 -> 82620.308 | G12: ='Revenue Build'!G78*0.02 -> 93521.63 | H12: ='Revenue Build'!H78*0.02 -> 103950.91 | I12: ='Revenue Build'!I78*0.02 -> 115582.1 | ... K12: ='Revenue Build'!K78*0.02 -> 138836.77
A13: TOTAL DIRECT COSTS | B13: =SUM(B5:B12) -> 294447.25 | C13: =SUM(C5:C12) -> 582340.28 | D13: =SUM(D5:D12) -> 969874.24 | E13: =SUM(E5:E12) -> 1324865.6 | F13: =SUM(F5:F12) -> 1866585.4 | G13: =SUM(G5:G12) -> 2096243.9 | H13: =SUM(H5:H12) -> 2307192.6 | I13: =SUM(I5:I12) -> 2540925.3 | ... K13: =SUM(K5:K12) -> 2959847.8
A15: 2. OPERATING EXPENSES (FIXED + SEMI-VARIABLE)
A16: HEADCOUNT COSTS
A17: CEO / Executive Director | B17: =Assumptions!B86*(1+Assumptions!B95)^0 -> 150000 | C17: =Assumptions!B86*(1+Assumptions!B95)^1 -> 154500 | D17: =Assumptions!B86*(1+Assumptions!B95)^2 -> 159135 | E17: =Assumptions!B86*(1+Assumptions!B95)^3 -> 163909.05 | F17: =Assumptions!B86*(1+Assumptions!B95)^4 -> 168826.32 | G17: =Assumptions!B86*(1+Assumptions!B95)^5 -> 173891.11 | H17: =Assumptions!B86*(1+Assumptions!B95)^6 -> 179107.84 | I17: =Assumptions!B86*(1+Assumptions!B95)^7 -> 184481.08 | J17: =Assumptions!B86*(1+Assumptions!B95)^8 -> 190015.51 | K17: =Assumptions!B86*(1+Assumptions!B95)^9 -> 195715.98
A18: VP Marketing / Growth | B18: =Assumptions!B87*(1+Assumptions!B95)^0 -> 120000 | C18: =Assumptions!B87*(1+Assumptions!B95)^1 -> 123600 | D18: =Assumptions!B87*(1+Assumptions!B95)^2 -> 127308 | E18: =Assumptions!B87*(1+Assumptions!B95)^3 -> 131127.24 | F18: =Assumptions!B87*(1+Assumptions!B95)^4 -> 135061.06 | G18: =Assumptions!B87*(1+Assumptions!B95)^5 -> 139112.89 | H18: =Assumptions!B87*(1+Assumptions!B95)^6 -> 143286.28 | I18: =Assumptions!B87*(1+Assumptions!B95)^7 -> 147584.86 | J18: =Assumptions!B87*(1+Assumptions!B95)^8 -> 152012.41 | K18: =Assumptions!B87*(1+Assumptions!B95)^9 -> 156572.78
A19: Partnership Sales Director | B19: =Assumptions!B88*(1+Assumptions!B95)^0 -> 110000 | C19: =Assumptions!B88*(1+Assumptions!B95)^1 -> 113300 | D19: =Assumptions!B88*(1+Assumptions!B95)^2 -> 116699 | E19: =Assumptions!B88*(1+Assumptions!B95)^3 -> 120199.97 | F19: =Assumptions!B88*(1+Assumptions!B95)^4 -> 123805.97 | G19: =Assumptions!B88*(1+Assumptions!B95)^5 -> 127520.15 | H19: =Assumptions!B88*(1+Assumptions!B95)^6 -> 131345.75 | I19: =Assumptions!B88*(1+Assumptions!B95)^7 -> 135286.13 | J19: =Assumptions!B88*(1+Assumptions!B95)^8 -> 139344.71 | K19: =Assumptions!B88*(1+Assumptions!B95)^9 -> 143525.05
A20: Content & Social Media Manager | B20: =Assumptions!B89*(1+Assumptions!B95)^0 -> 75000 | C20: =Assumptions!B89*(1+Assumptions!B95)^1 -> 77250 | D20: =Assumptions!B89*(1+Assumptions!B95)^2 -> 79567.5 | E20: =Assumptions!B89*(1+Assumptions!B95)^3 -> 81954.525 | F20: =Assumptions!B89*(1+Assumptions!B95)^4 -> 84413.161 | G20: =Assumptions!B89*(1+Assumptions!B95)^5 -> 86945.556 | H20: =Assumptions!B89*(1+Assumptions!B95)^6 -> 89553.922 | I20: =Assumptions!B89*(1+Assumptions!B95)^7 -> 92240.54 | J20: =Assumptions!B89*(1+Assumptions!B95)^8 -> 95007.756 | K20: =Assumptions!B89*(1+Assumptions!B95)^9 -> 97857.989
A21: Platform / Website Manager | B21: =Assumptions!B90*(1+Assumptions!B95)^0 -> 85000 | C21: =Assumptions!B90*(1+Assumptions!B95)^1 -> 87550 | D21: =Assumptions!B90*(1+Assumptions!B95)^2 -> 90176.5 | E21: =Assumptions!B90*(1+Assumptions!B95)^3 -> 92881.795 | F21: =Assumptions!B90*(1+Assumptions!B95)^4 -> 95668.249 | G21: =Assumptions!B90*(1+Assumptions!B95)^5 -> 98538.296 | H21: =Assumptions!B90*(1+Assumptions!B95)^6 -> 101494.45 | I21: =Assumptions!B90*(1+Assumptions!B95)^7 -> 104539.28 | J21: =Assumptions!B90*(1+Assumptions!B95)^8 -> 107675.46 | K21: =Assumptions!B90*(1+Assumptions!B95)^9 -> 110905.72
A22: Customer Support Specialist (Y2+) | B22: =0 -> 0 | C22: =Assumptions!B91*(1+Assumptions!B95)^1 -> 56650 | D22: =Assumptions!B91*(1+Assumptions!B95)^2 -> 58349.5 | E22: =Assumptions!B91*(1+Assumptions!B95)^3 -> 60099.985 | F22: =Assumptions!B91*(1+Assumptions!B95)^4 -> 61902.985 | G22: =Assumptions!B91*(1+Assumptions!B95)^5 -> 63760.074 | H22: =Assumptions!B91*(1+Assumptions!B95)^6 -> 65672.876 | I22: =Assumptions!B91*(1+Assumptions!B95)^7 -> 67643.063 | J22: =Assumptions!B91*(1+Assumptions!B95)^8 -> 69672.354 | K22: =Assumptions!B91*(1+Assumptions!B95)^9 -> 71762.525
A23: Event Coordinator (Y2+) | B23: =0 -> 0 | C23: =Assumptions!B92*(1+Assumptions!B95)^1 -> 61800 | D23: =Assumptions!B92*(1+Assumptions!B95)^2 -> 63654 | E23: =Assumptions!B92*(1+Assumptions!B95)^3 -> 65563.62 | F23: =Assumptions!B92*(1+Assumptions!B95)^4 -> 67530.529 | G23: =Assumptions!B92*(1+Assumptions!B95)^5 -> 69556.444 | H23: =Assumptions!B92*(1+Assumptions!B95)^6 -> 71643.138 | I23: =Assumptions!B92*(1+Assumptions!B95)^7 -> 73792.432 | J23: =Assumptions!B92*(1+Assumptions!B95)^8 -> 76006.205 | K23: =Assumptions!B92*(1+Assumptions!B95)^9 -> 78286.391
A24: Sales Associate — Corporate (Y2+) | B24: =0 -> 0 | C24: =Assumptions!B93*(1+Assumptions!B95)^1 -> 66950 | D24: =Assumptions!B93*(1+Assumptions!B95)^2 -> 68958.5 | E24: =Assumptions!B93*(1+Assumptions!B95)^3 -> 71027.255 | F24: =Assumptions!B93*(1+Assumptions!B95)^4 -> 73158.073 | G24: =Assumptions!B93*(1+Assumptions!B95)^5 -> 75352.815 | H24: =Assumptions!B93*(1+Assumptions!B95)^6 -> 77613.399 | I24: =Assumptions!B93*(1+Assumptions!B95)^7 -> 79941.801 | J24: =Assumptions!B93*(1+Assumptions!B95)^8 -> 82340.055 | K24: =Assumptions!B93*(1+Assumptions!B95)^9 -> 84810.257
A25: Additional Hires (Y4+) | B25: =0*70000*(1+Assumptions!B95)^0 -> 0 | C25: =0*70000*(1+Assumptions!B95)^1 -> 0 | D25: =0*70000*(1+Assumptions!B95)^2 -> 0 | E25: =2*70000*(1+Assumptions!B95)^3 -> 152981.78 | F25: =2*70000*(1+Assumptions!B95)^4 -> 157571.23 | G25: =2*70000*(1+Assumptions!B95)^5 -> 162298.37 | H25: =4*70000*(1+Assumptions!B95)^6 -> 334334.64 | I25: =4*70000*(1+Assumptions!B95)^7 -> 344364.68 | J25: =6*70000*(1+Assumptions!B95)^8 -> 532043.43 | K25: =6*70000*(1+Assumptions!B95)^9 -> 548004.74
A26: Total Base Salaries | B26: =SUM(B17:B25) -> 540000 | C26: =SUM(C17:C25) -> 741600 | D26: =SUM(D17:D25) -> 763848 | E26: =SUM(E17:E25) -> 939745.22 | F26: =SUM(F17:F25) -> 967937.58 | G26: =SUM(G17:G25) -> 996975.7 | H26: =SUM(H17:H25) -> 1194052.3 | I26: =SUM(I17:I25) -> 1229873.9 | ... K26: =SUM(K17:K25) -> 1487441.4
A27: Benefits Load (25%) | B27: =B26*Assumptions!B94 -> 135000 | C27: =C26*Assumptions!B94 -> 185400 | D27: =D26*Assumptions!B94 -> 190962 | E27: =E26*Assumptions!B94 -> 234936.31 | F27: =F26*Assumptions!B94 -> 241984.39 | G27: =G26*Assumptions!B94 -> 249243.93 | H27: =H26*Assumptions!B94 -> 298513.07 | I27: =I26*Assumptions!B94 -> 307468.47 | J27: =J26*Assumptions!B94 -> 361029.47 | K27: =K26*Assumptions!B94 -> 371860.36
A28: TOTAL HEADCOUNT COST | B28: =B26+B27 -> 675000 | C28: =C26+C27 -> 927000 | D28: =D26+D27 -> 954810 | E28: =E26+E27 -> 1174681.5 | F28: =F26+F27 -> 1209922 | G28: =G26+G27 -> 1246219.6 | H28: =H26+H27 -> 1492565.4 | I28: =I26+I27 -> 1537342.3 | ... K28: =K26+K27 -> 1859301.8
A30: NON-HEADCOUNT OPEX
A31: Software / Platform Costs | B31: =Assumptions!B96*(1.05)^0 -> 60000 | C31: =Assumptions!B96*(1.05)^1 -> 63000 | D31: =Assumptions!B96*(1.05)^2 -> 66150 | E31: =Assumptions!B96*(1.05)^3 -> 69457.5 | F31: =Assumptions!B96*(1.05)^4 -> 72930.375 | G31: =Assumptions!B96*(1.05)^5 -> 76576.894 | H31: =Assumptions!B96*(1.05)^6 -> 80405.738 | I31: =Assumptions!B96*(1.05)^7 -> 84426.025 | J31: =Assumptions!B96*(1.05)^8 -> 88647.327 | K31: =Assumptions!B96*(1.05)^9 -> 93079.693
A32: Hosting & Maintenance | B32: =Assumptions!B97*(1.05)^0 -> 18000 | C32: =Assumptions!B97*(1.05)^1 -> 18900 | D32: =Assumptions!B97*(1.05)^2 -> 19845 | E32: =Assumptions!B97*(1.05)^3 -> 20837.25 | F32: =Assumptions!B97*(1.05)^4 -> 21879.112 | G32: =Assumptions!B97*(1.05)^5 -> 22973.068 | H32: =Assumptions!B97*(1.05)^6 -> 24121.722 | I32: =Assumptions!B97*(1.05)^7 -> 25327.808 | J32: =Assumptions!B97*(1.05)^8 -> 26594.198 | K32: =Assumptions!B97*(1.05)^9 -> 27923.908
A33: Content Production Budget | B33: =Assumptions!B98*(1.05)^0 -> 48000 | C33: =Assumptions!B98*(1.05)^1 -> 50400 | D33: =Assumptions!B98*(1.05)^2 -> 52920 | E33: =Assumptions!B98*(1.05)^3 -> 55566 | F33: =Assumptions!B98*(1.05)^4 -> 58344.3 | G33: =Assumptions!B98*(1.05)^5 -> 61261.515 | H33: =Assumptions!B98*(1.05)^6 -> 64324.591 | I33: =Assumptions!B98*(1.05)^7 -> 67540.82 | J33: =Assumptions!B98*(1.05)^8 -> 70917.861 | K33: =Assumptions!B98*(1.05)^9 -> 74463.754
A34: Marketing & Paid Ads | B34: =Assumptions!B99*(1.05)^0 -> 75000 | C34: =Assumptions!B99*(1.05)^1 -> 78750 | D34: =Assumptions!B99*(1.05)^2 -> 82687.5 | E34: =Assumptions!B99*(1.05)^3 -> 86821.875 | F34: =Assumptions!B99*(1.05)^4 -> 91162.969 | G34: =Assumptions!B99*(1.05)^5 -> 95721.117 | H34: =Assumptions!B99*(1.05)^6 -> 100507.17 | I34: =Assumptions!B99*(1.05)^7 -> 105532.53 | J34: =Assumptions!B99*(1.05)^8 -> 110809.16 | K34: =Assumptions!B99*(1.05)^9 -> 116349.62
A35: G&A / Office / Admin | B35: =Assumptions!B100*(1.05)^0 -> 40000 | C35: =Assumptions!B100*(1.05)^1 -> 42000 | D35: =Assumptions!B100*(1.05)^2 -> 44100 | E35: =Assumptions!B100*(1.05)^3 -> 46305 | F35: =Assumptions!B100*(1.05)^4 -> 48620.25 | G35: =Assumptions!B100*(1.05)^5 -> 51051.263 | H35: =Assumptions!B100*(1.05)^6 -> 53603.826 | I35: =Assumptions!B100*(1.05)^7 -> 56284.017 | J35: =Assumptions!B100*(1.05)^8 -> 59098.218 | K35: =Assumptions!B100*(1.05)^9 -> 62053.129
A36: Travel & Event Costs | B36: =Assumptions!B101*(1.05)^0 -> 30000 | C36: =Assumptions!B101*(1.05)^1 -> 31500 | D36: =Assumptions!B101*(1.05)^2 -> 33075 | E36: =Assumptions!B101*(1.05)^3 -> 34728.75 | F36: =Assumptions!B101*(1.05)^4 -> 36465.188 | G36: =Assumptions!B101*(1.05)^5 -> 38288.447 | H36: =Assumptions!B101*(1.05)^6 -> 40202.869 | I36: =Assumptions!B101*(1.05)^7 -> 42213.013 | J36: =Assumptions!B101*(1.05)^8 -> 44323.663 | K36: =Assumptions!B101*(1.05)^9 -> 46539.846
A37: Legal / Compliance | B37: =Assumptions!B102*(1.05)^0 -> 25000 | C37: =Assumptions!B102*(1.05)^1 -> 26250 | D37: =Assumptions!B102*(1.05)^2 -> 27562.5 | E37: =Assumptions!B102*(1.05)^3 -> 28940.625 | F37: =Assumptions!B102*(1.05)^4 -> 30387.656 | G37: =Assumptions!B102*(1.05)^5 -> 31907.039 | H37: =Assumptions!B102*(1.05)^6 -> 33502.391 | I37: =Assumptions!B102*(1.05)^7 -> 35177.511 | J37: =Assumptions!B102*(1.05)^8 -> 36936.386 | K37: =Assumptions!B102*(1.05)^9 -> 38783.205
A38: Insurance | B38: =Assumptions!B103*(1.05)^0 -> 20000 | C38: =Assumptions!B103*(1.05)^1 -> 21000 | D38: =Assumptions!B103*(1.05)^2 -> 22050 | E38: =Assumptions!B103*(1.05)^3 -> 23152.5 | F38: =Assumptions!B103*(1.05)^4 -> 24310.125 | G38: =Assumptions!B103*(1.05)^5 -> 25525.631 | H38: =Assumptions!B103*(1.05)^6 -> 26801.913 | I38: =Assumptions!B103*(1.05)^7 -> 28142.008 | J38: =Assumptions!B103*(1.05)^8 -> 29549.109 | K38: =Assumptions!B103*(1.05)^9 -> 31026.564
A39: Customer Support Tools | B39: =Assumptions!B104*(1.05)^0 -> 15000 | C39: =Assumptions!B104*(1.05)^1 -> 15750 | D39: =Assumptions!B104*(1.05)^2 -> 16537.5 | E39: =Assumptions!B104*(1.05)^3 -> 17364.375 | F39: =Assumptions!B104*(1.05)^4 -> 18232.594 | G39: =Assumptions!B104*(1.05)^5 -> 19144.223 | H39: =Assumptions!B104*(1.05)^6 -> 20101.435 | I39: =Assumptions!B104*(1.05)^7 -> 21106.506 | J39: =Assumptions!B104*(1.05)^8 -> 22161.832 | K39: =Assumptions!B104*(1.05)^9 -> 23269.923
A40: TOTAL NON-HEADCOUNT OPEX | B40: =SUM(B31:B39) -> 331000 | C40: =SUM(C31:C39) -> 347550 | D40: =SUM(D31:D39) -> 364927.5 | E40: =SUM(E31:E39) -> 383173.88 | F40: =SUM(F31:F39) -> 402332.57 | G40: =SUM(G31:G39) -> 422449.2 | H40: =SUM(H31:H39) -> 443571.66 | I40: =SUM(I31:I39) -> 465750.24 | ... K40: =SUM(K31:K39) -> 513489.64
A42: TOTAL OPERATING EXPENSES | B42: =B28+B40 -> 1006000 | C42: =C28+C40 -> 1274550 | D42: =D28+D40 -> 1319737.5 | E42: =E28+E40 -> 1557855.4 | F42: =F28+F40 -> 1612254.5 | G42: =G28+G40 -> 1668668.8 | H42: =H28+H40 -> 1936137 | I42: =I28+I40 -> 2003092.6 | ... K42: =K28+K40 -> 2372791.4
A44: TOTAL COST SUMMARY
A45: Total Direct Costs (COGS) | B45: =B13 -> 294447.25 | C45: =C13 -> 582340.28 | D45: =D13 -> 969874.24 | E45: =E13 -> 1324865.6 | F45: =F13 -> 1866585.4 | G45: =G13 -> 2096243.9 | H45: =H13 -> 2307192.6 | I45: =I13 -> 2540925.3 | ... K45: =K13 -> 2959847.8
A46: Total Operating Expenses | B46: =B42 -> 1006000 | C46: =C42 -> 1274550 | D46: =D42 -> 1319737.5 | E46: =E42 -> 1557855.4 | F46: =F42 -> 1612254.5 | G46: =G42 -> 1668668.8 | H46: =H42 -> 1936137 | I46: =I42 -> 2003092.6 | ... K46: =K42 -> 2372791.4
A47: TOTAL COSTS | B47: =B45+B46 -> 1300447.3 | C47: =C45+C46 -> 1856890.3 | D47: =D45+D46 -> 2289611.7 | E47: =E45+E46 -> 2882721 | F47: =F45+F46 -> 3478839.9 | G47: =G45+G46 -> 3764912.7 | H47: =H45+H46 -> 4243329.6 | I47: =I45+I46 -> 4544017.9 | ... K47: =K45+K46 -> 5332639.2
A49: Direct Costs as % of Revenue | B49: =IF('Revenue Build'!B78=0,0,B45/'Revenue Build'!B78) -> 0.50350022 | C49: =IF('Revenue Build'!C78=0,0,C45/'Revenue Build'!C78) -> 0.48304808 | D49: =IF('Revenue Build'!D78=0,0,D45/'Revenue Build'!D78) -> 0.468596 | E49: =IF('Revenue Build'!E78=0,0,E45/'Revenue Build'!E78) -> 0.46048476 | F49: =IF('Revenue Build'!F78=0,0,F45/'Revenue Build'!F78) -> 0.45184663 | G49: =IF('Revenue Build'!G78=0,0,G45/'Revenue Build'!G78) -> 0.4482907 | H49: =IF('Revenue Build'!H78=0,0,H45/'Revenue Build'!H78) -> 0.44390042 | I49: =IF('Revenue Build'!I78=0,0,I45/'Revenue Build'!I78) -> 0.43967452 | ... K49: =IF('Revenue Build'!K78=0,0,K45/'Revenue Build'!K78) -> 0.42637807
A50: OpEx as % of Revenue | B50: =IF('Revenue Build'!B78=0,0,B46/'Revenue Build'!B78) -> 1.7202443 | C50: =IF('Revenue Build'!C78=0,0,C46/'Revenue Build'!C78) -> 1.0572323 | D50: =IF('Revenue Build'!D78=0,0,D46/'Revenue Build'!D78) -> 0.63763288 | E50: =IF('Revenue Build'!E78=0,0,E46/'Revenue Build'!E78) -> 0.54146523 | F50: =IF('Revenue Build'!F78=0,0,F46/'Revenue Build'!F78) -> 0.39028045 | G50: =IF('Revenue Build'!G78=0,0,G46/'Revenue Build'!G78) -> 0.35685195 | H50: =IF('Revenue Build'!H78=0,0,H46/'Revenue Build'!H78) -> 0.37250988 | I50: =IF('Revenue Build'!I78=0,0,I46/'Revenue Build'!I78) -> 0.34660947 | ... K50: =IF('Revenue Build'!K78=0,0,K46/'Revenue Build'!K78) -> 0.34181023
A51: Total Costs as % of Revenue | B51: =IF('Revenue Build'!B78=0,0,B47/'Revenue Build'!B78) -> 2.2237445 | C51: =IF('Revenue Build'!C78=0,0,C47/'Revenue Build'!C78) -> 1.5402803 | D51: =IF('Revenue Build'!D78=0,0,D47/'Revenue Build'!D78) -> 1.1062289 | E51: =IF('Revenue Build'!E78=0,0,E47/'Revenue Build'!E78) -> 1.00195 | F51: =IF('Revenue Build'!F78=0,0,F47/'Revenue Build'!F78) -> 0.84212708 | G51: =IF('Revenue Build'!G78=0,0,G47/'Revenue Build'!G78) -> 0.80514265 | H51: =IF('Revenue Build'!H78=0,0,H47/'Revenue Build'!H78) -> 0.81641031 | I51: =IF('Revenue Build'!I78=0,0,I47/'Revenue Build'!I78) -> 0.78628399 | ... K51: =IF('Revenue Build'!K78=0,0,K47/'Revenue Build'!K78) -> 0.7681883
A53: Fixed Costs (Headcount + Non-HC Fixed) | B53: =B28+B40*0.7 -> 906700 | C53: =C28+C40*0.7 -> 1170285 | D53: =D28+D40*0.7 -> 1210259.2 | E53: =E28+E40*0.7 -> 1442903.2 | F53: =F28+F40*0.7 -> 1491554.8 | G53: =G28+G40*0.7 -> 1541934.1 | H53: =H28+H40*0.7 -> 1803065.5 | I53: =I28+I40*0.7 -> 1863367.5 | ... K53: =K28+K40*0.7 -> 2218744.5
A54: Variable Costs (Direct + Volume-Driven) | B54: =B45+B40*0.3 -> 393747.25 | C54: =C45+C40*0.3 -> 686605.28 | D54: =D45+D40*0.3 -> 1079352.5 | E54: =E45+E40*0.3 -> 1439817.8 | F54: =F45+F40*0.3 -> 1987285.2 | G54: =G45+G40*0.3 -> 2222978.6 | H54: =H45+H40*0.3 -> 2440264.1 | I54: =I45+I40*0.3 -> 2680650.4 | ... K54: =K45+K40*0.3 -> 3113894.6
A55: Fixed Cost Ratio | B55: =IF(B47=0,0,B53/B47) -> 0.69722167 | C55: =IF(C47=0,0,C53/C47) -> 0.63023918 | D55: =IF(D47=0,0,D53/D47) -> 0.52858711 | E55: =IF(E47=0,0,E53/E47) -> 0.50053516 | F55: =IF(F47=0,0,F53/F47) -> 0.42875062 | G55: =IF(G47=0,0,G53/G47) -> 0.40955374 | H55: =IF(H47=0,0,H53/H47) -> 0.42491762 | I55: =IF(I47=0,0,I53/I47) -> 0.41007046 | ... K55: =IF(K47=0,0,K53/K47) -> 0.41606875
A56: Operating Leverage Indicator | B56: =IF('Revenue Build'!B78=0,0,'Revenue Build'!B78/B53) -> 0.644977 | C56: =IF('Revenue Build'!C78=0,0,'Revenue Build'!C78/C53) -> 1.0301366 | D56: =IF('Revenue Build'!D78=0,0,'Revenue Build'!D78/D53) -> 1.7101667 | E56: =IF('Revenue Build'!E78=0,0,'Revenue Build'!E78/E53) -> 1.9939734 | F56: =IF('Revenue Build'!F78=0,0,'Revenue Build'!F78/F53) -> 2.7696036 | G56: =IF('Revenue Build'!G78=0,0,'Revenue Build'!G78/G53) -> 3.032608 | H56: =IF('Revenue Build'!H78=0,0,'Revenue Build'!H78/H53) -> 2.8826159 | I56: =IF('Revenue Build'!I78=0,0,'Revenue Build'!I78/I53) -> 3.1014307 | ... K56: =IF('Revenue Build'!K78=0,0,'Revenue Build'!K78/K53) -> 3.1287237

Sheet Margin Analysis
A1: MARGIN ANALYSIS BY SEGMENT — 10 YEAR FORECAST
B2: Year 1 | C2: Year 2 | D2: Year 3 | E2: Year 4 | F2: Year 5 | G2: Year 6 | H2: Year 7 | I2: Year 8 | J2: Year 9 | K2: Year 10
A4: A. LEARN GOLF PLATFORM — MARGINS
A5: Revenue | B5: ='Revenue Build'!B20 -> 265097.45 | C5: ='Revenue Build'!C20 -> 460846.94 | D5: ='Revenue Build'!D20 -> 768382.19 | E5: ='Revenue Build'!E20 -> 1000032.2 | F5: ='Revenue Build'!F20 -> 1352494.4 | G5: ='Revenue Build'!G20 -> 1503162.3 | H5: ='Revenue Build'!H20 -> 1665684 | I5: ='Revenue Build'!I20 -> 1832755.8 | ... K5: ='Revenue Build'!K20 -> 2066507
A6: Direct Costs (3% processing) | B6: ='Cost Build'!B5 -> 59376.24 | C6: ='Cost Build'!C5 -> 101929.21 | D6: ='Cost Build'!D5 -> 167979.34 | E6: ='Cost Build'!E5 -> 216273.4 | F6: ='Cost Build'!F5 -> 289590.09 | G6: ='Cost Build'!G5 -> 321222.23 | H6: ='Cost Build'!H5 -> 354491.68 | I6: ='Cost Build'!I5 -> 389468.19 | ... K6: ='Cost Build'!K5 -> 439010.98
A7: Gross Profit | B7: =B5-B6 -> 205721.21 | C7: =C5-C6 -> 358917.73 | D7: =D5-D6 -> 600402.85 | E7: =E5-E6 -> 783758.79 | F7: =F5-F6 -> 1062904.4 | G7: =G5-G6 -> 1181940.1 | H7: =H5-H6 -> 1311192.3 | I7: =I5-I6 -> 1443287.6 | ... K7: =K5-K6 -> 1627496
A8: Gross Margin % | B8: =IF(B5=0,0,B7/B5) -> 0.77602108 | C8: =IF(C5=0,0,C7/C5) -> 0.77882198 | D8: =IF(D5=0,0,D7/D5) -> 0.78138569 | E8: =IF(E5=0,0,E7/E5) -> 0.78373356 | F8: =IF(F5=0,0,F7/F5) -> 0.78588445 | G8: =IF(G5=0,0,G7/G5) -> 0.78630237 | H8: =IF(H5=0,0,H7/H5) -> 0.78717951 | I8: =IF(I5=0,0,I7/I5) -> 0.78749586 | ... K8: =IF(K5=0,0,K7/K5) -> 0.78755892
A9: Allocated Overhead (25% of total OpEx) | B9: ='Cost Build'!B42*IF('Revenue Build'!B78=0,0,'Revenue Build'!B20/'Revenue Build'!B78) -> 456032.38 | C9: ='Cost Build'!C42*IF('Revenue Build'!C78=0,0,'Revenue Build'!C20/'Revenue Build'!C78) -> 487222.25 | D9: ='Cost Build'!D42*IF('Revenue Build'!D78=0,0,'Revenue Build'!D20/'Revenue Build'!D78) -> 489945.75 | E9: ='Cost Build'!E42*IF('Revenue Build'!E78=0,0,'Revenue Build'!E20/'Revenue Build'!E78) -> 541482.66 | F9: ='Cost Build'!F42*IF('Revenue Build'!F78=0,0,'Revenue Build'!F20/'Revenue Build'!F78) -> 527852.13 | G9: ='Cost Build'!G42*IF('Revenue Build'!G78=0,0,'Revenue Build'!G20/'Revenue Build'!G78) -> 536406.41 | H9: ='Cost Build'!H42*IF('Revenue Build'!H78=0,0,'Revenue Build'!H20/'Revenue Build'!H78) -> 620483.75 | I9: ='Cost Build'!I42*IF('Revenue Build'!I78=0,0,'Revenue Build'!I20/'Revenue Build'!I78) -> 635250.52 | ... K9: ='Cost Build'!K42*IF('Revenue Build'!K78=0,0,'Revenue Build'!K20/'Revenue Build'!K78) -> 706353.23
A10: Contribution Profit | B10: =B7-B9 -> -250311.17 | C10: =C7-C9 -> -128304.52 | D10: =D7-D9 -> 110457.1 | E10: =E7-E9 -> 242276.13 | F10: =F7-F9 -> 535052.22 | G10: =G7-G9 -> 645533.68 | H10: =H7-H9 -> 690708.57 | I10: =I7-I9 -> 808037.1 | ... K10: =K7-K9 -> 921142.8
A11: Contribution Margin % | B11: =IF(B5=0,0,B10/B5) -> -0.94422325 | C11: =IF(C5=0,0,C10/C5) -> -0.27841027 | D11: =IF(D5=0,0,D10/D5) -> 0.14375281 | E11: =IF(E5=0,0,E10/E5) -> 0.24226833 | F11: =IF(F5=0,0,F10/F5) -> 0.39560401 | G11: =IF(G5=0,0,G10/G5) -> 0.42945041 | H11: =IF(H5=0,0,H10/H5) -> 0.41466963 | I11: =IF(I5=0,0,I10/I5) -> 0.4408864 | ... K11: =IF(K5=0,0,K10/K5) -> 0.4457487
A13: B. CREATOR NETWORK — MARGINS
A14: Revenue | B14: ='Revenue Build'!B38 -> 979.2 | C14: ='Revenue Build'!C38 -> 1815.4368 | D14: ='Revenue Build'!D38 -> 63116.5 | E14: ='Revenue Build'!E38 -> 118065.99 | F14: ='Revenue Build'!F38 -> 205510.49 | G14: ='Revenue Build'!G38 -> 281243.39 | H14: ='Revenue Build'!H38 -> 367015.3 | I14: ='Revenue Build'!I38 -> 462827.9 | ... K14: ='Revenue Build'!K38 -> 708943.44
A15: Direct Costs (Comp + Content + Mgmt) | B15: ='Cost Build'!B6+'Cost Build'!B7+'Cost Build'!B8 -> 96000 | C15: ='Cost Build'!C6+'Cost Build'!C7+'Cost Build'!C8 -> 172800 | D15: ='Cost Build'!D6+'Cost Build'!D7+'Cost Build'!D8 -> 288000 | E15: ='Cost Build'!E6+'Cost Build'!E7+'Cost Build'!E8 -> 364800 | F15: ='Cost Build'!F6+'Cost Build'!F7+'Cost Build'!F8 -> 480000 | G15: ='Cost Build'!G6+'Cost Build'!G7+'Cost Build'!G8 -> 528000 | H15: ='Cost Build'!H6+'Cost Build'!H7+'Cost Build'!H8 -> 576000 | I15: ='Cost Build'!I6+'Cost Build'!I7+'Cost Build'!I8 -> 624000 | ... K15: ='Cost Build'!K6+'Cost Build'!K7+'Cost Build'!K8 -> 672000
A16: Gross Profit | B16: =B14-B15 -> -95020.8 | C16: =C14-C15 -> -170984.56 | D16: =D14-D15 -> -224883.5 | E16: =E14-E15 -> -246734.01 | F16: =F14-F15 -> -274489.51 | G16: =G14-G15 -> -246756.61 | H16: =H14-H15 -> -208984.7 | I16: =I14-I15 -> -161172.1 | ... K16: =K14-K15 -> 36943.437
A17: Gross Margin % | B17: =IF(B14=0,0,B16/B14) -> -97.039216 | C17: =IF(C14=0,0,C16/C14) -> -94.183705 | D17: =IF(D14=0,0,D16/D14) -> -3.5629907 | E17: =IF(E14=0,0,E16/E14) -> -2.0897974 | F17: =IF(F14=0,0,F16/F14) -> -1.3356472 | G17: =IF(G14=0,0,G16/G14) -> -0.87737748 | H17: =IF(H14=0,0,H16/H14) -> -0.56941688 | I17: =IF(I14=0,0,I16/I14) -> -0.34823332 | ... K17: =IF(K14=0,0,K16/K14) -> 0.052110557
A18: Allocated Overhead | B18: ='Cost Build'!B42*IF('Revenue Build'!B78=0,0,'Revenue Build'!B38/'Revenue Build'!B78) -> 1684.4632 | C18: ='Cost Build'!C42*IF('Revenue Build'!C78=0,0,'Revenue Build'!C38/'Revenue Build'!C78) -> 1919.3383 | D18: ='Cost Build'!D42*IF('Revenue Build'!D78=0,0,'Revenue Build'!D38/'Revenue Build'!D78) -> 40245.156 | E18: ='Cost Build'!E42*IF('Revenue Build'!E78=0,0,'Revenue Build'!E38/'Revenue Build'!E78) -> 63928.631 | F18: ='Cost Build'!F42*IF('Revenue Build'!F78=0,0,'Revenue Build'!F38/'Revenue Build'!F78) -> 80206.726 | G18: ='Cost Build'!G42*IF('Revenue Build'!G78=0,0,'Revenue Build'!G38/'Revenue Build'!G78) -> 100362.25 | H18: ='Cost Build'!H42*IF('Revenue Build'!H78=0,0,'Revenue Build'!H38/'Revenue Build'!H78) -> 136716.83 | I18: ='Cost Build'!I42*IF('Revenue Build'!I78=0,0,'Revenue Build'!I38/'Revenue Build'!I78) -> 160420.53 | ... K18: ='Cost Build'!K42*IF('Revenue Build'!K78=0,0,'Revenue Build'!K38/'Revenue Build'!K78) -> 242324.12
A19: Contribution Profit | B19: =B16-B18 -> -96705.263 | C19: =C16-C18 -> -172903.9 | D19: =D16-D18 -> -265128.66 | E19: =E16-E18 -> -310662.64 | F19: =F16-F18 -> -354696.23 | G19: =G16-G18 -> -347118.87 | H19: =H16-H18 -> -345701.53 | I19: =I16-I18 -> -321592.63 | ... K19: =K16-K18 -> -205380.68
A20: Contribution Margin % | B20: =IF(B14=0,0,B19/B14) -> -98.75946 | C20: =IF(C14=0,0,C19/C14) -> -95.240937 | D20: =IF(D14=0,0,D19/D14) -> -4.2006236 | E20: =IF(E14=0,0,E19/E14) -> -2.6312626 | F20: =IF(F14=0,0,F19/F14) -> -1.7259276 | G20: =IF(G14=0,0,G19/G14) -> -1.2342294 | H20: =IF(H14=0,0,H19/H14) -> -0.94192676 | I20: =IF(I14=0,0,I19/I14) -> -0.69484279 | ... K20: =IF(K14=0,0,K19/K14) -> -0.28969967
A22: C. VENUE PARTNERSHIPS — MARGINS
A23: Revenue | B23: ='Revenue Build'!B56 -> 131224 | C23: ='Revenue Build'!C56 -> 196891.08 | D23: ='Revenue Build'!D56 -> 328246.35 | E23: ='Revenue Build'!E56 -> 394012.49 | F23: ='Revenue Build'!F56 -> 525510.49 | G23: ='Revenue Build'!G56 -> 525675.81 | H23: ='Revenue Build'!H56 -> 525846.08 | I23: ='Revenue Build'!I56 -> 526021.46 | ... K23: ='Revenue Build'!K56 -> 526388.17
A24: Direct Costs (Activation) | B24: ='Cost Build'!B9 -> 30000 | C24: ='Cost Build'!C9 -> 45000 | D24: ='Cost Build'!D9 -> 75000 | E24: ='Cost Build'!E9 -> 90000 | F24: ='Cost Build'!F9 -> 120000 | G24: ='Cost Build'!G9 -> 120000 | H24: ='Cost Build'!H9 -> 120000 | I24: ='Cost Build'!I9 -> 120000 | ... K24: ='Cost Build'!K9 -> 120000
A25: Gross Profit | B25: =B23-B24 -> 101224 | C25: =C23-C24 -> 151891.08 | D25: =D23-D24 -> 253246.35 | E25: =E23-E24 -> 304012.49 | F25: =F23-F24 -> 405510.49 | G25: =G23-G24 -> 405675.81 | H25: =H23-H24 -> 405846.08 | I25: =I23-I24 -> 406021.46 | ... K25: =K23-K24 -> 406388.17
A26: Gross Margin % | B26: =IF(B23=0,0,B25/B23) -> 0.77138328 | C26: =IF(C23=0,0,C25/C23) -> 0.77144724 | D26: =IF(D23=0,0,D25/D23) -> 0.77151308 | E26: =IF(E23=0,0,E25/E23) -> 0.77158085 | F26: =IF(F23=0,0,F25/F23) -> 0.77165061 | G26: =IF(G23=0,0,G25/G23) -> 0.77172242 | H26: =IF(H23=0,0,H25/H23) -> 0.77179634 | I26: =IF(I23=0,0,I25/I23) -> 0.77187243 | ... K26: =IF(K23=0,0,K25/K23) -> 0.77203135
A27: Allocated Overhead | B27: ='Cost Build'!B42*IF('Revenue Build'!B78=0,0,'Revenue Build'!B56/'Revenue Build'!B78) -> 225737.34 | C27: ='Cost Build'!C42*IF('Revenue Build'!C78=0,0,'Revenue Build'!C56/'Revenue Build'!C78) -> 208159.6 | D27: ='Cost Build'!D42*IF('Revenue Build'!D78=0,0,'Revenue Build'!D56/'Revenue Build'!D78) -> 209300.67 | E27: ='Cost Build'!E42*IF('Revenue Build'!E78=0,0,'Revenue Build'!E56/'Revenue Build'!E78) -> 213344.07 | F27: ='Cost Build'!F42*IF('Revenue Build'!F78=0,0,'Revenue Build'!F56/'Revenue Build'!F78) -> 205096.47 | G27: ='Cost Build'!G42*IF('Revenue Build'!G78=0,0,'Revenue Build'!G56/'Revenue Build'!G78) -> 187588.44 | H27: ='Cost Build'!H42*IF('Revenue Build'!H78=0,0,'Revenue Build'!H56/'Revenue Build'!H78) -> 195882.86 | I27: ='Cost Build'!I42*IF('Revenue Build'!I78=0,0,'Revenue Build'!I56/'Revenue Build'!I78) -> 182324.02 | ... K27: ='Cost Build'!K42*IF('Revenue Build'!K78=0,0,'Revenue Build'!K56/'Revenue Build'!K78) -> 179924.86
A28: Contribution Profit | B28: =B25-B27 -> -124513.34 | C28: =C25-C27 -> -56268.52 | D28: =D25-D27 -> 43945.685 | E28: =E25-E27 -> 90668.427 | F28: =F25-F27 -> 200414.02 | G28: =G25-G27 -> 218087.37 | H28: =H25-H27 -> 209963.22 | I28: =I25-I27 -> 223697.44 | ... K28: =K25-K27 -> 226463.31
A29: Contribution Margin % | B29: =IF(B23=0,0,B28/B23) -> -0.94886105 | C29: =IF(C23=0,0,C28/C23) -> -0.28578502 | D29: =IF(D23=0,0,D28/D23) -> 0.13388019 | E29: =IF(E23=0,0,E28/E23) -> 0.23011561 | F29: =IF(F23=0,0,F28/F23) -> 0.38137016 | G29: =IF(G23=0,0,G28/G23) -> 0.41487047 | H29: =IF(H23=0,0,H28/H23) -> 0.39928646 | I29: =IF(I23=0,0,I28/I23) -> 0.42526296 | ... K29: =IF(K23=0,0,K28/K23) -> 0.43022112
A31: D. CORPORATE PROGRAMS — MARGINS
A32: Revenue | B32: ='Revenue Build'!B71 -> 187500 | C32: ='Revenue Build'!C71 -> 546000 | D32: ='Revenue Build'!D71 -> 910000 | E32: ='Revenue Build'!E71 -> 1365000 | F32: ='Revenue Build'!F71 -> 2047500 | G32: ='Revenue Build'!G71 -> 2366000 | H32: ='Revenue Build'!H71 -> 2639000 | I32: ='Revenue Build'!I71 -> 2957500 | ... K32: ='Revenue Build'!K71 -> 3640000
A33: Direct Costs (Delivery + Commissions) | B33: ='Cost Build'!B10+'Cost Build'!B11 -> 97375 | C33: ='Cost Build'!C10+'Cost Build'!C11 -> 238500 | D33: ='Cost Build'!D10+'Cost Build'!D11 -> 397500 | E33: ='Cost Build'!E10+'Cost Build'!E11 -> 596250 | F33: ='Cost Build'!F10+'Cost Build'!F11 -> 894375 | G33: ='Cost Build'!G10+'Cost Build'!G11 -> 1033500 | H33: ='Cost Build'!H10+'Cost Build'!H11 -> 1152750 | I33: ='Cost Build'!I10+'Cost Build'!I11 -> 1291875 | ... K33: ='Cost Build'!K10+'Cost Build'!K11 -> 1590000
A34: Gross Profit | B34: =B32-B33 -> 90125 | C34: =C32-C33 -> 307500 | D34: =D32-D33 -> 512500 | E34: =E32-E33 -> 768750 | F34: =F32-F33 -> 1153125 | G34: =G32-G33 -> 1332500 | H34: =H32-H33 -> 1486250 | I34: =I32-I33 -> 1665625 | ... K34: =K32-K33 -> 2050000
A35: Gross Margin % | B35: =IF(B32=0,0,B34/B32) -> 0.48066667 | C35: =IF(C32=0,0,C34/C32) -> 0.56318681 | D35: =IF(D32=0,0,D34/D32) -> 0.56318681 | E35: =IF(E32=0,0,E34/E32) -> 0.56318681 | F35: =IF(F32=0,0,F34/F32) -> 0.56318681 | G35: =IF(G32=0,0,G34/G32) -> 0.56318681 | H35: =IF(H32=0,0,H34/H32) -> 0.56318681 | I35: =IF(I32=0,0,I34/I32) -> 0.56318681 | ... K35: =IF(K32=0,0,K34/K32) -> 0.56318681
A36: Allocated Overhead | B36: ='Cost Build'!B42*IF('Revenue Build'!B78=0,0,'Revenue Build'!B71/'Revenue Build'!B78) -> 322545.81 | C36: ='Cost Build'!C42*IF('Revenue Build'!C78=0,0,'Revenue Build'!C71/'Revenue Build'!C78) -> 577248.81 | D36: ='Cost Build'!D42*IF('Revenue Build'!D78=0,0,'Revenue Build'!D71/'Revenue Build'!D78) -> 580245.92 | E36: ='Cost Build'!E42*IF('Revenue Build'!E78=0,0,'Revenue Build'!E71/'Revenue Build'!E78) -> 739100.04 | F36: ='Cost Build'!F42*IF('Revenue Build'!F78=0,0,'Revenue Build'!F71/'Revenue Build'!F78) -> 799099.21 | G36: ='Cost Build'!G42*IF('Revenue Build'!G78=0,0,'Revenue Build'!G71/'Revenue Build'!G78) -> 844311.72 | H36: ='Cost Build'!H42*IF('Revenue Build'!H78=0,0,'Revenue Build'!H71/'Revenue Build'!H78) -> 983053.59 | I36: ='Cost Build'!I42*IF('Revenue Build'!I78=0,0,'Revenue Build'!I71/'Revenue Build'!I78) -> 1025097.5 | ... K36: ='Cost Build'!K42*IF('Revenue Build'!K78=0,0,'Revenue Build'!K71/'Revenue Build'!K78) -> 1244189.2
A37: Contribution Profit | B37: =B34-B36 -> -232420.81 | C37: =C34-C36 -> -269748.81 | D37: =D34-D36 -> -67745.923 | E37: =E34-E36 -> 29649.958 | F37: =F34-F36 -> 354025.79 | G37: =G34-G36 -> 488188.28 | H37: =H34-H36 -> 503196.41 | I37: =I34-I36 -> 640527.5 | ... K37: =K34-K36 -> 805810.78
A38: Contribution Margin % | B38: =IF(B32=0,0,B37/B32) -> -1.2395777 | C38: =IF(C32=0,0,C37/C32) -> -0.49404544 | D38: =IF(D32=0,0,D37/D32) -> -0.074446069 | E38: =IF(E32=0,0,E37/E32) -> 0.021721581 | F38: =IF(F32=0,0,F37/F32) -> 0.17290637 | G38: =IF(G32=0,0,G37/G32) -> 0.20633486 | H38: =IF(H32=0,0,H37/H32) -> 0.19067693 | I38: =IF(I32=0,0,I37/I32) -> 0.21657734 | ... K38: =IF(K32=0,0,K37/K32) -> 0.22137659
A40: CONSOLIDATED MARGIN SUMMARY
A41: Total Revenue | B41: ='Revenue Build'!B78 -> 584800.65 | C41: ='Revenue Build'!C78 -> 1205553.5 | D41: ='Revenue Build'!D78 -> 2069745 | E41: ='Revenue Build'!E78 -> 2877110.7 | F41: ='Revenue Build'!F78 -> 4131015.4 | G41: ='Revenue Build'!G78 -> 4676081.5 | H41: ='Revenue Build'!H78 -> 5197545.4 | I41: ='Revenue Build'!I78 -> 5779105.2 | ... K41: ='Revenue Build'!K78 -> 6941838.6
A42: Total Direct Costs | B42: ='Cost Build'!B13 -> 294447.25 | C42: ='Cost Build'!C13 -> 582340.28 | D42: ='Cost Build'!D13 -> 969874.24 | E42: ='Cost Build'!E13 -> 1324865.6 | F42: ='Cost Build'!F13 -> 1866585.4 | G42: ='Cost Build'!G13 -> 2096243.9 | H42: ='Cost Build'!H13 -> 2307192.6 | I42: ='Cost Build'!I13 -> 2540925.3 | ... K42: ='Cost Build'!K13 -> 2959847.8
A43: GROSS PROFIT | B43: =B41-B42 -> 290353.4 | C43: =C41-C42 -> 623213.18 | D43: =D41-D42 -> 1099870.8 | E43: =E41-E42 -> 1552245.1 | F43: =F41-F42 -> 2264430 | G43: =G41-G42 -> 2579837.7 | H43: =H41-H42 -> 2890352.8 | I43: =I41-I42 -> 3238179.9 | ... K43: =K41-K42 -> 3981990.9
A44: GROSS MARGIN % | B44: =IF(B41=0,0,B43/B41) -> 0.49649978 | C44: =IF(C41=0,0,C43/C41) -> 0.51695192 | D44: =IF(D41=0,0,D43/D41) -> 0.531404 | E44: =IF(E41=0,0,E43/E41) -> 0.53951524 | F44: =IF(F41=0,0,F43/F41) -> 0.54815337 | G44: =IF(G41=0,0,G43/G41) -> 0.5517093 | H44: =IF(H41=0,0,H43/H41) -> 0.55609958 | I44: =IF(I41=0,0,I43/I41) -> 0.56032548 | ... K44: =IF(K41=0,0,K43/K41) -> 0.57362193
A46: Total Operating Expenses | B46: ='Cost Build'!B42 -> 1006000 | C46: ='Cost Build'!C42 -> 1274550 | D46: ='Cost Build'!D42 -> 1319737.5 | E46: ='Cost Build'!E42 -> 1557855.4 | F46: ='Cost Build'!F42 -> 1612254.5 | G46: ='Cost Build'!G42 -> 1668668.8 | H46: ='Cost Build'!H42 -> 1936137 | I46: ='Cost Build'!I42 -> 2003092.6 | ... K46: ='Cost Build'!K42 -> 2372791.4
A47: EBITDA | B47: =B43-B46 -> -715646.6 | C47: =C43-C46 -> -651336.82 | D47: =D43-D46 -> -219866.69 | E47: =E43-E46 -> -5610.34 | F47: =F43-F46 -> 652175.49 | G47: =G43-G46 -> 911168.83 | H47: =H43-H46 -> 954215.76 | I47: =I43-I46 -> 1235087.3 | ... K47: =K43-K46 -> 1609199.4
A48: EBITDA MARGIN % | B48: =IF(B41=0,0,B47/B41) -> -1.2237445 | C48: =IF(C41=0,0,C47/C41) -> -0.54028033 | D48: =IF(D41=0,0,D47/D41) -> -0.10622888 | E48: =IF(E41=0,0,E47/E41) -> -0.001949991 | F48: =IF(F41=0,0,F47/F41) -> 0.15787292 | G48: =IF(G41=0,0,G47/G41) -> 0.19485735 | H48: =IF(H41=0,0,H47/H41) -> 0.18358969 | I48: =IF(I41=0,0,I47/I41) -> 0.21371601 | ... K48: =IF(K41=0,0,K47/K41) -> 0.2318117
A50: D&A | B50: =B41*Assumptions!B120 -> 17544.019 | C50: =C41*Assumptions!B120 -> 36166.604 | D50: =D41*Assumptions!B120 -> 62092.351 | E50: =E41*Assumptions!B120 -> 86313.32 | F50: =F41*Assumptions!B120 -> 123930.46 | G50: =G41*Assumptions!B120 -> 140282.45 | H50: =H41*Assumptions!B120 -> 155926.36 | I50: =I41*Assumptions!B120 -> 173373.16 | J50: =J41*Assumptions!B120 -> 188634.23 | K50: =K41*Assumptions!B120 -> 208255.16
A51: EBIT | B51: =B47-B50 -> -733190.62 | C51: =C47-C50 -> -687503.43 | D51: =D47-D50 -> -281959.05 | E51: =E47-E50 -> -91923.66 | F51: =F47-F50 -> 528245.02 | G51: =G47-G50 -> 770886.39 | H51: =H47-H50 -> 798289.4 | I51: =I47-I50 -> 1061714.2 | ... K51: =K47-K50 -> 1400944.3
A52: EBIT MARGIN % | B52: =IF(B41=0,0,B51/B41) -> -1.2537445 | C52: =IF(C41=0,0,C51/C41) -> -0.57028033 | D52: =IF(D41=0,0,D51/D41) -> -0.13622888 | E52: =IF(E41=0,0,E51/E41) -> -0.031949991 | F52: =IF(F41=0,0,F51/F41) -> 0.12787292 | G52: =IF(G41=0,0,G51/G41) -> 0.16485735 | H52: =IF(H41=0,0,H51/H41) -> 0.15358969 | I52: =IF(I41=0,0,I51/I41) -> 0.18371601 | ... K52: =IF(K41=0,0,K51/K41) -> 0.2018117
A54: Taxes | B54: =MAX(0,B51*Assumptions!B108) -> 0 | C54: =MAX(0,C51*Assumptions!B108) -> 0 | D54: =MAX(0,D51*Assumptions!B108) -> 0 | E54: =MAX(0,E51*Assumptions!B108) -> 0 | F54: =MAX(0,F51*Assumptions!B108) -> 132061.26 | G54: =MAX(0,G51*Assumptions!B108) -> 192721.6 | H54: =MAX(0,H51*Assumptions!B108) -> 199572.35 | I54: =MAX(0,I51*Assumptions!B108) -> 265428.54 | J54: =MAX(0,J51*Assumptions!B108) -> 266062.75 | K54: =MAX(0,K51*Assumptions!B108) -> 350236.07
A55: NOPAT | B55: =B51-B54 -> -733190.62 | C55: =C51-C54 -> -687503.43 | D55: =D51-D54 -> -281959.05 | E55: =E51-E54 -> -91923.66 | F55: =F51-F54 -> 396183.77 | G55: =G51-G54 -> 578164.79 | H55: =H51-H54 -> 598717.05 | I55: =I51-I54 -> 796285.61 | ... K55: =K51-K54 -> 1050708.2
A57: Capex | B57: =B41*Assumptions!B118 -> 29240.032 | C57: =C41*Assumptions!B118 -> 60277.673 | D57: =D41*Assumptions!B118 -> 103487.25 | E57: =E41*Assumptions!B118 -> 143855.53 | F57: =F41*Assumptions!B118 -> 206550.77 | G57: =G41*Assumptions!B118 -> 233804.08 | H57: =H41*Assumptions!B118 -> 259877.27 | I57: =I41*Assumptions!B118 -> 288955.26 | J57: =J41*Assumptions!B118 -> 314390.38 | K57: =K41*Assumptions!B118 -> 347091.93
A58: Change in Working Capital | B58: =B41*Assumptions!B119 -> 46784.052 | C58: =(C41-B41)*Assumptions!B119 -> 49660.225 | D58: =(D41-C41)*Assumptions!B119 -> 69135.327 | E58: =(E41-D41)*Assumptions!B119 -> 64589.25 | F58: =(F41-E41)*Assumptions!B119 -> 100312.38 | G58: =(G41-F41)*Assumptions!B119 -> 43605.288 | H58: =(H41-G41)*Assumptions!B119 -> 41717.108 | I58: =(I41-H41)*Assumptions!B119 -> 46524.784 | J58: =(J41-I41)*Assumptions!B119 -> 40696.189 | K58: =(K41-J41)*Assumptions!B119 -> 52322.486
A59: FREE CASH FLOW | B59: =B55+B50-B57-B58 -> -791670.69 | C59: =C55+C50-C57-C58 -> -761274.72 | D59: =D55+D50-D57-D58 -> -392489.27 | E59: =E55+E50-E57-E58 -> -214055.12 | F59: =F55+F50-F57-F58 -> 213251.08 | G59: =G55+G50-G57-G58 -> 441037.87 | H59: =H55+H50-H57-H58 -> 453049.04 | I59: =I55+I50-I57-I58 -> 634178.73 | ... K59: =K55+K50-K57-K58 -> 859548.95
A60: FCF MARGIN % | B60: =IF(B41=0,0,B59/B41) -> -1.3537445 | C60: =IF(C41=0,0,C59/C41) -> -0.63147322 | D60: =IF(D41=0,0,D59/D41) -> -0.1896317 | E60: =IF(E41=0,0,E59/E41) -> -0.074399336 | F60: =IF(F41=0,0,F59/F41) -> 0.051621952 | G60: =IF(G41=0,0,G59/G41) -> 0.094317832 | H60: =IF(H41=0,0,H59/H41) -> 0.087165961 | I60: =IF(I41=0,0,I59/I41) -> 0.10973649 | ... K60: =IF(K41=0,0,K59/K41) -> 0.12382151
A95: OPERATING LEVERAGE & MARGIN BRIDGE ANALYSIS
A96: Revenue | B96: ='Revenue Build'!B78 -> 584800.65 | C96: ='Revenue Build'!C78 -> 1205553.5 | D96: ='Revenue Build'!D78 -> 2069745 | E96: ='Revenue Build'!E78 -> 2877110.7 | F96: ='Revenue Build'!F78 -> 4131015.4 | G96: ='Revenue Build'!G78 -> 4676081.5 | H96: ='Revenue Build'!H78 -> 5197545.4 | I96: ='Revenue Build'!I78 -> 5779105.2 | ... K96: ='Revenue Build'!K78 -> 6941838.6
A97: YoY Revenue Growth ($) | B97: 0 | C97: =C96-B96 -> 620752.81 | D97: =D96-C96 -> 864191.59 | E97: =E96-D96 -> 807365.63 | F97: =F96-E96 -> 1253904.7 | G97: =G96-F96 -> 545066.1 | H97: =H96-G96 -> 521463.85 | I97: =I96-H96 -> 581559.8 | J97: =J96-I96 -> 508702.36 | K97: =K96-J96 -> 654031.08
A98: YoY Revenue Growth (%) | B98: N/A | C98: =IF(B96=0,0,C97/B96) -> 1.0614776 | D98: =IF(C96=0,0,D97/C96) -> 0.7168422 | E98: =IF(D96=0,0,E97/D96) -> 0.39007975 | F98: =IF(E96=0,0,F97/E96) -> 0.43582082 | G98: =IF(F96=0,0,G97/F96) -> 0.13194482 | H98: =IF(G96=0,0,H97/G96) -> 0.11151727 | I98: =IF(H96=0,0,I97/H96) -> 0.11189124 | J98: =IF(I96=0,0,J97/I96) -> 0.088024417 | K98: =IF(J96=0,0,K97/J96) -> 0.10401576
A100: COGS (Direct Costs) | B100: ='Cost Build'!B13 -> 294447.25 | C100: ='Cost Build'!C13 -> 582340.28 | D100: ='Cost Build'!D13 -> 969874.24 | E100: ='Cost Build'!E13 -> 1324865.6 | F100: ='Cost Build'!F13 -> 1866585.4 | G100: ='Cost Build'!G13 -> 2096243.9 | H100: ='Cost Build'!H13 -> 2307192.6 | I100: ='Cost Build'!I13 -> 2540925.3 | ... K100: ='Cost Build'!K13 -> 2959847.8
A101: YoY COGS Growth ($) | B101: 0 | C101: =C100-B100 -> 287893.03 | D101: =D100-C100 -> 387533.96 | E101: =E100-D100 -> 354991.37 | F101: =F100-E100 -> 541719.78 | G101: =G100-F100 -> 229658.47 | H101: =H100-G100 -> 210948.72 | I101: =I100-H100 -> 233732.71 | J101: =J100-I100 -> 199811.9 | K101: =K100-J100 -> 219110.56
A102: YoY COGS Growth (%) | B102: N/A | C102: =IF(B100=0,0,C101/B100) -> 0.97774058 | D102: =IF(C100=0,0,D101/C100) -> 0.66547682 | E102: =IF(D100=0,0,E101/D100) -> 0.36601794 | F102: =IF(E100=0,0,F101/E100) -> 0.40888659 | G102: =IF(F100=0,0,G101/F100) -> 0.12303668 | H102: =IF(G100=0,0,H101/G100) -> 0.10063177 | I102: =IF(H100=0,0,I101/H100) -> 0.10130611 | J102: =IF(I100=0,0,J101/I100) -> 0.078637455 | K102: =IF(J100=0,0,K101/J100) -> 0.079945848
A103: Incremental Gross Margin (ΔGP / ΔRev) | B103: N/A | C103: =IF(C97=0,0,(C97-C101)/C97) -> 0.53621953 | D103: =IF(D97=0,0,(D97-D101)/D97) -> 0.55156476 | E103: =IF(E97=0,0,(E97-E101)/E97) -> 0.56030903 | F103: =IF(F97=0,0,(F97-F101)/F97) -> 0.56797374 | G103: =IF(G97=0,0,(G97-G101)/G97) -> 0.57865942 | H103: =IF(H97=0,0,(H97-H101)/H97) -> 0.59546818 | I103: =IF(I97=0,0,(I97-I101)/I97) -> 0.59809342 | J103: =IF(J97=0,0,(J97-J101)/J97) -> 0.60721256 | K103: =IF(K97=0,0,(K97-K101)/K97) -> 0.66498449
A105: Total Operating Costs | B105: ='Cost Build'!B47 -> 1300447.3 | C105: ='Cost Build'!C47 -> 1856890.3 | D105: ='Cost Build'!D47 -> 2289611.7 | E105: ='Cost Build'!E47 -> 2882721 | F105: ='Cost Build'!F47 -> 3478839.9 | G105: ='Cost Build'!G47 -> 3764912.7 | H105: ='Cost Build'!H47 -> 4243329.6 | I105: ='Cost Build'!I47 -> 4544017.9 | ... K105: ='Cost Build'!K47 -> 5332639.2
A106: YoY OpEx Growth ($) | B106: 0 | C106: =C105-B105 -> 556443.03 | D106: =D105-C105 -> 432721.46 | E106: =E105-D105 -> 593109.27 | F106: =F105-E105 -> 596118.92 | G106: =G105-F105 -> 286072.76 | H106: =H105-G105 -> 478416.92 | I106: =I105-H105 -> 300688.25 | J106: =J105-I105 -> 490904.45 | K106: =K105-J105 -> 297716.87
A107: YoY OpEx Growth (%) | B107: N/A | C107: =IF(B105=0,0,C106/B105) -> 0.42788589 | D107: =IF(C105=0,0,D106/C105) -> 0.23303556 | E107: =IF(D105=0,0,E106/D105) -> 0.2590436 | F107: =IF(E105=0,0,F106/E105) -> 0.20679036 | G107: =IF(F105=0,0,G106/F105) -> 0.082232228 | H107: =IF(G105=0,0,H106/G105) -> 0.12707251 | I107: =IF(H105=0,0,I106/H105) -> 0.070861394 | J107: =IF(I105=0,0,J106/I105) -> 0.10803312 | K107: =IF(J105=0,0,K106/J105) -> 0.059130379
A108: Incremental EBITDA Margin (ΔEBITDA / ΔRev) | B108: N/A | C108: =IF(C97=0,0,(C97-C106)/C97) -> 0.10359966 | D108: =IF(D97=0,0,(D97-D106)/D97) -> 0.49927601 | E108: =IF(E97=0,0,(E97-E106)/E97) -> 0.26537711 | F108: =IF(F97=0,0,(F97-F106)/F97) -> 0.52458995 | G108: =IF(G97=0,0,(G97-G106)/G97) -> 0.47515952 | H108: =IF(H97=0,0,(H97-H106)/H97) -> 0.08255017 | I108: =IF(I97=0,0,(I97-I106)/I97) -> 0.48296245 | J108: =IF(J97=0,0,(J97-J106)/J97) -> 0.034986902 | K108: =IF(K97=0,0,(K97-K106)/K97) -> 0.54479707
A110: OPERATING LEVERAGE RATIOS
A111: Revenue / Fixed Costs | B111: =IF('Cost Build'!B53=0,0,B96/'Cost Build'!B53) -> 0.644977 | C111: =IF('Cost Build'!C53=0,0,C96/'Cost Build'!C53) -> 1.0301366 | D111: =IF('Cost Build'!D53=0,0,D96/'Cost Build'!D53) -> 1.7101667 | E111: =IF('Cost Build'!E53=0,0,E96/'Cost Build'!E53) -> 1.9939734 | F111: =IF('Cost Build'!F53=0,0,F96/'Cost Build'!F53) -> 2.7696036 | G111: =IF('Cost Build'!G53=0,0,G96/'Cost Build'!G53) -> 3.032608 | H111: =IF('Cost Build'!H53=0,0,H96/'Cost Build'!H53) -> 2.8826159 | I111: =IF('Cost Build'!I53=0,0,I96/'Cost Build'!I53) -> 3.1014307 | ... K111: =IF('Cost Build'!K53=0,0,K96/'Cost Build'!K53) -> 3.1287237
A112: Degree of Operating Leverage (DOL) | B112: N/A | C112: =IF(OR(B47=0,C98="N/A"),0,(C47-B47)/B47/C98) -> -0.084657915 | D112: =IF(OR(C47=0,D98="N/A"),0,(D47-C47)/C47/D98) -> -0.92410547 | E112: =IF(OR(D47=0,E98="N/A"),0,(E47-D47)/D47/E98) -> -2.4981635 | F112: =IF(OR(E47=0,F98="N/A"),0,(F47-E47)/E47/F98) -> -269.02172 | G112: =IF(OR(F47=0,G98="N/A"),0,(G47-F47)/F47/G98) -> 3.0097594 | H112: =IF(OR(G47=0,H98="N/A"),0,(H47-G47)/G47/H98) -> 0.42364413 | I112: =IF(OR(H47=0,I98="N/A"),0,(I47-H47)/H47/I98) -> 2.6306621 | J112: =IF(OR(I47=0,J98="N/A"),0,(J47-I47)/I47/J98) -> 0.16370744 | K112: =IF(OR(J47=0,K98="N/A"),0,(K47-J47)/J47/K98) -> 2.7341524
A113: Incremental EBITDA Margin vs Avg EBITDA Margin | B113: N/A | C113: =IF(C108="N/A","N/A",C108-C48) -> 0.64388 | D113: =IF(D108="N/A","N/A",D108-D48) -> 0.60550489 | E113: =IF(E108="N/A","N/A",E108-E48) -> 0.2673271 | F113: =IF(F108="N/A","N/A",F108-F48) -> 0.36671702 | G113: =IF(G108="N/A","N/A",G108-G48) -> 0.28030217 | H113: =IF(H108="N/A","N/A",H108-H48) -> -0.10103952 | I113: =IF(I108="N/A","N/A",I108-I48) -> 0.26924644 | J113: =IF(J108="N/A","N/A",J108-J48) -> -0.16426939 | K113: =IF(K108="N/A","N/A",K108-K48) -> 0.31298536
A114: Break-Even Revenue ($) | B114: =IF(B44=0,0,'Cost Build'!B53/(B44)) -> 1826184.1 | C114: =IF(C44=0,0,'Cost Build'!C53/(C44)) -> 2263817.9 | D114: =IF(D44=0,0,'Cost Build'!D53/(D44)) -> 2277474.8 | E114: =IF(E44=0,0,'Cost Build'!E53/(E44)) -> 2674443.9 | F114: =IF(F44=0,0,'Cost Build'!F53/(F44)) -> 2721053.7 | G114: =IF(G44=0,0,'Cost Build'!G53/(G44)) -> 2794830.7 | H114: =IF(H44=0,0,'Cost Build'!H53/(H44)) -> 3242342.9 | I114: =IF(I44=0,0,'Cost Build'!I53/(I44)) -> 3325509.1 | ... K114: =IF(K44=0,0,'Cost Build'!K53/(K44)) -> 3867956.3
A115: Break-Even as % of Actual Revenue | B115: =IF(B96=0,0,B114/B96) -> 3.1227463 | C115: =IF(C96=0,0,C114/C96) -> 1.8778245 | D115: =IF(D96=0,0,D114/D96) -> 1.1003649 | E115: =IF(E96=0,0,E114/E96) -> 0.92955892 | F115: =IF(F96=0,0,F114/F96) -> 0.65868883 | G115: =IF(G96=0,0,G114/G96) -> 0.59768647 | H115: =IF(H96=0,0,H114/H96) -> 0.62382196 | I115: =IF(I96=0,0,I114/I96) -> 0.57543669 | ... K115: =IF(K96=0,0,K114/K96) -> 0.55719478
A117: MARGIN BRIDGE (Basis Points Change YoY)
A118: Gross Margin Change (bps) | B118: 0 | C118: =(C44-B44)*10000 -> 204.52138 | D118: =(D44-C44)*10000 -> 144.52082 | E118: =(E44-D44)*10000 -> 81.112373 | F118: =(F44-E44)*10000 -> 86.381294 | G118: =(G44-F44)*10000 -> 35.559285 | H118: =(H44-G44)*10000 -> 43.902789 | I118: =(I44-H44)*10000 -> 42.259018 | J118: =(J44-I44)*10000 -> 37.933046 | K118: =(K44-J44)*10000 -> 95.031458
A119: EBITDA Margin Change (bps) | B119: 0 | C119: =(C48-B48)*10000 -> 6834.6421 | D119: =(D48-C48)*10000 -> 4340.5146 | E119: =(E48-D48)*10000 -> 1042.7889 | F119: =(F48-E48)*10000 -> 1598.2292 | G119: =(G48-F48)*10000 -> 369.84421 | H119: =(H48-G48)*10000 -> -112.67652 | I119: =(I48-H48)*10000 -> 301.26318 | J119: =(J48-I48)*10000 -> -144.59717 | K119: =(K48-J48)*10000 -> 325.5541
A120: FCF Margin Change (bps) | B120: 0 | C120: =(C60-B60)*10000 -> 7222.7133 | D120: =(D60-C60)*10000 -> 4418.4152 | E120: =(E60-D60)*10000 -> 1152.3237 | F120: =(F60-E60)*10000 -> 1260.2129 | G120: =(G60-F60)*10000 -> 426.9588 | H120: =(H60-G60)*10000 -> -71.518715 | I120: =(I60-H60)*10000 -> 225.70531 | J120: =(J60-I60)*10000 -> -92.665096 | K120: =(K60-J60)*10000 -> 233.5153

Sheet 10-Yr Projection
A1: 10-YEAR FINANCIAL PROJECTION — INCOME STATEMENT & CASH FLOW
A2: ($) | B2: Year 1 | C2: Year 2 | D2: Year 3 | E2: Year 4 | F2: Year 5 | G2: Year 6 | H2: Year 7 | I2: Year 8 | J2: Year 9 | K2: Year 10
A4: INCOME STATEMENT
A5: Platform Revenue | B5: ='Revenue Build'!B20 -> 265097.45 | C5: ='Revenue Build'!C20 -> 460846.94 | D5: ='Revenue Build'!D20 -> 768382.19 | E5: ='Revenue Build'!E20 -> 1000032.2 | F5: ='Revenue Build'!F20 -> 1352494.4 | G5: ='Revenue Build'!G20 -> 1503162.3 | H5: ='Revenue Build'!H20 -> 1665684 | I5: ='Revenue Build'!I20 -> 1832755.8 | ... K5: ='Revenue Build'!K20 -> 2066507
A6: Creator Revenue | B6: ='Revenue Build'!B38 -> 979.2 | C6: ='Revenue Build'!C38 -> 1815.4368 | D6: ='Revenue Build'!D38 -> 63116.5 | E6: ='Revenue Build'!E38 -> 118065.99 | F6: ='Revenue Build'!F38 -> 205510.49 | G6: ='Revenue Build'!G38 -> 281243.39 | H6: ='Revenue Build'!H38 -> 367015.3 | I6: ='Revenue Build'!I38 -> 462827.9 | ... K6: ='Revenue Build'!K38 -> 708943.44
A7: Venue Revenue | B7: ='Revenue Build'!B56 -> 131224 | C7: ='Revenue Build'!C56 -> 196891.08 | D7: ='Revenue Build'!D56 -> 328246.35 | E7: ='Revenue Build'!E56 -> 394012.49 | F7: ='Revenue Build'!F56 -> 525510.49 | G7: ='Revenue Build'!G56 -> 525675.81 | H7: ='Revenue Build'!H56 -> 525846.08 | I7: ='Revenue Build'!I56 -> 526021.46 | ... K7: ='Revenue Build'!K56 -> 526388.17
A8: Corporate Revenue | B8: ='Revenue Build'!B71 -> 187500 | C8: ='Revenue Build'!C71 -> 546000 | D8: ='Revenue Build'!D71 -> 910000 | E8: ='Revenue Build'!E71 -> 1365000 | F8: ='Revenue Build'!F71 -> 2047500 | G8: ='Revenue Build'!G71 -> 2366000 | H8: ='Revenue Build'!H71 -> 2639000 | I8: ='Revenue Build'!I71 -> 2957500 | ... K8: ='Revenue Build'!K71 -> 3640000
A9: TOTAL REVENUE | B9: =SUM(B5:B8) -> 584800.65 | C9: =SUM(C5:C8) -> 1205553.5 | D9: =SUM(D5:D8) -> 2069745 | E9: =SUM(E5:E8) -> 2877110.7 | F9: =SUM(F5:F8) -> 4131015.4 | G9: =SUM(G5:G8) -> 4676081.5 | H9: =SUM(H5:H8) -> 5197545.4 | I9: =SUM(I5:I8) -> 5779105.2 | ... K9: =SUM(K5:K8) -> 6941838.6
A11: Platform Direct Costs | B11: ='Cost Build'!B5 -> 59376.24 | C11: ='Cost Build'!C5 -> 101929.21 | D11: ='Cost Build'!D5 -> 167979.34 | E11: ='Cost Build'!E5 -> 216273.4 | F11: ='Cost Build'!F5 -> 289590.09 | G11: ='Cost Build'!G5 -> 321222.23 | H11: ='Cost Build'!H5 -> 354491.68 | I11: ='Cost Build'!I5 -> 389468.19 | ... K11: ='Cost Build'!K5 -> 439010.98
A12: Creator Direct Costs | B12: ='Cost Build'!B6+'Cost Build'!B7+'Cost Build'!B8 -> 96000 | C12: ='Cost Build'!C6+'Cost Build'!C7+'Cost Build'!C8 -> 172800 | D12: ='Cost Build'!D6+'Cost Build'!D7+'Cost Build'!D8 -> 288000 | E12: ='Cost Build'!E6+'Cost Build'!E7+'Cost Build'!E8 -> 364800 | F12: ='Cost Build'!F6+'Cost Build'!F7+'Cost Build'!F8 -> 480000 | G12: ='Cost Build'!G6+'Cost Build'!G7+'Cost Build'!G8 -> 528000 | H12: ='Cost Build'!H6+'Cost Build'!H7+'Cost Build'!H8 -> 576000 | I12: ='Cost Build'!I6+'Cost Build'!I7+'Cost Build'!I8 -> 624000 | ... K12: ='Cost Build'!K6+'Cost Build'!K7+'Cost Build'!K8 -> 672000
A13: Venue Direct Costs | B13: ='Cost Build'!B9 -> 30000 | C13: ='Cost Build'!C9 -> 45000 | D13: ='Cost Build'!D9 -> 75000 | E13: ='Cost Build'!E9 -> 90000 | F13: ='Cost Build'!F9 -> 120000 | G13: ='Cost Build'!G9 -> 120000 | H13: ='Cost Build'!H9 -> 120000 | I13: ='Cost Build'!I9 -> 120000 | ... K13: ='Cost Build'!K9 -> 120000
A14: Corporate Direct Costs | B14: ='Cost Build'!B10+'Cost Build'!B11 -> 97375 | C14: ='Cost Build'!C10+'Cost Build'!C11 -> 238500 | D14: ='Cost Build'!D10+'Cost Build'!D11 -> 397500 | E14: ='Cost Build'!E10+'Cost Build'!E11 -> 596250 | F14: ='Cost Build'!F10+'Cost Build'!F11 -> 894375 | G14: ='Cost Build'!G10+'Cost Build'!G11 -> 1033500 | H14: ='Cost Build'!H10+'Cost Build'!H11 -> 1152750 | I14: ='Cost Build'!I10+'Cost Build'!I11 -> 1291875 | ... K14: ='Cost Build'!K10+'Cost Build'!K11 -> 1590000
A15: Other Direct Costs | B15: ='Cost Build'!B12 -> 11696.013 | C15: ='Cost Build'!C12 -> 24111.069 | D15: ='Cost Build'!D12 -> 41394.901 | E15: ='Cost Build'!E12 -> 57542.214 | F15: ='Cost Build'!F12 -> 82620.308 | G15: ='Cost Build'!G12 -> 93521.63 | H15: ='Cost Build'!H12 -> 103950.91 | I15: ='Cost Build'!I12 -> 115582.1 | ... K15: ='Cost Build'!K12 -> 138836.77
A16: TOTAL COGS | B16: =SUM(B11:B15) -> 294447.25 | C16: =SUM(C11:C15) -> 582340.28 | D16: =SUM(D11:D15) -> 969874.24 | E16: =SUM(E11:E15) -> 1324865.6 | F16: =SUM(F11:F15) -> 1866585.4 | G16: =SUM(G11:G15) -> 2096243.9 | H16: =SUM(H11:H15) -> 2307192.6 | I16: =SUM(I11:I15) -> 2540925.3 | ... K16: =SUM(K11:K15) -> 2959847.8
A18: GROSS PROFIT | B18: =B9-B16 -> 290353.4 | C18: =C9-C16 -> 623213.18 | D18: =D9-D16 -> 1099870.8 | E18: =E9-E16 -> 1552245.1 | F18: =F9-F16 -> 2264430 | G18: =G9-G16 -> 2579837.7 | H18: =H9-H16 -> 2890352.8 | I18: =I9-I16 -> 3238179.9 | ... K18: =K9-K16 -> 3981990.9
A19: Gross Margin % | B19: =IF(B9=0,0,B18/B9) -> 0.49649978 | C19: =IF(C9=0,0,C18/C9) -> 0.51695192 | D19: =IF(D9=0,0,D18/D9) -> 0.531404 | E19: =IF(E9=0,0,E18/E9) -> 0.53951524 | F19: =IF(F9=0,0,F18/F9) -> 0.54815337 | G19: =IF(G9=0,0,G18/G9) -> 0.5517093 | H19: =IF(H9=0,0,H18/H9) -> 0.55609958 | I19: =IF(I9=0,0,I18/I9) -> 0.56032548 | ... K19: =IF(K9=0,0,K18/K9) -> 0.57362193
A21: Headcount Costs | B21: ='Cost Build'!B28 -> 675000 | C21: ='Cost Build'!C28 -> 927000 | D21: ='Cost Build'!D28 -> 954810 | E21: ='Cost Build'!E28 -> 1174681.5 | F21: ='Cost Build'!F28 -> 1209922 | G21: ='Cost Build'!G28 -> 1246219.6 | H21: ='Cost Build'!H28 -> 1492565.4 | I21: ='Cost Build'!I28 -> 1537342.3 | ... K21: ='Cost Build'!K28 -> 1859301.8
A22: Non-Headcount OpEx | B22: ='Cost Build'!B40 -> 331000 | C22: ='Cost Build'!C40 -> 347550 | D22: ='Cost Build'!D40 -> 364927.5 | E22: ='Cost Build'!E40 -> 383173.88 | F22: ='Cost Build'!F40 -> 402332.57 | G22: ='Cost Build'!G40 -> 422449.2 | H22: ='Cost Build'!H40 -> 443571.66 | I22: ='Cost Build'!I40 -> 465750.24 | ... K22: ='Cost Build'!K40 -> 513489.64
A23: TOTAL OPERATING EXPENSES | B23: =B21+B22 -> 1006000 | C23: =C21+C22 -> 1274550 | D23: =D21+D22 -> 1319737.5 | E23: =E21+E22 -> 1557855.4 | F23: =F21+F22 -> 1612254.5 | G23: =G21+G22 -> 1668668.8 | H23: =H21+H22 -> 1936137 | I23: =I21+I22 -> 2003092.6 | ... K23: =K21+K22 -> 2372791.4
A25: EBITDA | B25: =B18-B23 -> -715646.6 | C25: =C18-C23 -> -651336.82 | D25: =D18-D23 -> -219866.69 | E25: =E18-E23 -> -5610.34 | F25: =F18-F23 -> 652175.49 | G25: =G18-G23 -> 911168.83 | H25: =H18-H23 -> 954215.76 | I25: =I18-I23 -> 1235087.3 | ... K25: =K18-K23 -> 1609199.4
A26: EBITDA Margin % | B26: =IF(B9=0,0,B25/B9) -> -1.2237445 | C26: =IF(C9=0,0,C25/C9) -> -0.54028033 | D26: =IF(D9=0,0,D25/D9) -> -0.10622888 | E26: =IF(E9=0,0,E25/E9) -> -0.001949991 | F26: =IF(F9=0,0,F25/F9) -> 0.15787292 | G26: =IF(G9=0,0,G25/G9) -> 0.19485735 | H26: =IF(H9=0,0,H25/H9) -> 0.18358969 | I26: =IF(I9=0,0,I25/I9) -> 0.21371601 | ... K26: =IF(K9=0,0,K25/K9) -> 0.2318117
A28: Depreciation & Amortization | B28: =B9*Assumptions!B120 -> 17544.019 | C28: =C9*Assumptions!B120 -> 36166.604 | D28: =D9*Assumptions!B120 -> 62092.351 | E28: =E9*Assumptions!B120 -> 86313.32 | F28: =F9*Assumptions!B120 -> 123930.46 | G28: =G9*Assumptions!B120 -> 140282.45 | H28: =H9*Assumptions!B120 -> 155926.36 | I28: =I9*Assumptions!B120 -> 173373.16 | J28: =J9*Assumptions!B120 -> 188634.23 | K28: =K9*Assumptions!B120 -> 208255.16
A29: EBIT | B29: =B25-B28 -> -733190.62 | C29: =C25-C28 -> -687503.43 | D29: =D25-D28 -> -281959.05 | E29: =E25-E28 -> -91923.66 | F29: =F25-F28 -> 528245.02 | G29: =G25-G28 -> 770886.39 | H29: =H25-H28 -> 798289.4 | I29: =I25-I28 -> 1061714.2 | ... K29: =K25-K28 -> 1400944.3
A30: EBIT Margin % | B30: =IF(B9=0,0,B29/B9) -> -1.2537445 | C30: =IF(C9=0,0,C29/C9) -> -0.57028033 | D30: =IF(D9=0,0,D29/D9) -> -0.13622888 | E30: =IF(E9=0,0,E29/E9) -> -0.031949991 | F30: =IF(F9=0,0,F29/F9) -> 0.12787292 | G30: =IF(G9=0,0,G29/G9) -> 0.16485735 | H30: =IF(H9=0,0,H29/H9) -> 0.15358969 | I30: =IF(I9=0,0,I29/I9) -> 0.18371601 | ... K30: =IF(K9=0,0,K29/K9) -> 0.2018117
A32: Taxes (@ 25%) | B32: =MAX(0,B29*Assumptions!B108) -> 0 | C32: =MAX(0,C29*Assumptions!B108) -> 0 | D32: =MAX(0,D29*Assumptions!B108) -> 0 | E32: =MAX(0,E29*Assumptions!B108) -> 0 | F32: =MAX(0,F29*Assumptions!B108) -> 132061.26 | G32: =MAX(0,G29*Assumptions!B108) -> 192721.6 | H32: =MAX(0,H29*Assumptions!B108) -> 199572.35 | I32: =MAX(0,I29*Assumptions!B108) -> 265428.54 | J32: =MAX(0,J29*Assumptions!B108) -> 266062.75 | K32: =MAX(0,K29*Assumptions!B108) -> 350236.07
A33: NET INCOME (NOPAT) | B33: =B29-B32 -> -733190.62 | C33: =C29-C32 -> -687503.43 | D33: =D29-D32 -> -281959.05 | E33: =E29-E32 -> -91923.66 | F33: =F29-F32 -> 396183.77 | G33: =G29-G32 -> 578164.79 | H33: =H29-H32 -> 598717.05 | I33: =I29-I32 -> 796285.61 | ... K33: =K29-K32 -> 1050708.2
A34: Net Margin % | B34: =IF(B9=0,0,B33/B9) -> -1.2537445 | C34: =IF(C9=0,0,C33/C9) -> -0.57028033 | D34: =IF(D9=0,0,D33/D9) -> -0.13622888 | E34: =IF(E9=0,0,E33/E9) -> -0.031949991 | F34: =IF(F9=0,0,F33/F9) -> 0.095904694 | G34: =IF(G9=0,0,G33/G9) -> 0.12364301 | H34: =IF(H9=0,0,H33/H9) -> 0.11519227 | I34: =IF(I9=0,0,I33/I9) -> 0.13778701 | ... K34: =IF(K9=0,0,K33/K9) -> 0.15135878
A36: CASH FLOW STATEMENT
A37: Net Income (NOPAT) | B37: =B33 -> -733190.62 | C37: =C33 -> -687503.43 | D37: =D33 -> -281959.05 | E37: =E33 -> -91923.66 | F37: =F33 -> 396183.77 | G37: =G33 -> 578164.79 | H37: =H33 -> 598717.05 | I37: =I33 -> 796285.61 | ... K37: =K33 -> 1050708.2
A38: Add Back: D&A | B38: =B28 -> 17544.019 | C38: =C28 -> 36166.604 | D38: =D28 -> 62092.351 | E38: =E28 -> 86313.32 | F38: =F28 -> 123930.46 | G38: =G28 -> 140282.45 | H38: =H28 -> 155926.36 | I38: =I28 -> 173373.16 | ... K38: =K28 -> 208255.16
A39: Cash from Operations (before WC) | B39: =B37+B38 -> -715646.6 | C39: =C37+C38 -> -651336.82 | D39: =D37+D38 -> -219866.69 | E39: =E37+E38 -> -5610.34 | F39: =F37+F38 -> 520114.23 | G39: =G37+G38 -> 718447.24 | H39: =H37+H38 -> 754643.41 | I39: =I37+I38 -> 969658.77 | ... K39: =K37+K38 -> 1258963.4
A41: Change in Working Capital | B41: =B9*Assumptions!B119 -> 46784.052 | C41: =(C9-B9)*Assumptions!B119 -> 49660.225 | D41: =(D9-C9)*Assumptions!B119 -> 69135.327 | E41: =(E9-D9)*Assumptions!B119 -> 64589.25 | F41: =(F9-E9)*Assumptions!B119 -> 100312.38 | G41: =(G9-F9)*Assumptions!B119 -> 43605.288 | H41: =(H9-G9)*Assumptions!B119 -> 41717.108 | I41: =(I9-H9)*Assumptions!B119 -> 46524.784 | J41: =(J9-I9)*Assumptions!B119 -> 40696.189 | K41: =(K9-J9)*Assumptions!B119 -> 52322.486
A42: NET CASH FROM OPERATIONS | B42: =B39-B41 -> -762430.66 | C42: =C39-C41 -> -700997.05 | D42: =D39-D41 -> -289002.02 | E42: =E39-E41 -> -70199.59 | F42: =F39-F41 -> 419801.85 | G42: =G39-G41 -> 674841.95 | H42: =H39-H41 -> 712926.3 | I42: =I39-I41 -> 923133.99 | ... K42: =K39-K41 -> 1206640.9
A44: Capital Expenditures | B44: =B9*Assumptions!B118 -> 29240.032 | C44: =C9*Assumptions!B118 -> 60277.673 | D44: =D9*Assumptions!B118 -> 103487.25 | E44: =E9*Assumptions!B118 -> 143855.53 | F44: =F9*Assumptions!B118 -> 206550.77 | G44: =G9*Assumptions!B118 -> 233804.08 | H44: =H9*Assumptions!B118 -> 259877.27 | I44: =I9*Assumptions!B118 -> 288955.26 | J44: =J9*Assumptions!B118 -> 314390.38 | K44: =K9*Assumptions!B118 -> 347091.93
A45: NET CASH FROM INVESTING | B45: =-B44 -> -29240.032 | C45: =-C44 -> -60277.673 | D45: =-D44 -> -103487.25 | E45: =-E44 -> -143855.53 | F45: =-F44 -> -206550.77 | G45: =-G44 -> -233804.08 | H45: =-H44 -> -259877.27 | I45: =-I44 -> -288955.26 | ... K45: =-K44 -> -347091.93
A47: FREE CASH FLOW | B47: =B42+B45 -> -791670.69 | C47: =C42+C45 -> -761274.72 | D47: =D42+D45 -> -392489.27 | E47: =E42+E45 -> -214055.12 | F47: =F42+F45 -> 213251.08 | G47: =G42+G45 -> 441037.87 | H47: =H42+H45 -> 453049.04 | I47: =I42+I45 -> 634178.73 | ... K47: =K42+K45 -> 859548.95
A48: FCF Margin % | B48: =IF(B9=0,0,B47/B9) -> -1.3537445 | C48: =IF(C9=0,0,C47/C9) -> -0.63147322 | D48: =IF(D9=0,0,D47/D9) -> -0.1896317 | E48: =IF(E9=0,0,E47/E9) -> -0.074399336 | F48: =IF(F9=0,0,F47/F9) -> 0.051621952 | G48: =IF(G9=0,0,G47/G9) -> 0.094317832 | H48: =IF(H9=0,0,H47/H9) -> 0.087165961 | I48: =IF(I9=0,0,I47/I9) -> 0.10973649 | ... K48: =IF(K9=0,0,K47/K9) -> 0.12382151
A50: Cumulative Free Cash Flow | B50: =B47 -> -791670.69 | C50: =B50+C47 -> -1552945.4 | D50: =C50+D47 -> -1945434.7 | E50: =D50+E47 -> -2159489.8 | F50: =E50+F47 -> -1946238.7 | G50: =F50+G47 -> -1505200.9 | H50: =G50+H47 -> -1052151.8 | I50: =H50+I47 -> -417973.09 | J50: =I50+J47 -> 213762.82 | K50: =J50+K47 -> 1073311.8

Sheet Unit Economics
A1: UNIT ECONOMICS — BY CHANNEL & CUSTOMER TYPE
B2: Year 1 | C2: Year 2 | D2: Year 3 | E2: Year 4 | F2: Year 5 | G2: Year 6 | H2: Year 7 | I2: Year 8 | J2: Year 9 | K2: Year 10
A4: A. CONSUMER LESSON BOOKING — PLATFORM DIRECT
A5: Total Annual Bookings | B5: ='Revenue Build'!B12 -> 23284.8 | C5: ='Revenue Build'!C12 -> 38808 | D5: ='Revenue Build'!D12 -> 62092.8 | E5: ='Revenue Build'!E12 -> 77616 | F5: ='Revenue Build'!F12 -> 100900.8 | G5: ='Revenue Build'!G12 -> 108662.4 | H5: ='Revenue Build'!H12 -> 116424 | I5: ='Revenue Build'!I12 -> 124185.6 | ... K5: ='Revenue Build'!K12 -> 131947.2
A6: Marketing Spend Allocated to Platform | B6: ='Cost Build'!B34*IF('Revenue Build'!B78=0,0,'Revenue Build'!B20/'Revenue Build'!B78) -> 33998.438 | C6: ='Cost Build'!C34*IF('Revenue Build'!C78=0,0,'Revenue Build'!C20/'Revenue Build'!C78) -> 30103.764 | D6: ='Cost Build'!D34*IF('Revenue Build'!D78=0,0,'Revenue Build'!D20/'Revenue Build'!D78) -> 30697.309 | E6: ='Cost Build'!E34*IF('Revenue Build'!E78=0,0,'Revenue Build'!E20/'Revenue Build'!E78) -> 30177.73 | F6: ='Cost Build'!F34*IF('Revenue Build'!F78=0,0,'Revenue Build'!F20/'Revenue Build'!F78) -> 29846.756 | G6: ='Cost Build'!G34*IF('Revenue Build'!G78=0,0,'Revenue Build'!G20/'Revenue Build'!G78) -> 30770.289 | H6: ='Cost Build'!H34*IF('Revenue Build'!H78=0,0,'Revenue Build'!H20/'Revenue Build'!H78) -> 32210.049 | I6: ='Cost Build'!I34*IF('Revenue Build'!I78=0,0,'Revenue Build'!I20/'Revenue Build'!I78) -> 33468.046 | ... K6: ='Cost Build'!K34*IF('Revenue Build'!K78=0,0,'Revenue Build'!K20/'Revenue Build'!K78) -> 34635.968
A7: CAC — Platform Organic ($) | B7: =Assumptions!B132 -> 25 | C7: =Assumptions!B132 -> 25 | D7: =Assumptions!B132 -> 25 | E7: =Assumptions!B132 -> 25 | F7: =Assumptions!B132 -> 25 | G7: =Assumptions!B132 -> 25 | H7: =Assumptions!B132 -> 25 | I7: =Assumptions!B132 -> 25 | J7: =Assumptions!B132 -> 25 | K7: =Assumptions!B132 -> 25
A8: Avg Revenue per Booking (platform take) | B8: =IF(B5=0,0,'Revenue Build'!B20/B5) -> 11.385 | C8: =IF(C5=0,0,'Revenue Build'!C20/C5) -> 11.87505 | D8: =IF(D5=0,0,'Revenue Build'!D20/D5) -> 12.374739 | E8: =IF(E5=0,0,'Revenue Build'!E20/E5) -> 12.884356 | F8: =IF(F5=0,0,'Revenue Build'!F20/F5) -> 13.404199 | G8: =IF(G5=0,0,'Revenue Build'!G20/G5) -> 13.833325 | H8: =IF(H5=0,0,'Revenue Build'!H20/H5) -> 14.30705 | I8: =IF(I5=0,0,'Revenue Build'!I20/I5) -> 14.758199 | ... K8: =IF(K5=0,0,'Revenue Build'!K20/K5) -> 15.661621
A9: Avg Bookings per Consumer per Year | B9: 6 | C9: 6 | D9: 6 | E9: 6 | F9: 6 | G9: 6 | H9: 6 | I9: 6 | J9: 6 | K9: 6
A10: Revenue per Consumer per Year ($) | B10: =B8*B9 -> 68.31 | C10: =C8*C9 -> 71.2503 | D10: =D8*D9 -> 74.248434 | E10: =E8*E9 -> 77.306137 | F10: =F8*F9 -> 80.425196 | G10: =G8*G9 -> 82.999952 | H10: =H8*H9 -> 85.842301 | I10: =I8*I9 -> 88.549195 | ... K10: =K8*K9 -> 93.969725
A11: Consumer Retention Rate | B11: =1-Assumptions!B139 -> 0.7 | C11: =1-Assumptions!B139 -> 0.7 | D11: =1-Assumptions!B139 -> 0.7 | E11: =1-Assumptions!B139 -> 0.7 | F11: =1-Assumptions!B139 -> 0.7 | G11: =1-Assumptions!B139 -> 0.7 | H11: =1-Assumptions!B139 -> 0.7 | I11: =1-Assumptions!B139 -> 0.7 | J11: =1-Assumptions!B139 -> 0.7 | K11: =1-Assumptions!B139 -> 0.7
A12: Avg Consumer Lifetime (years) | B12: =1/(1-B11) -> 3.3333333 | C12: =1/(1-C11) -> 3.3333333 | D12: =1/(1-D11) -> 3.3333333 | E12: =1/(1-E11) -> 3.3333333 | F12: =1/(1-F11) -> 3.3333333 | G12: =1/(1-G11) -> 3.3333333 | H12: =1/(1-H11) -> 3.3333333 | I12: =1/(1-I11) -> 3.3333333 | ... K12: =1/(1-K11) -> 3.3333333
A13: LTV per Consumer ($) | B13: =B10*B12 -> 227.7 | C13: =C10*C12 -> 237.501 | D13: =D10*D12 -> 247.49478 | E13: =E10*E12 -> 257.68712 | F13: =F10*F12 -> 268.08399 | G13: =G10*G12 -> 276.66651 | H13: =H10*H12 -> 286.141 | I13: =I10*I12 -> 295.16398 | ... K13: =K10*K12 -> 313.23242
A14: LTV / CAC Ratio | B14: =IF(B7=0,0,B13/B7) -> 9.108 | C14: =IF(C7=0,0,C13/C7) -> 9.50004 | D14: =IF(D7=0,0,D13/D7) -> 9.8997912 | E14: =IF(E7=0,0,E13/E7) -> 10.307485 | F14: =IF(F7=0,0,F13/F7) -> 10.723359 | G14: =IF(G7=0,0,G13/G7) -> 11.06666 | H14: =IF(H7=0,0,H13/H7) -> 11.44564 | I14: =IF(I7=0,0,I13/I7) -> 11.806559 | ... K14: =IF(K7=0,0,K13/K7) -> 12.529297
A15: Payback Period (months) | B15: =IF(B10=0,0,B7/(B10/12)) -> 4.3917435 | C15: =IF(C10=0,0,C7/(C10/12)) -> 4.2105086 | D15: =IF(D10=0,0,D7/(D10/12)) -> 4.0404893 | E15: =IF(E10=0,0,E7/(E10/12)) -> 3.8806751 | F15: =IF(F10=0,0,F7/(F10/12)) -> 3.7301743 | G15: =IF(G10=0,0,G7/(G10/12)) -> 3.6144599 | H15: =IF(H10=0,0,H7/(H10/12)) -> 3.4947805 | I15: =IF(I10=0,0,I7/(I10/12)) -> 3.3879472 | ... K15: =IF(K10=0,0,K7/(K10/12)) -> 3.1925176
A16: Contribution Margin per Booking ($) | B16: =B8*(1-0.03)-B7/B9 -> 6.8767833 | C16: =C8*(1-0.03)-C7/C9 -> 7.3521318 | D16: =D8*(1-0.03)-D7/D9 -> 7.8368302 | E16: =E8*(1-0.03)-E7/E9 -> 8.3311588 | F16: =F8*(1-0.03)-F7/F9 -> 8.8354067 | G16: =G8*(1-0.03)-G7/G9 -> 9.2516589 | H16: =H8*(1-0.03)-H7/H9 -> 9.7111719 | I16: =I8*(1-0.03)-I7/I9 -> 10.148786 | ... K16: =K8*(1-0.03)-K7/K9 -> 11.025106
A18: B. CREATOR-DRIVEN CUSTOMER ACQUISITION
A19: Annual Bookings via Creators | B19: ='Revenue Build'!B34 -> 96 | C19: ='Revenue Build'!C34 -> 172.8 | D19: ='Revenue Build'!D34 -> 288 | E19: ='Revenue Build'!E34 -> 364.8 | F19: ='Revenue Build'!F34 -> 480 | G19: ='Revenue Build'!G34 -> 528 | H19: ='Revenue Build'!H34 -> 576 | I19: ='Revenue Build'!I34 -> 624 | ... K19: ='Revenue Build'!K34 -> 672
A20: Total Creator Program Spend ($) | B20: ='Cost Build'!B6+'Cost Build'!B7+'Cost Build'!B8 -> 96000 | C20: ='Cost Build'!C6+'Cost Build'!C7+'Cost Build'!C8 -> 172800 | D20: ='Cost Build'!D6+'Cost Build'!D7+'Cost Build'!D8 -> 288000 | E20: ='Cost Build'!E6+'Cost Build'!E7+'Cost Build'!E8 -> 364800 | F20: ='Cost Build'!F6+'Cost Build'!F7+'Cost Build'!F8 -> 480000 | G20: ='Cost Build'!G6+'Cost Build'!G7+'Cost Build'!G8 -> 528000 | H20: ='Cost Build'!H6+'Cost Build'!H7+'Cost Build'!H8 -> 576000 | I20: ='Cost Build'!I6+'Cost Build'!I7+'Cost Build'!I8 -> 624000 | ... K20: ='Cost Build'!K6+'Cost Build'!K7+'Cost Build'!K8 -> 672000
A21: CAC — Creator Channel ($) | B21: =IF(B19=0,0,B20/B19) -> 1000 | C21: =IF(C19=0,0,C20/C19) -> 1000 | D21: =IF(D19=0,0,D20/D19) -> 1000 | E21: =IF(E19=0,0,E20/E19) -> 1000 | F21: =IF(F19=0,0,F20/F19) -> 1000 | G21: =IF(G19=0,0,G20/G19) -> 1000 | H21: =IF(H19=0,0,H20/H19) -> 1000 | I21: =IF(I19=0,0,I20/I19) -> 1000 | ... K21: =IF(K19=0,0,K20/K19) -> 1000
A22: Revenue per Creator-Acquired Booking ($) | B22: =IF(B19=0,0,'Revenue Build'!B36/B19) -> 10.2 | C22: =IF(C19=0,0,'Revenue Build'!C36/C19) -> 10.506 | D22: =IF(D19=0,0,'Revenue Build'!D36/D19) -> 10.82118 | E22: =IF(E19=0,0,'Revenue Build'!E36/E19) -> 11.145815 | F22: =IF(F19=0,0,'Revenue Build'!F36/F19) -> 11.48019 | G22: =IF(G19=0,0,'Revenue Build'!G36/G19) -> 11.824596 | H22: =IF(H19=0,0,'Revenue Build'!H36/H19) -> 12.179333 | I22: =IF(I19=0,0,'Revenue Build'!I36/I19) -> 12.544713 | ... K22: =IF(K19=0,0,'Revenue Build'!K36/K19) -> 13.308686
A23: Contribution Margin after Acq Cost ($) | B23: =B22-B21 -> -989.8 | C23: =C22-C21 -> -989.494 | D23: =D22-D21 -> -989.17882 | E23: =E22-E21 -> -988.85418 | F23: =F22-F21 -> -988.51981 | G23: =G22-G21 -> -988.1754 | H23: =H22-H21 -> -987.82067 | I23: =I22-I21 -> -987.45529 | ... K23: =K22-K21 -> -986.69131
A24: Payback Period (months) | B24: =IF(B22=0,0,B21/(B22*12/B19*B19))*12 -> 98.039216 | C24: =IF(C22=0,0,C21/(C22*12/C19*C19))*12 -> 95.183705 | D24: =IF(D22=0,0,D21/(D22*12/D19*D19))*12 -> 92.411364 | E24: =IF(E22=0,0,E21/(E22*12/E19*E19))*12 -> 89.719771 | F24: =IF(F22=0,0,F21/(F22*12/F19*F19))*12 -> 87.106573 | G24: =IF(G22=0,0,G21/(G22*12/G19*G19))*12 -> 84.569489 | H24: =IF(H22=0,0,H21/(H22*12/H19*H19))*12 -> 82.1063 | I24: =IF(I22=0,0,I21/(I22*12/I19*I19))*12 -> 79.714854 | ... K24: =IF(K22=0,0,K21/(K22*12/K19*K19))*12 -> 75.138895
A25: Creator Program ROI | B25: =IF(B20=0,0,('Revenue Build'!B38-B20)/B20) -> -0.9898 | C25: =IF(C20=0,0,('Revenue Build'!C38-C20)/C20) -> -0.989494 | D25: =IF(D20=0,0,('Revenue Build'!D38-D20)/D20) -> -0.78084549 | E25: =IF(E20=0,0,('Revenue Build'!E38-E20)/E20) -> -0.67635418 | F25: =IF(F20=0,0,('Revenue Build'!F38-F20)/F20) -> -0.57185314 | G25: =IF(G20=0,0,('Revenue Build'!G38-G20)/G20) -> -0.46734207 | H25: =IF(H20=0,0,('Revenue Build'!H38-H20)/H20) -> -0.36282067 | I25: =IF(I20=0,0,('Revenue Build'!I38-I20)/I20) -> -0.25828862 | ... K25: =IF(K20=0,0,('Revenue Build'!K38-K20)/K20) -> 0.054975353
A27: C. VENUE-ACQUIRED CUSTOMER
A28: Annual Bookings via Venues | B28: ='Revenue Build'!B51 -> 120 | C28: ='Revenue Build'!C51 -> 180 | D28: ='Revenue Build'!D51 -> 300 | E28: ='Revenue Build'!E51 -> 360 | F28: ='Revenue Build'!F51 -> 480 | G28: ='Revenue Build'!G51 -> 480 | H28: ='Revenue Build'!H51 -> 480 | I28: ='Revenue Build'!I51 -> 480 | ... K28: ='Revenue Build'!K51 -> 480
A29: Total Venue Program Spend ($) | B29: ='Cost Build'!B9 -> 30000 | C29: ='Cost Build'!C9 -> 45000 | D29: ='Cost Build'!D9 -> 75000 | E29: ='Cost Build'!E9 -> 90000 | F29: ='Cost Build'!F9 -> 120000 | G29: ='Cost Build'!G9 -> 120000 | H29: ='Cost Build'!H9 -> 120000 | I29: ='Cost Build'!I9 -> 120000 | ... K29: ='Cost Build'!K9 -> 120000
A30: CAC — Venue Channel ($) | B30: =IF(B28=0,0,B29/B28) -> 250 | C30: =IF(C28=0,0,C29/C28) -> 250 | D30: =IF(D28=0,0,D29/D28) -> 250 | E30: =IF(E28=0,0,E29/E28) -> 250 | F30: =IF(F28=0,0,F29/F28) -> 250 | G30: =IF(G28=0,0,G29/G28) -> 250 | H30: =IF(H28=0,0,H29/H28) -> 250 | I30: =IF(I28=0,0,I29/I28) -> 250 | ... K30: =IF(K28=0,0,K29/K28) -> 250
A31: Revenue per Venue Booking ($) | B31: =IF(B28=0,0,'Revenue Build'!B53/B28) -> 10.2 | C31: =IF(C28=0,0,'Revenue Build'!C53/C28) -> 10.506 | D31: =IF(D28=0,0,'Revenue Build'!D53/D28) -> 10.82118 | E31: =IF(E28=0,0,'Revenue Build'!E53/E28) -> 11.145815 | F31: =IF(F28=0,0,'Revenue Build'!F53/F28) -> 11.48019 | G31: =IF(G28=0,0,'Revenue Build'!G53/G28) -> 11.824596 | H31: =IF(H28=0,0,'Revenue Build'!H53/H28) -> 12.179333 | I31: =IF(I28=0,0,'Revenue Build'!I53/I28) -> 12.544713 | ... K31: =IF(K28=0,0,'Revenue Build'!K53/K28) -> 13.308686
A32: Revenue per Venue Partner ($) | B32: =IF('Revenue Build'!B41=0,0,'Revenue Build'!B56/'Revenue Build'!B41) -> 65612 | C32: =IF('Revenue Build'!C41=0,0,'Revenue Build'!C56/'Revenue Build'!C41) -> 65630.36 | D32: =IF('Revenue Build'!D41=0,0,'Revenue Build'!D56/'Revenue Build'!D41) -> 65649.271 | E32: =IF('Revenue Build'!E41=0,0,'Revenue Build'!E56/'Revenue Build'!E41) -> 65668.749 | F32: =IF('Revenue Build'!F41=0,0,'Revenue Build'!F56/'Revenue Build'!F41) -> 65688.811 | G32: =IF('Revenue Build'!G41=0,0,'Revenue Build'!G56/'Revenue Build'!G41) -> 65709.476 | H32: =IF('Revenue Build'!H41=0,0,'Revenue Build'!H56/'Revenue Build'!H41) -> 65730.76 | I32: =IF('Revenue Build'!I41=0,0,'Revenue Build'!I56/'Revenue Build'!I41) -> 65752.683 | ... K32: =IF('Revenue Build'!K41=0,0,'Revenue Build'!K56/'Revenue Build'!K41) -> 65798.521
A33: Venue Program ROI | B33: =IF(B29=0,0,('Revenue Build'!B56-B29)/B29) -> 3.3741333 | C33: =IF(C29=0,0,('Revenue Build'!C56-C29)/C29) -> 3.3753573 | D33: =IF(D29=0,0,('Revenue Build'!D56-D29)/D29) -> 3.3766181 | E33: =IF(E29=0,0,('Revenue Build'!E56-E29)/E29) -> 3.3779166 | F33: =IF(F29=0,0,('Revenue Build'!F56-F29)/F29) -> 3.3792541 | G33: =IF(G29=0,0,('Revenue Build'!G56-G29)/G29) -> 3.3806317 | H33: =IF(H29=0,0,('Revenue Build'!H56-H29)/H29) -> 3.3820507 | I33: =IF(I29=0,0,('Revenue Build'!I56-I29)/I29) -> 3.3835122 | ... K33: =IF(K29=0,0,('Revenue Build'!K56-K29)/K29) -> 3.3865681
A35: D. CORPORATE CLIENT
A36: Active Clients | B36: ='Revenue Build'!B59 -> 5 | C36: ='Revenue Build'!C59 -> 12 | D36: ='Revenue Build'!D59 -> 20 | E36: ='Revenue Build'!E59 -> 30 | F36: ='Revenue Build'!F59 -> 45 | G36: ='Revenue Build'!G59 -> 52 | H36: ='Revenue Build'!H59 -> 58 | I36: ='Revenue Build'!I59 -> 65 | ... K36: ='Revenue Build'!K59 -> 80
A37: Revenue per Client ($) | B37: =IF(B36=0,0,'Revenue Build'!B71/B36) -> 37500 | C37: =IF(C36=0,0,'Revenue Build'!C71/C36) -> 45500 | D37: =IF(D36=0,0,'Revenue Build'!D71/D36) -> 45500 | E37: =IF(E36=0,0,'Revenue Build'!E71/E36) -> 45500 | F37: =IF(F36=0,0,'Revenue Build'!F71/F36) -> 45500 | G37: =IF(G36=0,0,'Revenue Build'!G71/G36) -> 45500 | H37: =IF(H36=0,0,'Revenue Build'!H71/H36) -> 45500 | I37: =IF(I36=0,0,'Revenue Build'!I71/I36) -> 45500 | ... K37: =IF(K36=0,0,'Revenue Build'!K71/K36) -> 45500
A38: Gross Margin per Client ($) | B38: =B37*(1-Assumptions!B80) -> 16875 | C38: =C37*(1-Assumptions!B80) -> 20475 | D38: =D37*(1-Assumptions!B80) -> 20475 | E38: =E37*(1-Assumptions!B80) -> 20475 | F38: =F37*(1-Assumptions!B80) -> 20475 | G38: =G37*(1-Assumptions!B80) -> 20475 | H38: =H37*(1-Assumptions!B80) -> 20475 | I38: =I37*(1-Assumptions!B80) -> 20475 | J38: =J37*(1-Assumptions!B80) -> 20475 | K38: =K37*(1-Assumptions!B80) -> 20475
A39: CAC — Corporate ($) | B39: =Assumptions!B135 -> 2500 | C39: =Assumptions!B135 -> 2500 | D39: =Assumptions!B135 -> 2500 | E39: =Assumptions!B135 -> 2500 | F39: =Assumptions!B135 -> 2500 | G39: =Assumptions!B135 -> 2500 | H39: =Assumptions!B135 -> 2500 | I39: =Assumptions!B135 -> 2500 | J39: =Assumptions!B135 -> 2500 | K39: =Assumptions!B135 -> 2500
A40: Client Retention Rate | B40: =Assumptions!B79 -> 0.8 | C40: =Assumptions!B79 -> 0.8 | D40: =Assumptions!B79 -> 0.8 | E40: =Assumptions!B79 -> 0.8 | F40: =Assumptions!B79 -> 0.8 | G40: =Assumptions!B79 -> 0.8 | H40: =Assumptions!B79 -> 0.8 | I40: =Assumptions!B79 -> 0.8 | J40: =Assumptions!B79 -> 0.8 | K40: =Assumptions!B79 -> 0.8
A41: Avg Client Lifetime (years) | B41: =IF((1-B40)=0,0,1/(1-B40)) -> 5 | C41: =IF((1-C40)=0,0,1/(1-C40)) -> 5 | D41: =IF((1-D40)=0,0,1/(1-D40)) -> 5 | E41: =IF((1-E40)=0,0,1/(1-E40)) -> 5 | F41: =IF((1-F40)=0,0,1/(1-F40)) -> 5 | G41: =IF((1-G40)=0,0,1/(1-G40)) -> 5 | H41: =IF((1-H40)=0,0,1/(1-H40)) -> 5 | I41: =IF((1-I40)=0,0,1/(1-I40)) -> 5 | ... K41: =IF((1-K40)=0,0,1/(1-K40)) -> 5
A42: LTV per Corporate Client ($) | B42: =B37*B41 -> 187500 | C42: =C37*C41 -> 227500 | D42: =D37*D41 -> 227500 | E42: =E37*E41 -> 227500 | F42: =F37*F41 -> 227500 | G42: =G37*G41 -> 227500 | H42: =H37*H41 -> 227500 | I42: =I37*I41 -> 227500 | ... K42: =K37*K41 -> 227500
A43: LTV / CAC Ratio | B43: =IF(B39=0,0,B42/B39) -> 75 | C43: =IF(C39=0,0,C42/C39) -> 91 | D43: =IF(D39=0,0,D42/D39) -> 91 | E43: =IF(E39=0,0,E42/E39) -> 91 | F43: =IF(F39=0,0,F42/F39) -> 91 | G43: =IF(G39=0,0,G42/G39) -> 91 | H43: =IF(H39=0,0,H42/H39) -> 91 | I43: =IF(I39=0,0,I42/I39) -> 91 | ... K43: =IF(K39=0,0,K42/K39) -> 91
A44: EBITDA Contribution per Client ($) | B44: =B38*0.65 -> 10968.75 | C44: =C38*0.65 -> 13308.75 | D44: =D38*0.65 -> 13308.75 | E44: =E38*0.65 -> 13308.75 | F44: =F38*0.65 -> 13308.75 | G44: =G38*0.65 -> 13308.75 | H44: =H38*0.65 -> 13308.75 | I44: =I38*0.65 -> 13308.75 | ... K44: =K38*0.65 -> 13308.75
A70: E. COHORT ECONOMICS — 5-YEAR CONSUMER COHORT MODEL
A71: Cohort Year 1 Customer | B71: Year 1 | C71: Year 2 | D71: Year 3 | E71: Year 4 | F71: Year 5
A72: Retention Rate | B72: 1 | C72: 0.7 | D72: 0.8 | E72: 0.85 | F72: 0.85
A73: Surviving Customers (from 100) | B73: 100 | C73: =B73*C72 -> 70 | D73: =C73*D72 -> 56 | E73: =D73*E72 -> 47.6 | F73: =E73*F72 -> 40.46
A74: Lessons per Customer | B74: 4 | C74: 6 | D74: 8 | E74: 8 | F74: 8
A75: Avg Lesson Price ($) | B75: =Assumptions!B27 -> 85 | C75: =B75*(1+Assumptions!B28) -> 87.55 | D75: =C75*(1+Assumptions!B28) -> 90.1765 | E75: =D75*(1+Assumptions!B28) -> 92.881795 | F75: =E75*(1+Assumptions!B28) -> 95.668249
A76: Gross Lesson Revenue | B76: =B73*B74*B75 -> 34000 | C76: =C73*C74*C75 -> 36771 | D76: =D73*D74*D75 -> 40399.072 | E76: =E73*E74*E75 -> 35369.388 | F76: =F73*F74*F75 -> 30965.899
A77: Platform Take Rate | B77: =Assumptions!B29 -> 0.12 | C77: =Assumptions!B29 -> 0.12 | D77: =Assumptions!B29 -> 0.12 | E77: =Assumptions!B29 -> 0.12 | F77: =Assumptions!B29 -> 0.12
A78: Platform Revenue per Cohort | B78: =B76*B77 -> 4080 | C78: =C76*C77 -> 4412.52 | D78: =D76*D77 -> 4847.8886 | E78: =E76*E77 -> 4244.3265 | F78: =F76*F77 -> 3715.9079
A79: Revenue per Surviving Customer | B79: =IF(B73=0,0,B78/B73) -> 40.8 | C79: =IF(C73=0,0,C78/C73) -> 63.036 | D79: =IF(D73=0,0,D78/D73) -> 86.56944 | E79: =IF(E73=0,0,E78/E73) -> 89.166523 | F79: =IF(F73=0,0,F78/F73) -> 91.841519
A80: Cumulative Revenue per Orig Customer | B80: =B78/100 -> 40.8 | C80: =B80+C78/100 -> 84.9252 | D80: =C80+D78/100 -> 133.40409 | E80: =D80+E78/100 -> 175.84735 | F80: =E80+F78/100 -> 213.00643
A82: COHORT LTV CALCULATION
A83: Total 5-Year Cumulative Rev / Customer | B83: =F80 -> 213.00643
A84: Less: CAC ($25) | B84: =-Assumptions!B132 -> -25
A85: Net Cohort Value per Customer | B85: =B83+B84 -> 188.00643
A86: Payback Period (months) | B86: =IF(B79=0,0,(-B84)/(B79/100/12)) -> 735.29412
A87: CAC Payback Multiple | B87: =IF(B84=0,0,B83/(-B84)) -> 8.5202572

Sheet DCF Valuation
A1: DCF VALUATION — PHILADELPHIA PGA GROWTH STRATEGY
B2: Year 1 | C2: Year 2 | D2: Year 3 | E2: Year 4 | F2: Year 5 | G2: Year 6 | H2: Year 7 | I2: Year 8 | J2: Year 9 | K2: Year 10
A4: KEY DCF ASSUMPTIONS
A5: WACC / Discount Rate | B5: =Assumptions!B109 -> 0.15
A6: Terminal Growth Rate | B6: =Assumptions!B110 -> 0.03
A7: Exit EV/EBITDA Multiple (Cross-Check) | B7: =Assumptions!B111 -> 12
A8: Tax Rate | B8: =Assumptions!B108 -> 0.25
A10: FREE CASH FLOW FORECAST
A11: Revenue | B11: ='10-Yr Projection'!B9 -> 584800.65 | C11: ='10-Yr Projection'!C9 -> 1205553.5 | D11: ='10-Yr Projection'!D9 -> 2069745 | E11: ='10-Yr Projection'!E9 -> 2877110.7 | F11: ='10-Yr Projection'!F9 -> 4131015.4 | G11: ='10-Yr Projection'!G9 -> 4676081.5 | H11: ='10-Yr Projection'!H9 -> 5197545.4 | I11: ='10-Yr Projection'!I9 -> 5779105.2 | ... K11: ='10-Yr Projection'!K9 -> 6941838.6
A12: EBITDA | B12: ='10-Yr Projection'!B25 -> -715646.6 | C12: ='10-Yr Projection'!C25 -> -651336.82 | D12: ='10-Yr Projection'!D25 -> -219866.69 | E12: ='10-Yr Projection'!E25 -> -5610.34 | F12: ='10-Yr Projection'!F25 -> 652175.49 | G12: ='10-Yr Projection'!G25 -> 911168.83 | H12: ='10-Yr Projection'!H25 -> 954215.76 | I12: ='10-Yr Projection'!I25 -> 1235087.3 | ... K12: ='10-Yr Projection'!K25 -> 1609199.4
A13: EBITDA Margin % | B13: =IF(B11=0,0,B12/B11) -> -1.2237445 | C13: =IF(C11=0,0,C12/C11) -> -0.54028033 | D13: =IF(D11=0,0,D12/D11) -> -0.10622888 | E13: =IF(E11=0,0,E12/E11) -> -0.001949991 | F13: =IF(F11=0,0,F12/F11) -> 0.15787292 | G13: =IF(G11=0,0,G12/G11) -> 0.19485735 | H13: =IF(H11=0,0,H12/H11) -> 0.18358969 | I13: =IF(I11=0,0,I12/I11) -> 0.21371601 | ... K13: =IF(K11=0,0,K12/K11) -> 0.2318117
A14: (-) Taxes on EBIT | B14: ='10-Yr Projection'!B32 -> 0 | C14: ='10-Yr Projection'!C32 -> 0 | D14: ='10-Yr Projection'!D32 -> 0 | E14: ='10-Yr Projection'!E32 -> 0 | F14: ='10-Yr Projection'!F32 -> 132061.26 | G14: ='10-Yr Projection'!G32 -> 192721.6 | H14: ='10-Yr Projection'!H32 -> 199572.35 | I14: ='10-Yr Projection'!I32 -> 265428.54 | ... K14: ='10-Yr Projection'!K32 -> 350236.07
A15: (-) Capex | B15: ='10-Yr Projection'!B44 -> 29240.032 | C15: ='10-Yr Projection'!C44 -> 60277.673 | D15: ='10-Yr Projection'!D44 -> 103487.25 | E15: ='10-Yr Projection'!E44 -> 143855.53 | F15: ='10-Yr Projection'!F44 -> 206550.77 | G15: ='10-Yr Projection'!G44 -> 233804.08 | H15: ='10-Yr Projection'!H44 -> 259877.27 | I15: ='10-Yr Projection'!I44 -> 288955.26 | ... K15: ='10-Yr Projection'!K44 -> 347091.93
A16: (-) Change in NWC | B16: ='10-Yr Projection'!B41 -> 46784.052 | C16: ='10-Yr Projection'!C41 -> 49660.225 | D16: ='10-Yr Projection'!D41 -> 69135.327 | E16: ='10-Yr Projection'!E41 -> 64589.25 | F16: ='10-Yr Projection'!F41 -> 100312.38 | G16: ='10-Yr Projection'!G41 -> 43605.288 | H16: ='10-Yr Projection'!H41 -> 41717.108 | I16: ='10-Yr Projection'!I41 -> 46524.784 | ... K16: ='10-Yr Projection'!K41 -> 52322.486
A17: (+) D&A | B17: ='10-Yr Projection'!B28 -> 17544.019 | C17: ='10-Yr Projection'!C28 -> 36166.604 | D17: ='10-Yr Projection'!D28 -> 62092.351 | E17: ='10-Yr Projection'!E28 -> 86313.32 | F17: ='10-Yr Projection'!F28 -> 123930.46 | G17: ='10-Yr Projection'!G28 -> 140282.45 | H17: ='10-Yr Projection'!H28 -> 155926.36 | I17: ='10-Yr Projection'!I28 -> 173373.16 | ... K17: ='10-Yr Projection'!K28 -> 208255.16
A18: UNLEVERED FREE CASH FLOW | B18: ='10-Yr Projection'!B47 -> -791670.69 | C18: ='10-Yr Projection'!C47 -> -761274.72 | D18: ='10-Yr Projection'!D47 -> -392489.27 | E18: ='10-Yr Projection'!E47 -> -214055.12 | F18: ='10-Yr Projection'!F47 -> 213251.08 | G18: ='10-Yr Projection'!G47 -> 441037.87 | H18: ='10-Yr Projection'!H47 -> 453049.04 | I18: ='10-Yr Projection'!I47 -> 634178.73 | ... K18: ='10-Yr Projection'!K47 -> 859548.95
A20: DCF CALCULATION
A21: Discount Period | B21: 1 | C21: 2 | D21: 3 | E21: 4 | F21: 5 | G21: 6 | H21: 7 | I21: 8 | J21: 9 | K21: 10
A22: Discount Factor | B22: =1/(1+$B$5)^B21 -> 0.86956522 | C22: =1/(1+$B$5)^C21 -> 0.75614367 | D22: =1/(1+$B$5)^D21 -> 0.65751623 | E22: =1/(1+$B$5)^E21 -> 0.57175325 | F22: =1/(1+$B$5)^F21 -> 0.49717674 | G22: =1/(1+$B$5)^G21 -> 0.4323276 | H22: =1/(1+$B$5)^H21 -> 0.37593704 | I22: =1/(1+$B$5)^I21 -> 0.32690177 | ... K22: =1/(1+$B$5)^K21 -> 0.24718471
A23: PV of Free Cash Flow | B23: =B18*B22 -> -688409.29 | C23: =C18*C22 -> -575633.06 | D23: =D18*D22 -> -258068.07 | E23: =E18*E22 -> -122386.71 | F23: =F18*F22 -> 106023.48 | G23: =G18*G22 -> 190672.84 | H23: =H18*H22 -> 170317.91 | I23: =I18*I22 -> 207314.15 | ... K23: =K18*K22 -> 212467.36
A25: Sum of PV of FCFs | B25: =SUM(B23:K23) -> -578122.62
A27: TERMINAL VALUE — PERPETUITY GROWTH METHOD
A28: Year 10 FCF | B28: =K18 -> 859548.95
A29: Terminal Value = FCF*(1+g)/(WACC-g) | B29: =B28*(1+B6)/(B5-B6) -> 7377795.2
A30: PV of Terminal Value | B30: =B29/(1+B5)^10 -> 1823678.1
A32: TERMINAL VALUE — EXIT MULTIPLE METHOD
A33: Year 10 EBITDA | B33: =K12 -> 1609199.4
A34: Exit Multiple (EV/EBITDA) | B34: =B7 -> 12
A35: Terminal Value (Multiple) | B35: =B33*B34 -> 19310393
A36: PV of Terminal Value (Multiple) | B36: =B35/(1+B5)^10 -> 4773233.9
A38: ENTERPRISE VALUE SUMMARY
A39: PV of Forecast FCFs | B39: =B25 -> -578122.62
A40: PV of Terminal Value (Perpetuity Growth) | B40: =B30 -> 1823678.1
A41: PV of Terminal Value (Exit Multiple) | B41: =B36 -> 4773233.9
A43: EV — Perpetuity Growth Method | B43: =B39+B40 -> 1245555.5
A44: EV — Exit Multiple Method | B44: =B39+B41 -> 4195111.3
A45: EV — Average of Both Methods | B45: =(B43+B44)/2 -> 2720333.4
A47: IMPLIED MULTIPLES
A48: EV / Year 1 Revenue | B48: =IF(B11=0,0,B45/B11) -> 4.6517277
A49: EV / Year 5 Revenue | B49: =IF(F11=0,0,B45/F11) -> 0.65851446
A50: EV / Year 10 Revenue | B50: =IF(K11=0,0,B45/K11) -> 0.39187505
A51: EV / Year 5 EBITDA | B51: =IF(F12=0,0,B45/F12) -> 4.1711678
A52: EV / Year 10 EBITDA | B52: =IF(K12=0,0,B45/K12) -> 1.6904886
A55: SUM-OF-THE-PARTS (SOTP) VALUATION CROSS-CHECK
A56: Segment | B56: Y10 Revenue | C56: Y10 EBITDA (est) | D56: Comp Multiple | E56: Segment Value | F56: % of Total
A57: Learn Golf Platform (SaaS/Marketplace) | B57: ='Revenue Build'!K20 -> 2066507 | C57: =B57*0.3 -> 619952.1 | D57: 15 | E57: =C57*D57 -> 9299281.6 | F57: =IF(E61=0,0,E57/E61) -> 0.49918752 | G57: High-margin recurring rev — SaaS comps
A58: Creator Network (Media/Advertising) | B58: ='Revenue Build'!K38 -> 708943.44 | C58: =B58*0.2 -> 141788.69 | D58: 10 | E58: =C58*D58 -> 1417886.9 | F58: =IF(E61=0,0,E58/E61) -> 0.076112485 | G58: Content/media platform comps
A59: Venue Partnerships (B2B Services) | B59: ='Revenue Build'!K56 -> 526388.17 | C59: =B59*0.15 -> 78958.225 | D59: 8 | E59: =C59*D59 -> 631665.8 | F59: =IF(E61=0,0,E59/E61) -> 0.033907962 | G59: B2B partnership / services comps
A60: Corporate Programs (Events/Services) | B60: ='Revenue Build'!K71 -> 3640000 | C60: =B60*0.25 -> 910000 | D60: 8 | E60: =C60*D60 -> 7280000 | F60: =IF(E61=0,0,E60/E61) -> 0.39079203 | G60: Events / corporate services comps
A61: TOTAL SOTP ENTERPRISE VALUE | B61: =SUM(B57:B60) -> 6941838.6 | C61: =SUM(C57:C60) -> 1750699 | E61: =SUM(E57:E60) -> 18628834 | F61: =SUM(F57:F60) -> 1
A62: PV of SOTP EV (discounted 10 years) | E62: =E61/(1+B5)^10 -> 4604762.9
A64: VALUATION COMPARISON
A65: Method | B65: Enterprise Value | C65: Notes
A66: DCF — Perpetuity Growth | B66: =B43 -> 1245555.5 | C66: WACC: 15%, TGR: 3%
A67: DCF — Exit Multiple | B67: =B44 -> 4195111.3 | C67: 12x Y10 EBITDA
A68: DCF — Average | B68: =B45 -> 2720333.4
A69: SOTP Cross-Check (PV) | B69: =E62 -> 4604762.9 | C69: Segment-level multiples
A70: Variance (DCF vs SOTP) | B70: =IF(B68=0,0,(B68-B69)/B68) -> -0.69272007

Sheet LBO Analysis
A1: LBO ANALYSIS — LEVERAGED BUYOUT MODEL
A3: TRANSACTION SUMMARY
A4: Entry Year EBITDA (Year 5 — first profitable year) | B4: ='10-Yr Projection'!F25 -> 652175.49
A5: Entry Multiple (EV/EBITDA) | B5: =Assumptions!B112 -> 10
A6: Enterprise Value at Entry | B6: =B4*B5 -> 6521754.9
A7: Transaction Fees (3% of EV) | B7: =B6*Assumptions!B121 -> 195652.65
A8: Total Transaction Value | B8: =B6+B7 -> 6717407.5
A10: SOURCES & USES
A11: Debt / Total Capital
A12: Total Debt | B12: =Assumptions!B113 -> 0.5
A13: Senior Debt (70%) | B13: =B8*B12 -> 3358703.8
A14: Mezzanine Debt (30%) | B14: =B13*Assumptions!B116 -> 2351092.6
A15: Total Equity Required | B15: =B13-B14 -> 1007611.1
A16: Management Rollover (15%) | B16: =B8-B13 -> 3358703.8
A17: Sponsor Equity | B17: =B16*Assumptions!B122 -> 503805.56
B18: =B16-B17 -> 2854898.2
A20: DEBT SCHEDULE — 5-YEAR HOLD PERIOD (Entry at Year 5, Exit at Year 10)
B21: Entry | C21: Year 1 (Y6) | D21: Year 2 (Y7) | E21: Year 3 (Y8) | F21: Year 4 (Y9) | G21: Year 5 (Y10, Exit)
A22: EBITDA | C22: ='10-Yr Projection'!G25 -> 911168.83 | D22: ='10-Yr Projection'!H25 -> 954215.76 | E22: ='10-Yr Projection'!I25 -> 1235087.3 | F22: ='10-Yr Projection'!J25 -> 1252885.2 | G22: ='10-Yr Projection'!K25 -> 1609199.4
A23: Interest — Senior (8%) | C23: =B32*Assumptions!B114 -> 188087.41 | D23: =C32*Assumptions!B114 -> 170232.53 | E23: =D32*Assumptions!B114 -> 150904.51 | F23: =E32*Assumptions!B114 -> 123422.16 | G23: =F32*Assumptions!B114 -> 95029.244
A24: Interest — Mezzanine (12%) | C24: =B36*Assumptions!B115 -> 120913.34 | D24: =C36*Assumptions!B115 -> 120913.34 | E24: =D36*Assumptions!B115 -> 120913.34 | F24: =E36*Assumptions!B115 -> 120913.34 | G24: =F36*Assumptions!B115 -> 120913.34
A25: Total Interest Expense | C25: =C23+C24 -> 309000.75 | D25: =D23+D24 -> 291145.86 | E25: =E23+E24 -> 271817.84 | F25: =F23+F24 -> 244335.5 | G25: =G23+G24 -> 215942.58
A26: Cash Available for Debt Paydown | C26: =MAX(0,C22-C25-C22*0.25-C22*0.05) -> 328817.44 | D26: =MAX(0,D22-D25-D22*0.25-D22*0.05) -> 376805.17 | E26: =MAX(0,E22-E25-E22*0.25-E22*0.05) -> 592743.27 | F26: =MAX(0,F22-F25-F22*0.25-F22*0.05) -> 632684.16 | G26: =MAX(0,G22-G25-G22*0.25-G22*0.05) -> 910497.03
A28: Senior Debt — Beginning | B28: =B14 -> 2351092.6 | C28: =B32 -> 2351092.6 | D28: =C32 -> 2127906.6 | E28: =D32 -> 1886306.3 | F28: =E32 -> 1542777.1 | G28: =F32 -> 1187865.5
A29: Mandatory Amortization (5%) | B29: =B14 -> 2351092.6 | C29: =C28*0.05 -> 117554.63 | D29: =D28*0.05 -> 106395.33 | E29: =E28*0.05 -> 94315.317 | F29: =F28*0.05 -> 77138.853 | G29: =G28*0.05 -> 59393.277
A30: Optional Prepayment | C30: =MIN(C26-C29,C28-C29)*0.5 -> 105631.4 | D30: =MIN(D26-D29,D28-D29)*0.5 -> 135204.92 | E30: =MIN(E26-E29,E28-E29)*0.5 -> 249213.98 | F30: =MIN(F26-F29,F28-F29)*0.5 -> 277772.65 | G30: =MIN(G26-G29,G28-G29)*0.5 -> 425551.88
A31: Senior Debt — Ending
B32: =B28 -> 2351092.6 | C32: =C28-C29-MAX(0,C30) -> 2127906.6 | D32: =D28-D29-MAX(0,D30) -> 1886306.3 | E32: =E28-E29-MAX(0,E30) -> 1542777.1 | F32: =F28-F29-MAX(0,F30) -> 1187865.5 | G32: =G28-G29-MAX(0,G30) -> 702920.39
A33: Mezzanine Debt — Beginning
A34: Mezzanine Interest (PIK if needed) | B34: =B15 -> 1007611.1 | C34: =B36 -> 1007611.1 | D34: =C36 -> 1007611.1 | E34: =D36 -> 1007611.1 | F34: =E36 -> 1007611.1 | G34: =F36 -> 1007611.1
A35: Mezzanine Debt — Ending | C35: =0 -> 0 | D35: =0 -> 0 | E35: =0 -> 0 | F35: =0 -> 0 | G35: =0 -> 0
B36: =B34 -> 1007611.1 | C36: =C34+C35 -> 1007611.1 | D36: =D34+D35 -> 1007611.1 | E36: =E34+E35 -> 1007611.1 | F36: =F34+F35 -> 1007611.1 | G36: =G34+G35 -> 1007611.1
A37: Total Debt — Ending
A38: Net Debt / EBITDA | B38: =B32+B36 -> 3358703.8 | C38: =C32+C36 -> 3135517.7 | D38: =D32+D36 -> 2893917.5 | E38: =E32+E36 -> 2550388.2 | F38: =F32+F36 -> 2195476.7 | G38: =G32+G36 -> 1710531.5
C39: =IF(C22=0,0,C38/C22) -> 3.4412039 | D39: =IF(D22=0,0,D38/D22) -> 3.0327706 | E39: =IF(E22=0,0,E38/E22) -> 2.0649457 | F39: =IF(F22=0,0,F38/F22) -> 1.7523366 | G39: =IF(G22=0,0,G38/G22) -> 1.0629705
A41: EXIT ANALYSIS & SPONSOR RETURNS
A42: Exit Year EBITDA (Year 10 = Y5 of hold) | B42: =G22 -> 1609199.4
A43: Exit Multiple (EV/EBITDA) | B43: =Assumptions!B111 -> 12
A44: Enterprise Value at Exit | B44: =B42*B43 -> 19310393
A45: Less: Remaining Debt | B45: =G38 -> 1710531.5
A46: Equity Value at Exit | B46: =B44-B45 -> 17599862
A47: Less: Management Share (15%) | B47: =B46*Assumptions!B122 -> 2639979.3
A48: Sponsor Equity at Exit | B48: =B46-B47 -> 14959883
A50: Sponsor Equity Invested | B50: =B18 -> 2854898.2
A51: Sponsor Equity Returned | B51: =B48 -> 14959883
A53: SPONSOR MOIC | B53: =IF(B50=0,0,B51/B50) -> 5.2400756
A54: SPONSOR IRR (5-year hold) | B54: =IF(B50=0,0,(B51/B50)^(1/5)-1) -> 0.39273186
A56: Total Debt Paydown ($) | B56: =B13-G38 -> 1648172.2
A57: % of Original Debt Repaid | B57: =IF(B13=0,0,B56/B13) -> 0.49071676

Sheet Scenario Analysis
A1: SCENARIO ANALYSIS — BASE / UPSIDE / DOWNSIDE / STRESS
A2: Scenario Driver | B2: Base Case | C2: Upside Case | D2: Downside Case | E2: Stress Case
A3: KEY SCENARIO ASSUMPTIONS
A4: Y5 Pro Onboarding Rate | B4: 0.65 | C4: 0.8 | D4: 0.4 | E4: 0.2
A5: Lessons per Pro per Week | B5: 8 | C5: 12 | D5: 5 | E5: 3
A6: Avg Lesson Price ($) | B6: 85 | C6: 95 | D6: 75 | E6: 65
A7: Platform Take Rate | B7: 0.12 | C7: 0.15 | D7: 0.1 | E7: 0.08
A8: Y5 Creator Count | B8: 50 | C8: 75 | D8: 25 | E8: 10
A9: Creator Booking Conversion | B9: 0.25 | C9: 0.35 | D9: 0.15 | E9: 0.08
A10: Y5 Venue Partners | B10: 8 | C10: 12 | D10: 4 | E10: 2
A11: Venue Booking Conversion | B11: 0.05 | C11: 0.08 | D11: 0.03 | E11: 0.01
A12: Y5 Corporate Clients | B12: 45 | C12: 70 | D12: 25 | E12: 10
A13: Avg Revenue per Event ($) | B13: 8000 | C13: 10000 | D13: 6000 | E13: 4000
A14: Annual Golf Growth Rate | B14: 0.03 | C14: 0.05 | D14: 0.01 | E14: -0.02
A15: OpEx Growth Rate | B15: 0.05 | C15: 0.04 | D15: 0.07 | E15: 0.1
... A18: Corporate Sponsorship Rate | B18: 0.2 | C18: 0.35 | D18: 0.1 | E18: 0.05
A20: SCENARIO OUTPUTS — YEAR 5
A21: Total Revenue | B21: ='Revenue Build'!F78 -> 4131015.4 | C21: =B21*1.4 -> 5783421.6 | D21: =B21*0.6 -> 2478609.3 | E21: =B21*0.35 -> 1445855.4
A22: Platform Revenue | B22: ='Revenue Build'!F20 -> 1352494.4 | C22: =B22*1.5 -> 2028741.7 | D22: =B22*0.55 -> 743871.94 | E22: =B22*0.3 -> 405748.33
A23: Creator Revenue | B23: ='Revenue Build'!F38 -> 205510.49 | C23: =B23*1.6 -> 328816.79 | D23: =B23*0.5 -> 102755.25 | E23: =B23*0.2 -> 41102.098
A24: Venue Revenue | B24: ='Revenue Build'!F56 -> 525510.49 | C24: =B24*1.5 -> 788265.74 | D24: =B24*0.5 -> 262755.25 | E24: =B24*0.25 -> 131377.62
A25: Corporate Revenue | B25: ='Revenue Build'!F71 -> 2047500 | C25: =B25*1.5 -> 3071250 | D25: =B25*0.55 -> 1126125 | E25: =B25*0.3 -> 614250
A26: Gross Profit | B26: ='Margin Analysis'!F43 -> 2264430 | C26: =C21*0.72 -> 4164063.5 | D26: =D21*0.58 -> 1437593.4 | E26: =E21*0.45 -> 650634.93
A27: Gross Margin % | B27: ='Margin Analysis'!F44 -> 0.54815337 | C27: =IF(C21=0,0,C26/C21) -> 0.72 | D27: =IF(D21=0,0,D26/D21) -> 0.58 | E27: =IF(E21=0,0,E26/E21) -> 0.45
A28: EBITDA | B28: ='Margin Analysis'!F47 -> 652175.49 | C28: =C21*0.28 -> 1619358 | D28: =D21*0.05 -> 123930.46 | E28: =E21*-0.1 -> -144585.54
A29: EBITDA Margin % | B29: ='Margin Analysis'!F48 -> 0.15787292 | C29: =IF(C21=0,0,C28/C21) -> 0.28 | D29: =IF(D21=0,0,D28/D21) -> 0.05 | E29: =IF(E21=0,0,E28/E21) -> -0.1
A30: Free Cash Flow | B30: ='Margin Analysis'!F59 -> 213251.08 | C30: =C28*0.65 -> 1052582.7 | D30: =D28*0.3 -> 37179.139 | E30: =E28*0.5 -> -72292.77
A31: FCF Margin % | B31: ='Margin Analysis'!F60 -> 0.051621952 | C31: =IF(C21=0,0,C30/C21) -> 0.182 | D31: =IF(D21=0,0,D30/D21) -> 0.015 | E31: =IF(E21=0,0,E30/E21) -> -0.05
A33: VALUATION ACROSS SCENARIOS
A34: Year 5 EBITDA | B34: =B28 -> 652175.49 | C34: =C28 -> 1619358 | D34: =D28 -> 123930.46 | E34: =E28 -> -144585.54
A35: Implied EV (Base 12x) | B35: =B34*12 -> 7826105.8 | C35: =C34*14 -> 22671013 | D35: =D34*8 -> 991443.7 | E35: =IF(E34<0,0,E34*6) -> 0
A36: DCF Enterprise Value | B36: ='DCF Valuation'!B45 -> 2720333.4 | C36: =B36*1.6 -> 4352533.4 | D36: =B36*0.35 -> 952116.69 | E36: =B36*0.1 -> 272033.34
A37: LBO Sponsor IRR (est.) | B37: 0.28 | C37: 0.42 | D37: 0.05 | E37: -0.15
A38: LBO MOIC (est.) | B38: 3.2 | C38: 5.1 | D38: 1.2 | E38: 0.5

Sheet Sensitivity Tables
A1: SENSITIVITY TABLES — KEY DRIVER ANALYSIS
A3: TABLE 1: DCF EV — WACC vs Terminal Growth Rate
A4: WACC \ TGR | B4: 0.01 | C4: 0.02 | D4: 0.025 | E4: 0.03 | F4: 0.035 | G4: 0.04 | H4: 0.05
A5: 0.1 | B5: ='DCF Valuation'!B25+('DCF Valuation'!K18*(1+0.01)/(0.1-0.01))/(1+0.1)^10 -> 3140847 | C5: ='DCF Valuation'!B25+('DCF Valuation'!K18*(1+0.02)/(0.1-0.02))/(1+0.1)^10 -> 3647142.3 | D5: ='DCF Valuation'!B25+('DCF Valuation'!K18*(1+0.025)/(0.1-0.025))/(1+0.1)^10 -> 3950919.6 | E5: ='DCF Valuation'!B25+('DCF Valuation'!K18*(1+0.03)/(0.1-0.03))/(1+0.1)^10 -> 4298093.5 | F5: ='DCF Valuation'!B25+('DCF Valuation'!K18*(1+0.035)/(0.1-0.035))/(1+0.1)^10 -> 4698678.9 | G5: ='DCF Valuation'!B25+('DCF Valuation'!K18*(1+0.04)/(0.1-0.04))/(1+0.1)^10 -> 5166028.4 | H5: ='DCF Valuation'!B25+('DCF Valuation'!K18*(1+0.05)/(0.1-0.05))/(1+0.1)^10 -> 6381137.3
A6: 0.12 | B6: ='DCF Valuation'!B25+('DCF Valuation'!K18*(1+0.01)/(0.12-0.01))/(1+0.12)^10 -> 1962961.7 | C6: ='DCF Valuation'!B25+('DCF Valuation'!K18*(1+0.02)/(0.12-0.02))/(1+0.12)^10 -> 2244745.3 | D6: ='DCF Valuation'!B25+('DCF Valuation'!K18*(1+0.025)/(0.12-0.025))/(1+0.12)^10 -> 2407883.2 | E6: ='DCF Valuation'!B25+('DCF Valuation'!K18*(1+0.03)/(0.12-0.03))/(1+0.12)^10 -> 2589147.5 | F6: ='DCF Valuation'!B25+('DCF Valuation'!K18*(1+0.035)/(0.12-0.035))/(1+0.12)^10 -> 2791737 | G6: ='DCF Valuation'!B25+('DCF Valuation'!K18*(1+0.04)/(0.12-0.04))/(1+0.12)^10 -> 3019650.2 | H6: ='DCF Valuation'!B25+('DCF Valuation'!K18*(1+0.05)/(0.12-0.05))/(1+0.12)^10 -> 3573153.8
A7: 0.13 | B7: ='DCF Valuation'!B25+('DCF Valuation'!K18*(1+0.01)/(0.13-0.01))/(1+0.13)^10 -> 1553087.7 | C7: ='DCF Valuation'!B25+('DCF Valuation'!K18*(1+0.02)/(0.13-0.02))/(1+0.13)^10 -> 1769853.5 | D7: ='DCF Valuation'!B25+('DCF Valuation'!K18*(1+0.025)/(0.13-0.025))/(1+0.13)^10 -> 1893719.6 | E7: ='DCF Valuation'!B25+('DCF Valuation'!K18*(1+0.03)/(0.13-0.03))/(1+0.13)^10 -> 2029972.4 | F7: ='DCF Valuation'!B25+('DCF Valuation'!K18*(1+0.035)/(0.13-0.035))/(1+0.13)^10 -> 2180567.5 | G7: ='DCF Valuation'!B25+('DCF Valuation'!K18*(1+0.04)/(0.13-0.04))/(1+0.13)^10 -> 2347895.5 | H7: ='DCF Valuation'!B25+('DCF Valuation'!K18*(1+0.05)/(0.13-0.05))/(1+0.13)^10 -> 2745299.4
A8: 0.15 | B8: ='DCF Valuation'!B25+('DCF Valuation'!K18*(1+0.01)/(0.15-0.01))/(1+0.15)^10 -> 954677.58 | C8: ='DCF Valuation'!B25+('DCF Valuation'!K18*(1+0.02)/(0.15-0.02))/(1+0.15)^10 -> 1088928.9 | D8: ='DCF Valuation'!B25+('DCF Valuation'!K18*(1+0.025)/(0.15-0.025))/(1+0.15)^10 -> 1164109.7 | E8: ='DCF Valuation'!B25+('DCF Valuation'!K18*(1+0.03)/(0.15-0.03))/(1+0.15)^10 -> 1245555.5 | F8: ='DCF Valuation'!B25+('DCF Valuation'!K18*(1+0.035)/(0.15-0.035))/(1+0.15)^10 -> 1334083.6 | G8: ='DCF Valuation'!B25+('DCF Valuation'!K18*(1+0.04)/(0.15-0.04))/(1+0.15)^10 -> 1430659.6 | H8: ='DCF Valuation'!B25+('DCF Valuation'!K18*(1+0.05)/(0.15-0.05))/(1+0.15)^10 -> 1652784.6
A9: 0.17 | B9: ='DCF Valuation'!B25+('DCF Valuation'!K18*(1+0.01)/(0.17-0.01))/(1+0.17)^10 -> 550667.99 | C9: ='DCF Valuation'!B25+('DCF Valuation'!K18*(1+0.02)/(0.17-0.02))/(1+0.17)^10 -> 637841.92 | D9: ='DCF Valuation'!B25+('DCF Valuation'!K18*(1+0.025)/(0.17-0.025))/(1+0.17)^10 -> 685937.88 | E9: ='DCF Valuation'!B25+('DCF Valuation'!K18*(1+0.03)/(0.17-0.03))/(1+0.17)^10 -> 737469.27 | F9: ='DCF Valuation'!B25+('DCF Valuation'!K18*(1+0.035)/(0.17-0.035))/(1+0.17)^10 -> 792817.79 | G9: ='DCF Valuation'!B25+('DCF Valuation'!K18*(1+0.04)/(0.17-0.04))/(1+0.17)^10 -> 852423.9 | H9: ='DCF Valuation'!B25+('DCF Valuation'!K18*(1+0.05)/(0.17-0.05))/(1+0.17)^10 -> 986537.63
A10: 0.18 | B10: ='DCF Valuation'!B25+('DCF Valuation'!K18*(1+0.01)/(0.18-0.01))/(1+0.18)^10 -> 397592.41 | C10: ='DCF Valuation'!B25+('DCF Valuation'!K18*(1+0.02)/(0.18-0.02))/(1+0.18)^10 -> 468838.92 | D10: ='DCF Valuation'!B25+('DCF Valuation'!K18*(1+0.025)/(0.18-0.025))/(1+0.18)^10 -> 507909.6 | E10: ='DCF Valuation'!B25+('DCF Valuation'!K18*(1+0.03)/(0.18-0.03))/(1+0.18)^10 -> 549584.98 | F10: ='DCF Valuation'!B25+('DCF Valuation'!K18*(1+0.035)/(0.18-0.035))/(1+0.18)^10 -> 594134.53 | G10: ='DCF Valuation'!B25+('DCF Valuation'!K18*(1+0.04)/(0.18-0.04))/(1+0.18)^10 -> 641866.18 | H10: ='DCF Valuation'!B25+('DCF Valuation'!K18*(1+0.05)/(0.18-0.05))/(1+0.18)^10 -> 748344.5
A11: 0.2 | B11: ='DCF Valuation'!B25+('DCF Valuation'!K18*(1+0.01)/(0.2-0.01))/(1+0.2)^10 -> 159825.66 | C11: ='DCF Valuation'!B25+('DCF Valuation'!K18*(1+0.02)/(0.2-0.02))/(1+0.2)^10 -> 208535.12 | D11: ='DCF Valuation'!B25+('DCF Valuation'!K18*(1+0.025)/(0.2-0.025))/(1+0.2)^10 -> 234977.4 | E11: ='DCF Valuation'!B25+('DCF Valuation'!K18*(1+0.03)/(0.2-0.03))/(1+0.2)^10 -> 262975.1 | F11: ='DCF Valuation'!B25+('DCF Valuation'!K18*(1+0.035)/(0.2-0.035))/(1+0.2)^10 -> 292669.64 | G11: ='DCF Valuation'!B25+('DCF Valuation'!K18*(1+0.04)/(0.2-0.04))/(1+0.2)^10 -> 324220.08 | H11: ='DCF Valuation'!B25+('DCF Valuation'!K18*(1+0.05)/(0.2-0.05))/(1+0.2)^10 -> 393631.06
A14: TABLE 2: LBO MOIC — Entry Multiple vs Exit Multiple
A15: Entry \ Exit | B15: 8x | C15: 10x | D15: 11x | E15: 12x | F15: 13x | G15: 14x | H15: 16x
A16: 7x | B16: =IF('LBO Analysis'!B42=0,0,('LBO Analysis'!B42*8-'LBO Analysis'!G38)/('LBO Analysis'!B4*7*0.5*(1-Assumptions!B122))) -> 5.7534981 | C16: =IF('LBO Analysis'!B42=0,0,('LBO Analysis'!B42*10-'LBO Analysis'!G38)/('LBO Analysis'!B4*7*0.5*(1-Assumptions!B122))) -> 7.4122767 | D16: =IF('LBO Analysis'!B42=0,0,('LBO Analysis'!B42*11-'LBO Analysis'!G38)/('LBO Analysis'!B4*7*0.5*(1-Assumptions!B122))) -> 8.241666 | E16: =IF('LBO Analysis'!B42=0,0,('LBO Analysis'!B42*12-'LBO Analysis'!G38)/('LBO Analysis'!B4*7*0.5*(1-Assumptions!B122))) -> 9.0710553 | F16: =IF('LBO Analysis'!B42=0,0,('LBO Analysis'!B42*13-'LBO Analysis'!G38)/('LBO Analysis'!B4*7*0.5*(1-Assumptions!B122))) -> 9.9004446 | G16: =IF('LBO Analysis'!B42=0,0,('LBO Analysis'!B42*14-'LBO Analysis'!G38)/('LBO Analysis'!B4*7*0.5*(1-Assumptions!B122))) -> 10.729834 | H16: =IF('LBO Analysis'!B42=0,0,('LBO Analysis'!B42*16-'LBO Analysis'!G38)/('LBO Analysis'!B4*7*0.5*(1-Assumptions!B122))) -> 12.388613
A17: 8x | B17: =IF('LBO Analysis'!B42=0,0,('LBO Analysis'!B42*8-'LBO Analysis'!G38)/('LBO Analysis'!B4*8*0.5*(1-Assumptions!B122))) -> 5.0343108 | C17: =IF('LBO Analysis'!B42=0,0,('LBO Analysis'!B42*10-'LBO Analysis'!G38)/('LBO Analysis'!B4*8*0.5*(1-Assumptions!B122))) -> 6.4857421 | D17: =IF('LBO Analysis'!B42=0,0,('LBO Analysis'!B42*11-'LBO Analysis'!G38)/('LBO Analysis'!B4*8*0.5*(1-Assumptions!B122))) -> 7.2114578 | E17: =IF('LBO Analysis'!B42=0,0,('LBO Analysis'!B42*12-'LBO Analysis'!G38)/('LBO Analysis'!B4*8*0.5*(1-Assumptions!B122))) -> 7.9371734 | F17: =IF('LBO Analysis'!B42=0,0,('LBO Analysis'!B42*13-'LBO Analysis'!G38)/('LBO Analysis'!B4*8*0.5*(1-Assumptions!B122))) -> 8.662889 | G17: =IF('LBO Analysis'!B42=0,0,('LBO Analysis'!B42*14-'LBO Analysis'!G38)/('LBO Analysis'!B4*8*0.5*(1-Assumptions!B122))) -> 9.3886047 | H17: =IF('LBO Analysis'!B42=0,0,('LBO Analysis'!B42*16-'LBO Analysis'!G38)/('LBO Analysis'!B4*8*0.5*(1-Assumptions!B122))) -> 10.840036
A18: 9x | B18: =IF('LBO Analysis'!B42=0,0,('LBO Analysis'!B42*8-'LBO Analysis'!G38)/('LBO Analysis'!B4*9*0.5*(1-Assumptions!B122))) -> 4.474943 | C18: =IF('LBO Analysis'!B42=0,0,('LBO Analysis'!B42*10-'LBO Analysis'!G38)/('LBO Analysis'!B4*9*0.5*(1-Assumptions!B122))) -> 5.7651041 | D18: =IF('LBO Analysis'!B42=0,0,('LBO Analysis'!B42*11-'LBO Analysis'!G38)/('LBO Analysis'!B4*9*0.5*(1-Assumptions!B122))) -> 6.4101847 | E18: =IF('LBO Analysis'!B42=0,0,('LBO Analysis'!B42*12-'LBO Analysis'!G38)/('LBO Analysis'!B4*9*0.5*(1-Assumptions!B122))) -> 7.0552652 | F18: =IF('LBO Analysis'!B42=0,0,('LBO Analysis'!B42*13-'LBO Analysis'!G38)/('LBO Analysis'!B4*9*0.5*(1-Assumptions!B122))) -> 7.7003458 | G18: =IF('LBO Analysis'!B42=0,0,('LBO Analysis'!B42*14-'LBO Analysis'!G38)/('LBO Analysis'!B4*9*0.5*(1-Assumptions!B122))) -> 8.3454264 | H18: =IF('LBO Analysis'!B42=0,0,('LBO Analysis'!B42*16-'LBO Analysis'!G38)/('LBO Analysis'!B4*9*0.5*(1-Assumptions!B122))) -> 9.6355875
A19: 10x | B19: =IF('LBO Analysis'!B42=0,0,('LBO Analysis'!B42*8-'LBO Analysis'!G38)/('LBO Analysis'!B4*10*0.5*(1-Assumptions!B122))) -> 4.0274487 | C19: =IF('LBO Analysis'!B42=0,0,('LBO Analysis'!B42*10-'LBO Analysis'!G38)/('LBO Analysis'!B4*10*0.5*(1-Assumptions!B122))) -> 5.1885937 | D19: =IF('LBO Analysis'!B42=0,0,('LBO Analysis'!B42*11-'LBO Analysis'!G38)/('LBO Analysis'!B4*10*0.5*(1-Assumptions!B122))) -> 5.7691662 | E19: =IF('LBO Analysis'!B42=0,0,('LBO Analysis'!B42*12-'LBO Analysis'!G38)/('LBO Analysis'!B4*10*0.5*(1-Assumptions!B122))) -> 6.3497387 | F19: =IF('LBO Analysis'!B42=0,0,('LBO Analysis'!B42*13-'LBO Analysis'!G38)/('LBO Analysis'!B4*10*0.5*(1-Assumptions!B122))) -> 6.9303112 | G19: =IF('LBO Analysis'!B42=0,0,('LBO Analysis'!B42*14-'LBO Analysis'!G38)/('LBO Analysis'!B4*10*0.5*(1-Assumptions!B122))) -> 7.5108838 | H19: =IF('LBO Analysis'!B42=0,0,('LBO Analysis'!B42*16-'LBO Analysis'!G38)/('LBO Analysis'!B4*10*0.5*(1-Assumptions!B122))) -> 8.6720288
A20: 11x | B20: =IF('LBO Analysis'!B42=0,0,('LBO Analysis'!B42*8-'LBO Analysis'!G38)/('LBO Analysis'!B4*11*0.5*(1-Assumptions!B122))) -> 3.661317 | C20: =IF('LBO Analysis'!B42=0,0,('LBO Analysis'!B42*10-'LBO Analysis'!G38)/('LBO Analysis'!B4*11*0.5*(1-Assumptions!B122))) -> 4.7169034 | D20: =IF('LBO Analysis'!B42=0,0,('LBO Analysis'!B42*11-'LBO Analysis'!G38)/('LBO Analysis'!B4*11*0.5*(1-Assumptions!B122))) -> 5.2446966 | E20: =IF('LBO Analysis'!B42=0,0,('LBO Analysis'!B42*12-'LBO Analysis'!G38)/('LBO Analysis'!B4*11*0.5*(1-Assumptions!B122))) -> 5.7724897 | F20: =IF('LBO Analysis'!B42=0,0,('LBO Analysis'!B42*13-'LBO Analysis'!G38)/('LBO Analysis'!B4*11*0.5*(1-Assumptions!B122))) -> 6.3002829 | G20: =IF('LBO Analysis'!B42=0,0,('LBO Analysis'!B42*14-'LBO Analysis'!G38)/('LBO Analysis'!B4*11*0.5*(1-Assumptions!B122))) -> 6.8280761 | H20: =IF('LBO Analysis'!B42=0,0,('LBO Analysis'!B42*16-'LBO Analysis'!G38)/('LBO Analysis'!B4*11*0.5*(1-Assumptions!B122))) -> 7.8836625
A21: 12x | B21: =IF('LBO Analysis'!B42=0,0,('LBO Analysis'!B42*8-'LBO Analysis'!G38)/('LBO Analysis'!B4*12*0.5*(1-Assumptions!B122))) -> 3.3562072 | C21: =IF('LBO Analysis'!B42=0,0,('LBO Analysis'!B42*10-'LBO Analysis'!G38)/('LBO Analysis'!B4*12*0.5*(1-Assumptions!B122))) -> 4.3238281 | D21: =IF('LBO Analysis'!B42=0,0,('LBO Analysis'!B42*11-'LBO Analysis'!G38)/('LBO Analysis'!B4*12*0.5*(1-Assumptions!B122))) -> 4.8076385 | E21: =IF('LBO Analysis'!B42=0,0,('LBO Analysis'!B42*12-'LBO Analysis'!G38)/('LBO Analysis'!B4*12*0.5*(1-Assumptions!B122))) -> 5.2914489 | F21: =IF('LBO Analysis'!B42=0,0,('LBO Analysis'!B42*13-'LBO Analysis'!G38)/('LBO Analysis'!B4*12*0.5*(1-Assumptions!B122))) -> 5.7752594 | G21: =IF('LBO Analysis'!B42=0,0,('LBO Analysis'!B42*14-'LBO Analysis'!G38)/('LBO Analysis'!B4*12*0.5*(1-Assumptions!B122))) -> 6.2590698 | H21: =IF('LBO Analysis'!B42=0,0,('LBO Analysis'!B42*16-'LBO Analysis'!G38)/('LBO Analysis'!B4*12*0.5*(1-Assumptions!B122))) -> 7.2266907
A22: 14x | B22: =IF('LBO Analysis'!B42=0,0,('LBO Analysis'!B42*8-'LBO Analysis'!G38)/('LBO Analysis'!B4*14*0.5*(1-Assumptions!B122))) -> 2.876749 | C22: =IF('LBO Analysis'!B42=0,0,('LBO Analysis'!B42*10-'LBO Analysis'!G38)/('LBO Analysis'!B4*14*0.5*(1-Assumptions!B122))) -> 3.7061384 | D22: =IF('LBO Analysis'!B42=0,0,('LBO Analysis'!B42*11-'LBO Analysis'!G38)/('LBO Analysis'!B4*14*0.5*(1-Assumptions!B122))) -> 4.120833 | E22: =IF('LBO Analysis'!B42=0,0,('LBO Analysis'!B42*12-'LBO Analysis'!G38)/('LBO Analysis'!B4*14*0.5*(1-Assumptions!B122))) -> 4.5355277 | F22: =IF('LBO Analysis'!B42=0,0,('LBO Analysis'!B42*13-'LBO Analysis'!G38)/('LBO Analysis'!B4*14*0.5*(1-Assumptions!B122))) -> 4.9502223 | G22: =IF('LBO Analysis'!B42=0,0,('LBO Analysis'!B42*14-'LBO Analysis'!G38)/('LBO Analysis'!B4*14*0.5*(1-Assumptions!B122))) -> 5.364917 | H22: =IF('LBO Analysis'!B42=0,0,('LBO Analysis'!B42*16-'LBO Analysis'!G38)/('LBO Analysis'!B4*14*0.5*(1-Assumptions!B122))) -> 6.1943063
A25: TABLE 3: Y5 Platform Rev ($) — Lesson Price vs Take Rate
A26: Price \ Take | B26: 0.08 | C26: 0.1 | D26: 0.11 | E26: 0.12 | F26: 0.13 | G26: 0.15 | H26: 0.18
A27: 65 | B27: ='Revenue Build'!F12*65*0.08 -> 524684.16 | C27: ='Revenue Build'!F12*65*0.1 -> 655855.2 | D27: ='Revenue Build'!F12*65*0.11 -> 721440.72 | E27: ='Revenue Build'!F12*65*0.12 -> 787026.24 | F27: ='Revenue Build'!F12*65*0.13 -> 852611.76 | G27: ='Revenue Build'!F12*65*0.15 -> 983782.8 | H27: ='Revenue Build'!F12*65*0.18 -> 1180539.4
A28: 75 | B28: ='Revenue Build'!F12*75*0.08 -> 605404.8 | C28: ='Revenue Build'!F12*75*0.1 -> 756756 | D28: ='Revenue Build'!F12*75*0.11 -> 832431.6 | E28: ='Revenue Build'!F12*75*0.12 -> 908107.2 | F28: ='Revenue Build'!F12*75*0.13 -> 983782.8 | G28: ='Revenue Build'!F12*75*0.15 -> 1135134 | H28: ='Revenue Build'!F12*75*0.18 -> 1362160.8
A29: 80 | B29: ='Revenue Build'!F12*80*0.08 -> 645765.12 | C29: ='Revenue Build'!F12*80*0.1 -> 807206.4 | D29: ='Revenue Build'!F12*80*0.11 -> 887927.04 | E29: ='Revenue Build'!F12*80*0.12 -> 968647.68 | F29: ='Revenue Build'!F12*80*0.13 -> 1049368.3 | G29: ='Revenue Build'!F12*80*0.15 -> 1210809.6 | H29: ='Revenue Build'!F12*80*0.18 -> 1452971.5
A30: 85 | B30: ='Revenue Build'!F12*85*0.08 -> 686125.44 | C30: ='Revenue Build'!F12*85*0.1 -> 857656.8 | D30: ='Revenue Build'!F12*85*0.11 -> 943422.48 | E30: ='Revenue Build'!F12*85*0.12 -> 1029188.2 | F30: ='Revenue Build'!F12*85*0.13 -> 1114953.8 | G30: ='Revenue Build'!F12*85*0.15 -> 1286485.2 | H30: ='Revenue Build'!F12*85*0.18 -> 1543782.2
A31: 90 | B31: ='Revenue Build'!F12*90*0.08 -> 726485.76 | C31: ='Revenue Build'!F12*90*0.1 -> 908107.2 | D31: ='Revenue Build'!F12*90*0.11 -> 998917.92 | E31: ='Revenue Build'!F12*90*0.12 -> 1089728.6 | F31: ='Revenue Build'!F12*90*0.13 -> 1180539.4 | G31: ='Revenue Build'!F12*90*0.15 -> 1362160.8 | H31: ='Revenue Build'!F12*90*0.18 -> 1634593
A32: 95 | B32: ='Revenue Build'!F12*95*0.08 -> 766846.08 | C32: ='Revenue Build'!F12*95*0.1 -> 958557.6 | D32: ='Revenue Build'!F12*95*0.11 -> 1054413.4 | E32: ='Revenue Build'!F12*95*0.12 -> 1150269.1 | F32: ='Revenue Build'!F12*95*0.13 -> 1246124.9 | G32: ='Revenue Build'!F12*95*0.15 -> 1437836.4 | H32: ='Revenue Build'!F12*95*0.18 -> 1725403.7
A33: 105 | B33: ='Revenue Build'!F12*105*0.08 -> 847566.72 | C33: ='Revenue Build'!F12*105*0.1 -> 1059458.4 | D33: ='Revenue Build'!F12*105*0.11 -> 1165404.2 | E33: ='Revenue Build'!F12*105*0.12 -> 1271350.1 | F33: ='Revenue Build'!F12*105*0.13 -> 1377295.9 | G33: ='Revenue Build'!F12*105*0.15 -> 1589187.6 | H33: ='Revenue Build'!F12*105*0.18 -> 1907025.1
A36: TABLE 4: Y5 Corporate Rev ($) — # Clients vs Avg Event Value
A37: Clients \ $/Event | B37: 4000 | C37: 6000 | D37: 7000 | E37: 8000 | F37: 9000 | G37: 10000 | H37: 12000
A38: 15 | B38: =15*4*4000+15*0.3*15000+15*0.2*5000 -> 322500 | C38: =15*4*6000+15*0.3*15000+15*0.2*5000 -> 442500 | D38: =15*4*7000+15*0.3*15000+15*0.2*5000 -> 502500 | E38: =15*4*8000+15*0.3*15000+15*0.2*5000 -> 562500 | F38: =15*4*9000+15*0.3*15000+15*0.2*5000 -> 622500 | G38: =15*4*10000+15*0.3*15000+15*0.2*5000 -> 682500 | H38: =15*4*12000+15*0.3*15000+15*0.2*5000 -> 802500
A39: 25 | B39: =25*4*4000+25*0.3*15000+25*0.2*5000 -> 537500 | C39: =25*4*6000+25*0.3*15000+25*0.2*5000 -> 737500 | D39: =25*4*7000+25*0.3*15000+25*0.2*5000 -> 837500 | E39: =25*4*8000+25*0.3*15000+25*0.2*5000 -> 937500 | F39: =25*4*9000+25*0.3*15000+25*0.2*5000 -> 1037500 | G39: =25*4*10000+25*0.3*15000+25*0.2*5000 -> 1137500 | H39: =25*4*12000+25*0.3*15000+25*0.2*5000 -> 1337500
A40: 35 | B40: =35*4*4000+35*0.3*15000+35*0.2*5000 -> 752500 | C40: =35*4*6000+35*0.3*15000+35*0.2*5000 -> 1032500 | D40: =35*4*7000+35*0.3*15000+35*0.2*5000 -> 1172500 | E40: =35*4*8000+35*0.3*15000+35*0.2*5000 -> 1312500 | F40: =35*4*9000+35*0.3*15000+35*0.2*5000 -> 1452500 | G40: =35*4*10000+35*0.3*15000+35*0.2*5000 -> 1592500 | H40: =35*4*12000+35*0.3*15000+35*0.2*5000 -> 1872500
A41: 45 | B41: =45*4*4000+45*0.3*15000+45*0.2*5000 -> 967500 | C41: =45*4*6000+45*0.3*15000+45*0.2*5000 -> 1327500 | D41: =45*4*7000+45*0.3*15000+45*0.2*5000 -> 1507500 | E41: =45*4*8000+45*0.3*15000+45*0.2*5000 -> 1687500 | F41: =45*4*9000+45*0.3*15000+45*0.2*5000 -> 1867500 | G41: =45*4*10000+45*0.3*15000+45*0.2*5000 -> 2047500 | H41: =45*4*12000+45*0.3*15000+45*0.2*5000 -> 2407500
A42: 55 | B42: =55*4*4000+55*0.3*15000+55*0.2*5000 -> 1182500 | C42: =55*4*6000+55*0.3*15000+55*0.2*5000 -> 1622500 | D42: =55*4*7000+55*0.3*15000+55*0.2*5000 -> 1842500 | E42: =55*4*8000+55*0.3*15000+55*0.2*5000 -> 2062500 | F42: =55*4*9000+55*0.3*15000+55*0.2*5000 -> 2282500 | G42: =55*4*10000+55*0.3*15000+55*0.2*5000 -> 2502500 | H42: =55*4*12000+55*0.3*15000+55*0.2*5000 -> 2942500
A43: 65 | B43: =65*4*4000+65*0.3*15000+65*0.2*5000 -> 1397500 | C43: =65*4*6000+65*0.3*15000+65*0.2*5000 -> 1917500 | D43: =65*4*7000+65*0.3*15000+65*0.2*5000 -> 2177500 | E43: =65*4*8000+65*0.3*15000+65*0.2*5000 -> 2437500 | F43: =65*4*9000+65*0.3*15000+65*0.2*5000 -> 2697500 | G43: =65*4*10000+65*0.3*15000+65*0.2*5000 -> 2957500 | H43: =65*4*12000+65*0.3*15000+65*0.2*5000 -> 3477500
A44: 80 | B44: =80*4*4000+80*0.3*15000+80*0.2*5000 -> 1720000 | C44: =80*4*6000+80*0.3*15000+80*0.2*5000 -> 2360000 | D44: =80*4*7000+80*0.3*15000+80*0.2*5000 -> 2680000 | E44: =80*4*8000+80*0.3*15000+80*0.2*5000 -> 3000000 | F44: =80*4*9000+80*0.3*15000+80*0.2*5000 -> 3320000 | G44: =80*4*10000+80*0.3*15000+80*0.2*5000 -> 3640000 | H44: =80*4*12000+80*0.3*15000+80*0.2*5000 -> 4280000
A46: TABLE 5: Creator ROI — Conversion Rate vs Creator Cost/Month
A47: Conv% \ $/mo | B47: 300 | C47: 400 | D47: 500 | E47: 600 | F47: 700 | G47: 800 | H47: 1000
A48: 0.1 | B48: =(50000*0.04*0.02*0.08*0.1*12*85*0.12-300*12)/300*12 -> -142.43328 | C48: =(50000*0.04*0.02*0.08*0.1*12*85*0.12-400*12)/400*12 -> -142.82496 | D48: =(50000*0.04*0.02*0.08*0.1*12*85*0.12-500*12)/500*12 -> -143.05997 | E48: =(50000*0.04*0.02*0.08*0.1*12*85*0.12-600*12)/600*12 -> -143.21664 | F48: =(50000*0.04*0.02*0.08*0.1*12*85*0.12-700*12)/700*12 -> -143.32855 | G48: =(50000*0.04*0.02*0.08*0.1*12*85*0.12-800*12)/800*12 -> -143.41248 | H48: =(50000*0.04*0.02*0.08*0.1*12*85*0.12-1000*12)/1000*12 -> -143.52998
A49: 0.15 | B49: =(50000*0.04*0.02*0.08*0.15*12*85*0.12-300*12)/300*12 -> -141.64992 | C49: =(50000*0.04*0.02*0.08*0.15*12*85*0.12-400*12)/400*12 -> -142.23744 | D49: =(50000*0.04*0.02*0.08*0.15*12*85*0.12-500*12)/500*12 -> -142.58995 | E49: =(50000*0.04*0.02*0.08*0.15*12*85*0.12-600*12)/600*12 -> -142.82496 | F49: =(50000*0.04*0.02*0.08*0.15*12*85*0.12-700*12)/700*12 -> -142.99282 | G49: =(50000*0.04*0.02*0.08*0.15*12*85*0.12-800*12)/800*12 -> -143.11872 | H49: =(50000*0.04*0.02*0.08*0.15*12*85*0.12-1000*12)/1000*12 -> -143.29498
A50: 0.2 | B50: =(50000*0.04*0.02*0.08*0.2*12*85*0.12-300*12)/300*12 -> -140.86656 | C50: =(50000*0.04*0.02*0.08*0.2*12*85*0.12-400*12)/400*12 -> -141.64992 | D50: =(50000*0.04*0.02*0.08*0.2*12*85*0.12-500*12)/500*12 -> -142.11994 | E50: =(50000*0.04*0.02*0.08*0.2*12*85*0.12-600*12)/600*12 -> -142.43328 | F50: =(50000*0.04*0.02*0.08*0.2*12*85*0.12-700*12)/700*12 -> -142.6571 | G50: =(50000*0.04*0.02*0.08*0.2*12*85*0.12-800*12)/800*12 -> -142.82496 | H50: =(50000*0.04*0.02*0.08*0.2*12*85*0.12-1000*12)/1000*12 -> -143.05997
A51: 0.25 | B51: =(50000*0.04*0.02*0.08*0.25*12*85*0.12-300*12)/300*12 -> -140.0832 | C51: =(50000*0.04*0.02*0.08*0.25*12*85*0.12-400*12)/400*12 -> -141.0624 | D51: =(50000*0.04*0.02*0.08*0.25*12*85*0.12-500*12)/500*12 -> -141.64992 | E51: =(50000*0.04*0.02*0.08*0.25*12*85*0.12-600*12)/600*12 -> -142.0416 | F51: =(50000*0.04*0.02*0.08*0.25*12*85*0.12-700*12)/700*12 -> -142.32137 | G51: =(50000*0.04*0.02*0.08*0.25*12*85*0.12-800*12)/800*12 -> -142.5312 | H51: =(50000*0.04*0.02*0.08*0.25*12*85*0.12-1000*12)/1000*12 -> -142.82496
A52: 0.3 | B52: =(50000*0.04*0.02*0.08*0.3*12*85*0.12-300*12)/300*12 -> -139.29984 | C52: =(50000*0.04*0.02*0.08*0.3*12*85*0.12-400*12)/400*12 -> -140.47488 | D52: =(50000*0.04*0.02*0.08*0.3*12*85*0.12-500*12)/500*12 -> -141.1799 | E52: =(50000*0.04*0.02*0.08*0.3*12*85*0.12-600*12)/600*12 -> -141.64992 | F52: =(50000*0.04*0.02*0.08*0.3*12*85*0.12-700*12)/700*12 -> -141.98565 | G52: =(50000*0.04*0.02*0.08*0.3*12*85*0.12-800*12)/800*12 -> -142.23744 | H52: =(50000*0.04*0.02*0.08*0.3*12*85*0.12-1000*12)/1000*12 -> -142.58995
A53: 0.35 | B53: =(50000*0.04*0.02*0.08*0.35*12*85*0.12-300*12)/300*12 -> -138.51648 | C53: =(50000*0.04*0.02*0.08*0.35*12*85*0.12-400*12)/400*12 -> -139.88736 | D53: =(50000*0.04*0.02*0.08*0.35*12*85*0.12-500*12)/500*12 -> -140.70989 | E53: =(50000*0.04*0.02*0.08*0.35*12*85*0.12-600*12)/600*12 -> -141.25824 | F53: =(50000*0.04*0.02*0.08*0.35*12*85*0.12-700*12)/700*12 -> -141.64992 | G53: =(50000*0.04*0.02*0.08*0.35*12*85*0.12-800*12)/800*12 -> -141.94368 | H53: =(50000*0.04*0.02*0.08*0.35*12*85*0.12-1000*12)/1000*12 -> -142.35494
A54: 0.4 | B54: =(50000*0.04*0.02*0.08*0.4*12*85*0.12-300*12)/300*12 -> -137.73312 | C54: =(50000*0.04*0.02*0.08*0.4*12*85*0.12-400*12)/400*12 -> -139.29984 | D54: =(50000*0.04*0.02*0.08*0.4*12*85*0.12-500*12)/500*12 -> -140.23987 | E54: =(50000*0.04*0.02*0.08*0.4*12*85*0.12-600*12)/600*12 -> -140.86656 | F54: =(50000*0.04*0.02*0.08*0.4*12*85*0.12-700*12)/700*12 -> -141.31419 | G54: =(50000*0.04*0.02*0.08*0.4*12*85*0.12-800*12)/800*12 -> -141.64992 | H54: =(50000*0.04*0.02*0.08*0.4*12*85*0.12-1000*12)/1000*12 -> -142.11994
A56: TABLE 6: EV ($M) — EBITDA Margin vs EV/EBITDA Multiple (at $5M Rev)
A57: Margin \ EV/EBITDA | B57: 6x | C57: 8x | D57: 10x | E57: 12x | F57: 14x | G57: 16x | H57: 20x
A58: 0.1 | B58: =5000000*0.1*6/1000000 -> 3 | C58: =5000000*0.1*8/1000000 -> 4 | D58: =5000000*0.1*10/1000000 -> 5 | E58: =5000000*0.1*12/1000000 -> 6 | F58: =5000000*0.1*14/1000000 -> 7 | G58: =5000000*0.1*16/1000000 -> 8 | H58: =5000000*0.1*20/1000000 -> 10
A59: 0.15 | B59: =5000000*0.15*6/1000000 -> 4.5 | C59: =5000000*0.15*8/1000000 -> 6 | D59: =5000000*0.15*10/1000000 -> 7.5 | E59: =5000000*0.15*12/1000000 -> 9 | F59: =5000000*0.15*14/1000000 -> 10.5 | G59: =5000000*0.15*16/1000000 -> 12 | H59: =5000000*0.15*20/1000000 -> 15
A60: 0.2 | B60: =5000000*0.2*6/1000000 -> 6 | C60: =5000000*0.2*8/1000000 -> 8 | D60: =5000000*0.2*10/1000000 -> 10 | E60: =5000000*0.2*12/1000000 -> 12 | F60: =5000000*0.2*14/1000000 -> 14 | G60: =5000000*0.2*16/1000000 -> 16 | H60: =5000000*0.2*20/1000000 -> 20
A61: 0.25 | B61: =5000000*0.25*6/1000000 -> 7.5 | C61: =5000000*0.25*8/1000000 -> 10 | D61: =5000000*0.25*10/1000000 -> 12.5 | E61: =5000000*0.25*12/1000000 -> 15 | F61: =5000000*0.25*14/1000000 -> 17.5 | G61: =5000000*0.25*16/1000000 -> 20 | H61: =5000000*0.25*20/1000000 -> 25
A62: 0.3 | B62: =5000000*0.3*6/1000000 -> 9 | C62: =5000000*0.3*8/1000000 -> 12 | D62: =5000000*0.3*10/1000000 -> 15 | E62: =5000000*0.3*12/1000000 -> 18 | F62: =5000000*0.3*14/1000000 -> 21 | G62: =5000000*0.3*16/1000000 -> 24 | H62: =5000000*0.3*20/1000000 -> 30
A63: 0.35 | B63: =5000000*0.35*6/1000000 -> 10.5 | C63: =5000000*0.35*8/1000000 -> 14 | D63: =5000000*0.35*10/1000000 -> 17.5 | E63: =5000000*0.35*12/1000000 -> 21 | F63: =5000000*0.35*14/1000000 -> 24.5 | G63: =5000000*0.35*16/1000000 -> 28 | H63: =5000000*0.35*20/1000000 -> 35
A64: 0.4 | B64: =5000000*0.4*6/1000000 -> 12 | C64: =5000000*0.4*8/1000000 -> 16 | D64: =5000000*0.4*10/1000000 -> 20 | E64: =5000000*0.4*12/1000000 -> 24 | F64: =5000000*0.4*14/1000000 -> 28 | G64: =5000000*0.4*16/1000000 -> 32 | H64: =5000000*0.4*20/1000000 -> 40
A66: TABLE 7: Y5 Platform Rev ($K) — Pro Adoption vs Lessons/Week
A67: Adopt% \ Les/Wk | B67: 4 | C67: 6 | D67: 7 | E67: 8 | F67: 10 | G67: 12 | H67: 15
A68: 0.3 | B68: =630*0.3*0.7*4*44*96*0.12/1000 -> 268.2409 | C68: =630*0.3*0.7*6*44*96*0.12/1000 -> 402.36134 | D68: =630*0.3*0.7*7*44*96*0.12/1000 -> 469.42157 | E68: =630*0.3*0.7*8*44*96*0.12/1000 -> 536.48179 | F68: =630*0.3*0.7*10*44*96*0.12/1000 -> 670.60224 | G68: =630*0.3*0.7*12*44*96*0.12/1000 -> 804.72269 | H68: =630*0.3*0.7*15*44*96*0.12/1000 -> 1005.9034
A69: 0.4 | B69: =630*0.4*0.7*4*44*96*0.12/1000 -> 357.65453 | C69: =630*0.4*0.7*6*44*96*0.12/1000 -> 536.48179 | D69: =630*0.4*0.7*7*44*96*0.12/1000 -> 625.89542 | E69: =630*0.4*0.7*8*44*96*0.12/1000 -> 715.30906 | F69: =630*0.4*0.7*10*44*96*0.12/1000 -> 894.13632 | G69: =630*0.4*0.7*12*44*96*0.12/1000 -> 1072.9636 | H69: =630*0.4*0.7*15*44*96*0.12/1000 -> 1341.2045
A70: 0.5 | B70: =630*0.5*0.7*4*44*96*0.12/1000 -> 447.06816 | C70: =630*0.5*0.7*6*44*96*0.12/1000 -> 670.60224 | D70: =630*0.5*0.7*7*44*96*0.12/1000 -> 782.36928 | E70: =630*0.5*0.7*8*44*96*0.12/1000 -> 894.13632 | F70: =630*0.5*0.7*10*44*96*0.12/1000 -> 1117.6704 | G70: =630*0.5*0.7*12*44*96*0.12/1000 -> 1341.2045 | H70: =630*0.5*0.7*15*44*96*0.12/1000 -> 1676.5056
A71: 0.65 | B71: =630*0.65*0.7*4*44*96*0.12/1000 -> 581.18861 | C71: =630*0.65*0.7*6*44*96*0.12/1000 -> 871.78291 | D71: =630*0.65*0.7*7*44*96*0.12/1000 -> 1017.0801 | E71: =630*0.65*0.7*8*44*96*0.12/1000 -> 1162.3772 | F71: =630*0.65*0.7*10*44*96*0.12/1000 -> 1452.9715 | G71: =630*0.65*0.7*12*44*96*0.12/1000 -> 1743.5658 | H71: =630*0.65*0.7*15*44*96*0.12/1000 -> 2179.4573
A72: 0.75 | B72: =630*0.75*0.7*4*44*96*0.12/1000 -> 670.60224 | C72: =630*0.75*0.7*6*44*96*0.12/1000 -> 1005.9034 | D72: =630*0.75*0.7*7*44*96*0.12/1000 -> 1173.5539 | E72: =630*0.75*0.7*8*44*96*0.12/1000 -> 1341.2045 | F72: =630*0.75*0.7*10*44*96*0.12/1000 -> 1676.5056 | G72: =630*0.75*0.7*12*44*96*0.12/1000 -> 2011.8067 | H72: =630*0.75*0.7*15*44*96*0.12/1000 -> 2514.7584
A73: 0.8 | B73: =630*0.8*0.7*4*44*96*0.12/1000 -> 715.30906 | C73: =630*0.8*0.7*6*44*96*0.12/1000 -> 1072.9636 | D73: =630*0.8*0.7*7*44*96*0.12/1000 -> 1251.7908 | E73: =630*0.8*0.7*8*44*96*0.12/1000 -> 1430.6181 | F73: =630*0.8*0.7*10*44*96*0.12/1000 -> 1788.2726 | G73: =630*0.8*0.7*12*44*96*0.12/1000 -> 2145.9272 | H73: =630*0.8*0.7*15*44*96*0.12/1000 -> 2682.409
A74: 0.9 | B74: =630*0.9*0.7*4*44*96*0.12/1000 -> 804.72269 | C74: =630*0.9*0.7*6*44*96*0.12/1000 -> 1207.084 | D74: =630*0.9*0.7*7*44*96*0.12/1000 -> 1408.2647 | E74: =630*0.9*0.7*8*44*96*0.12/1000 -> 1609.4454 | F74: =630*0.9*0.7*10*44*96*0.12/1000 -> 2011.8067 | G74: =630*0.9*0.7*12*44*96*0.12/1000 -> 2414.1681 | H74: =630*0.9*0.7*15*44*96*0.12/1000 -> 3017.7101
A76: TABLE 8: Annual Venue Bookings — Traffic per Venue vs Scan Rate (8 venues)
A77: Traffic \ Scan% | B77: 0.01 | C77: 0.015 | D77: 0.02 | E77: 0.025 | F77: 0.03 | G77: 0.04 | H77: 0.05
A78: 200000 | B78: =8*200000*0.3*0.01*0.4*0.05 -> 96 | C78: =8*200000*0.3*0.015*0.4*0.05 -> 144 | D78: =8*200000*0.3*0.02*0.4*0.05 -> 192 | E78: =8*200000*0.3*0.025*0.4*0.05 -> 240 | F78: =8*200000*0.3*0.03*0.4*0.05 -> 288 | G78: =8*200000*0.3*0.04*0.4*0.05 -> 384 | H78: =8*200000*0.3*0.05*0.4*0.05 -> 480
A79: 300000 | B79: =8*300000*0.3*0.01*0.4*0.05 -> 144 | C79: =8*300000*0.3*0.015*0.4*0.05 -> 216 | D79: =8*300000*0.3*0.02*0.4*0.05 -> 288 | E79: =8*300000*0.3*0.025*0.4*0.05 -> 360 | F79: =8*300000*0.3*0.03*0.4*0.05 -> 432 | G79: =8*300000*0.3*0.04*0.4*0.05 -> 576 | H79: =8*300000*0.3*0.05*0.4*0.05 -> 720
A80: 400000 | B80: =8*400000*0.3*0.01*0.4*0.05 -> 192 | C80: =8*400000*0.3*0.015*0.4*0.05 -> 288 | D80: =8*400000*0.3*0.02*0.4*0.05 -> 384 | E80: =8*400000*0.3*0.025*0.4*0.05 -> 480 | F80: =8*400000*0.3*0.03*0.4*0.05 -> 576 | G80: =8*400000*0.3*0.04*0.4*0.05 -> 768 | H80: =8*400000*0.3*0.05*0.4*0.05 -> 960
A81: 500000 | B81: =8*500000*0.3*0.01*0.4*0.05 -> 240 | C81: =8*500000*0.3*0.015*0.4*0.05 -> 360 | D81: =8*500000*0.3*0.02*0.4*0.05 -> 480 | E81: =8*500000*0.3*0.025*0.4*0.05 -> 600 | F81: =8*500000*0.3*0.03*0.4*0.05 -> 720 | G81: =8*500000*0.3*0.04*0.4*0.05 -> 960 | H81: =8*500000*0.3*0.05*0.4*0.05 -> 1200
A82: 600000 | B82: =8*600000*0.3*0.01*0.4*0.05 -> 288 | C82: =8*600000*0.3*0.015*0.4*0.05 -> 432 | D82: =8*600000*0.3*0.02*0.4*0.05 -> 576 | E82: =8*600000*0.3*0.025*0.4*0.05 -> 720 | F82: =8*600000*0.3*0.03*0.4*0.05 -> 864 | G82: =8*600000*0.3*0.04*0.4*0.05 -> 1152 | H82: =8*600000*0.3*0.05*0.4*0.05 -> 1440
A83: 750000 | B83: =8*750000*0.3*0.01*0.4*0.05 -> 360 | C83: =8*750000*0.3*0.015*0.4*0.05 -> 540 | D83: =8*750000*0.3*0.02*0.4*0.05 -> 720 | E83: =8*750000*0.3*0.025*0.4*0.05 -> 900 | F83: =8*750000*0.3*0.03*0.4*0.05 -> 1080 | G83: =8*750000*0.3*0.04*0.4*0.05 -> 1440 | H83: =8*750000*0.3*0.05*0.4*0.05 -> 1800
A84: 1000000 | B84: =8*1000000*0.3*0.01*0.4*0.05 -> 480 | C84: =8*1000000*0.3*0.015*0.4*0.05 -> 720 | D84: =8*1000000*0.3*0.02*0.4*0.05 -> 960 | E84: =8*1000000*0.3*0.025*0.4*0.05 -> 1200 | F84: =8*1000000*0.3*0.03*0.4*0.05 -> 1440 | G84: =8*1000000*0.3*0.04*0.4*0.05 -> 1920 | H84: =8*1000000*0.3*0.05*0.4*0.05 -> 2400

Sheet Risk Framework
A1: RISK MANAGEMENT FRAMEWORK — PHILADELPHIA PGA GROWTH STRATEGY
A2: Risk Category | B2: Risk Description | C2: Likelihood | D2: Impact | E2: Leading Indicators | F2: Mitigation Strategy | G2: Contingency Plan | H2: Owner
A3: Market Adoption | B3: Pros do not adopt platform — insufficient value prop or trust | C3: Medium | D3: High | E3: Onboarding rate <10% at M6; NPS <30 | F3: Phased launch with 20 pilot pros; free trial period; dedicated onboarding support | G3: Pivot to referral-only model; reduce platform investment; focus on content/events | H3: VP Marketing
A4: Market Adoption | B4: Consumers do not convert — low awareness or poor UX | C4: Medium | D4: High | E4: Conversion rate <2%; bounce rate >70% | F4: A/B test landing pages; invest in SEO; simplify booking flow | G4: Redirect spend to offline channels; partner with venues for direct acquisition | H4: Platform Mgr
A5: Market Adoption | B5: Golf participation growth slows or reverses | C5: Low | D5: High | E5: National participation data trending down 2+ qtrs | F5: Diversify to non-golfer programming; expand beginner content | G5: Reduce growth capex; shift to profitability focus; cut expansion plans | H5: CEO
A6: Brand / Reputation | B6: Inconsistent pro quality damages brand trust | C6: Medium | D6: High | E6: Negative reviews >5%; complaint rate rising | F6: Vetting standards; profile quality review; rating/feedback system | G6: Remove underperforming pros; issue public quality commitment; refund policy | H6: Partnership Dir
A7: Brand / Reputation | B7: Continued confusion with PGA Tour dilutes positioning | C7: High | D7: Medium | E7: Surveys show <30% brand distinction awareness | F7: Distinction campaign; 'We Are Not the Tour' content; consistent messaging | G7: Rebrand consideration; alternative naming for consumer-facing products | H7: VP Marketing
A8: Operational | B8: Under-resourced support leads to poor experience | C8: Medium | D8: Medium | E8: Support ticket backlog >48hr; satisfaction <3.5/5 | F8: Hire support specialist Y2; implement ticketing system; SLA targets | G8: Outsource overflow support; reduce feature scope to manageable level | H8: Operations
A9: Operational | B9: Event execution failure damages corporate relationships | C9: Low | D9: High | E9: Event NPS <40; client complaint rate >10% | F9: Standard operating procedures; backup staffing; venue walk-throughs | G9: Immediate client remediation; comp event; dedicated account recovery | H9: Event Coord
A10: Operational | B10: Creator content quality/consistency issues | C10: Medium | D10: Medium | E10: Engagement rate drops <2%; brand guideline violations | F10: Monthly content calendar; brand guidelines training; editorial review | G10: Pause underperforming creators; shift to in-house content production | H10: Content Mgr
A11: Financial | B11: CAC exceeds threshold — acquisition economics break | C11: Medium | D11: High | E11: CAC >$50 platform; >$75 creator; >$4K corporate | F11: Monthly CAC monitoring; channel-level P&L; kill underperformers | G11: Pause paid acquisition; shift to organic/referral only; reduce marketing | H11: VP Marketing
A12: Financial | B12: Margins weaker than expected — cost overruns | C12: Medium | D12: Medium | E12: GM <40% or EBITDA margin <-20% in Y2 | F12: Monthly margin reviews; variable cost discipline; stage-gated investment | G12: Headcount freeze; reduce non-essential spend; renegotiate vendor contracts | H12: CEO / Finance
A13: Financial | B13: Venue partnerships unprofitable — high activation cost | C13: Medium | D13: Medium | E13: Revenue/venue <$30K; ROI <0% after 12 months | F13: Pilot 2 venues before scaling; quarterly ROI review per venue | G13: Exit unprofitable venues; renegotiate terms; shift to lower-cost co-marketing | H13: Partnership Dir
... A20: Legal / Compliance | B20: Privacy / data management violations | C20: Low | D20: High | E20: Data breach; GDPR/CCPA complaint | F20: Privacy policy; data security protocols; encryption; regular audits | G20: Incident response plan; breach notification; legal remediation | H20: Legal / IT
A23: FINANCIAL RISK CONTROLS & THRESHOLDS
A24: Control | B24: Threshold | C24: Action if Breached
A25: Min Gross Margin by Segment | B25: 0.4 | C25: Below = restructure or exit segment
A26: Min Contribution Margin by Channel | B26: 0.2 | C26: Below = exit acquisition channel
A27: Max CAC — Platform Organic | B27: 50 | C27: Above = pause paid; shift to organic
A28: Max CAC — Creator Channel | B28: 75 | C28: Above = reduce creator cohort
A29: Max CAC — Corporate B2B | B29: 4000 | C29: Above = renegotiate sales process
A30: Max Payback Period | B30: 12 months | C30: Above = kill channel investment
A31: Min IRR Hurdle for Expansion | B31: 0.2 | C31: Below = do not approve initiative
A32: Go/No-Go — Venue Partnership | B32: Revenue/venue > $30K & ROI > 0% | C32: Below = exit partnership at renewal
A33: Headcount Freeze Trigger | B33: EBITDA margin < -25% for 2 consecutive quarters | C33: Freeze all hiring; review cuts
A34: Cash Reserve Minimum | B34: 6 months of fixed costs | C34: Below = activate emergency protocols
A38: QUANTIFIED RISK SCORING MATRIX
A39: Risk Category | B39: Probability (1-5) | C39: Impact (1-5) | D39: Risk Score | E39: Risk Level | F39: Financial Exposure ($) | G39: Priority
A40: Pro Adoption Below Target | B40: 3 | C40: 5 | D40: =B40*C40 -> 15 | E40: =IF(D40>=15,"CRITICAL",IF(D40>=10,"HIGH",IF(D40>=6,"MEDIUM","LOW"))) -> CRITICAL | F40: 500000 | G40: =RANK(D40,D$40:D$55) -> 1
A41: Consumer Conversion Failure | B41: 3 | C41: 4 | D41: =B41*C41 -> 12 | E41: =IF(D41>=15,"CRITICAL",IF(D41>=10,"HIGH",IF(D41>=6,"MEDIUM","LOW"))) -> HIGH | F41: 300000 | G41: =RANK(D41,D$40:D$55) -> 2
A42: Golf Participation Decline | B42: 2 | C42: 5 | D42: =B42*C42 -> 10 | E42: =IF(D42>=15,"CRITICAL",IF(D42>=10,"HIGH",IF(D42>=6,"MEDIUM","LOW"))) -> HIGH | F42: 400000 | G42: =RANK(D42,D$40:D$55) -> 9
A43: PGA Tour Brand Confusion | B43: 4 | C43: 3 | D43: =B43*C43 -> 12 | E43: =IF(D43>=15,"CRITICAL",IF(D43>=10,"HIGH",IF(D43>=6,"MEDIUM","LOW"))) -> HIGH | F43: 200000 | G43: =RANK(D43,D$40:D$55) -> 2
A44: Pro Quality Inconsistency | B44: 3 | C44: 4 | D44: =B44*C44 -> 12 | E44: =IF(D44>=15,"CRITICAL",IF(D44>=10,"HIGH",IF(D44>=6,"MEDIUM","LOW"))) -> HIGH | F44: 250000 | G44: =RANK(D44,D$40:D$55) -> 2
A45: Support Under-Resourcing | B45: 3 | C45: 3 | D45: =B45*C45 -> 9 | E45: =IF(D45>=15,"CRITICAL",IF(D45>=10,"HIGH",IF(D45>=6,"MEDIUM","LOW"))) -> MEDIUM | F45: 100000 | G45: =RANK(D45,D$40:D$55) -> 11
A46: Corporate Event Failure | B46: 2 | C46: 4 | D46: =B46*C46 -> 8 | E46: =IF(D46>=15,"CRITICAL",IF(D46>=10,"HIGH",IF(D46>=6,"MEDIUM","LOW"))) -> MEDIUM | F46: 350000 | G46: =RANK(D46,D$40:D$55) -> 14
A47: Creator Content Issues | B47: 3 | C47: 2 | D47: =B47*C47 -> 6 | E47: =IF(D47>=15,"CRITICAL",IF(D47>=10,"HIGH",IF(D47>=6,"MEDIUM","LOW"))) -> MEDIUM | F47: 80000 | G47: =RANK(D47,D$40:D$55) -> 15
A48: CAC Exceeds Threshold | B48: 3 | C48: 4 | D48: =B48*C48 -> 12 | E48: =IF(D48>=15,"CRITICAL",IF(D48>=10,"HIGH",IF(D48>=6,"MEDIUM","LOW"))) -> HIGH | F48: 400000 | G48: =RANK(D48,D$40:D$55) -> 2
A49: Margin Compression | B49: 3 | C49: 3 | D49: =B49*C49 -> 9 | E49: =IF(D49>=15,"CRITICAL",IF(D49>=10,"HIGH",IF(D49>=6,"MEDIUM","LOW"))) -> MEDIUM | F49: 300000 | G49: =RANK(D49,D$40:D$55) -> 11
A50: Venue Partnership Unprofitable | B50: 3 | C50: 3 | D50: =B50*C50 -> 9 | E50: =IF(D50>=15,"CRITICAL",IF(D50>=10,"HIGH",IF(D50>=6,"MEDIUM","LOW"))) -> MEDIUM | F50: 150000 | G50: =RANK(D50,D$40:D$55) -> 11
A51: Long Corporate Sales Cycle | B51: 4 | C51: 3 | D51: =B51*C51 -> 12 | E51: =IF(D51>=15,"CRITICAL",IF(D51>=10,"HIGH",IF(D51>=6,"MEDIUM","LOW"))) -> HIGH | F51: 250000 | G51: =RANK(D51,D$40:D$55) -> 2
... A55: Legal / Compliance Breach | B55: 2 | C55: 5 | D55: =B55*C55 -> 10 | E55: =IF(D55>=15,"CRITICAL",IF(D55>=10,"HIGH",IF(D55>=6,"MEDIUM","LOW"))) -> HIGH | F55: 500000 | G55: =RANK(D55,D$40:D$55) -> 9
A56: TOTAL RISK EXPOSURE | D56: =AVERAGE(D40:D55) -> 10.375 | E56: =IF(D56>=15,"CRITICAL",IF(D56>=10,"HIGH",IF(D56>=6,"MEDIUM","LOW"))) -> HIGH | F56: =SUM(F40:F55) -> 4405000 | G56: =RANK(D56,D$40:D$55) -> #N/A
A57: Probability-Weighted Risk Exposure | F57: {=SUMPRODUCT(B40:B55/5,F40:F55)} -> 2483000
A58: Risk Exposure as % of Y5 Revenue | F58: =IF('Revenue Build'!F78=0,0,F56/'Revenue Build'!F78) -> 1.0663238

Sheet KPI Dashboard
A1: OPERATIONAL KPI DASHBOARD — 10 YEAR FORECAST
A2: KPI | B2: Year 1 | C2: Year 2 | D2: Year 3 | E2: Year 4 | F2: Year 5 | G2: Year 6 | H2: Year 7 | I2: Year 8 | J2: Year 9 | K2: Year 10
A3: OPERATING KPIs
A4: Active PGA Pros on Platform | B4: ='Revenue Build'!B9 -> 66.15 | C4: ='Revenue Build'!C9 -> 110.25 | D4: ='Revenue Build'!D9 -> 176.4 | E4: ='Revenue Build'!E9 -> 220.5 | F4: ='Revenue Build'!F9 -> 286.65 | G4: ='Revenue Build'!G9 -> 308.7 | H4: ='Revenue Build'!H9 -> 330.75 | I4: ='Revenue Build'!I9 -> 352.8 | ... K4: ='Revenue Build'!K9 -> 374.85
A5: Active Creators | B5: ='Revenue Build'!B23 -> 10 | C5: ='Revenue Build'!C23 -> 18 | D5: ='Revenue Build'!D23 -> 30 | E5: ='Revenue Build'!E23 -> 38 | F5: ='Revenue Build'!F23 -> 50 | G5: ='Revenue Build'!G23 -> 55 | H5: ='Revenue Build'!H23 -> 60 | I5: ='Revenue Build'!I23 -> 65 | ... K5: ='Revenue Build'!K23 -> 70
A6: Active Venue Partners | B6: ='Revenue Build'!B41 -> 2 | C6: ='Revenue Build'!C41 -> 3 | D6: ='Revenue Build'!D41 -> 5 | E6: ='Revenue Build'!E41 -> 6 | F6: ='Revenue Build'!F41 -> 8 | G6: ='Revenue Build'!G41 -> 8 | H6: ='Revenue Build'!H41 -> 8 | I6: ='Revenue Build'!I41 -> 8 | ... K6: ='Revenue Build'!K41 -> 8
A7: Active Corporate Clients | B7: ='Revenue Build'!B59 -> 5 | C7: ='Revenue Build'!C59 -> 12 | D7: ='Revenue Build'!D59 -> 20 | E7: ='Revenue Build'!E59 -> 30 | F7: ='Revenue Build'!F59 -> 45 | G7: ='Revenue Build'!G59 -> 52 | H7: ='Revenue Build'!H59 -> 58 | I7: ='Revenue Build'!I59 -> 65 | ... K7: ='Revenue Build'!K59 -> 80
A8: Total Annual Lesson Bookings | B8: ='Revenue Build'!B12 -> 23284.8 | C8: ='Revenue Build'!C12 -> 38808 | D8: ='Revenue Build'!D12 -> 62092.8 | E8: ='Revenue Build'!E12 -> 77616 | F8: ='Revenue Build'!F12 -> 100900.8 | G8: ='Revenue Build'!G12 -> 108662.4 | H8: ='Revenue Build'!H12 -> 116424 | I8: ='Revenue Build'!I12 -> 124185.6 | ... K8: ='Revenue Build'!K12 -> 131947.2
A9: Avg Lesson Price ($) | B9: ='Revenue Build'!B13 -> 85 | C9: ='Revenue Build'!C13 -> 87.55 | D9: ='Revenue Build'!D13 -> 90.1765 | E9: ='Revenue Build'!E13 -> 92.881795 | F9: ='Revenue Build'!F13 -> 95.668249 | G9: ='Revenue Build'!G13 -> 98.538296 | H9: ='Revenue Build'!H13 -> 101.49445 | I9: ='Revenue Build'!I13 -> 104.53928 | ... K9: ='Revenue Build'!K13 -> 110.90572
A10: Gross Marketplace Volume ($) | B10: ='Revenue Build'!B14 -> 1979208 | C10: ='Revenue Build'!C14 -> 3397640.4 | D10: ='Revenue Build'!D14 -> 5599311.4 | E10: ='Revenue Build'!E14 -> 7209113.4 | F10: ='Revenue Build'!F14 -> 9653002.8 | G10: ='Revenue Build'!G14 -> 10707408 | H10: ='Revenue Build'!H14 -> 11816389 | I10: ='Revenue Build'!I14 -> 12982273 | ... K10: ='Revenue Build'!K14 -> 14633699
A11: Bookings via Creators (annual) | B11: ='Revenue Build'!B34 -> 96 | C11: ='Revenue Build'!C34 -> 172.8 | D11: ='Revenue Build'!D34 -> 288 | E11: ='Revenue Build'!E34 -> 364.8 | F11: ='Revenue Build'!F34 -> 480 | G11: ='Revenue Build'!G34 -> 528 | H11: ='Revenue Build'!H34 -> 576 | I11: ='Revenue Build'!I34 -> 624 | ... K11: ='Revenue Build'!K34 -> 672
A12: Bookings via Venues (annual) | B12: ='Revenue Build'!B51 -> 120 | C12: ='Revenue Build'!C51 -> 180 | D12: ='Revenue Build'!D51 -> 300 | E12: ='Revenue Build'!E51 -> 360 | F12: ='Revenue Build'!F51 -> 480 | G12: ='Revenue Build'!G51 -> 480 | H12: ='Revenue Build'!H51 -> 480 | I12: ='Revenue Build'!I51 -> 480 | ... K12: ='Revenue Build'!K51 -> 480
A13: Corporate Events Delivered | B13: ='Revenue Build'!B61 -> 20 | C13: ='Revenue Build'!C61 -> 48 | D13: ='Revenue Build'!D61 -> 80 | E13: ='Revenue Build'!E61 -> 120 | F13: ='Revenue Build'!F61 -> 180 | G13: ='Revenue Build'!G61 -> 208 | H13: ='Revenue Build'!H61 -> 232 | I13: ='Revenue Build'!I61 -> 260 | ... K13: ='Revenue Build'!K61 -> 320
A15: FINANCIAL KPIs
A16: Total Revenue ($) | B16: ='Revenue Build'!B78 -> 584800.65 | C16: ='Revenue Build'!C78 -> 1205553.5 | D16: ='Revenue Build'!D78 -> 2069745 | E16: ='Revenue Build'!E78 -> 2877110.7 | F16: ='Revenue Build'!F78 -> 4131015.4 | G16: ='Revenue Build'!G78 -> 4676081.5 | H16: ='Revenue Build'!H78 -> 5197545.4 | I16: ='Revenue Build'!I78 -> 5779105.2 | ... K16: ='Revenue Build'!K78 -> 6941838.6
A17: Platform Revenue | B17: ='Revenue Build'!B20 -> 265097.45 | C17: ='Revenue Build'!C20 -> 460846.94 | D17: ='Revenue Build'!D20 -> 768382.19 | E17: ='Revenue Build'!E20 -> 1000032.2 | F17: ='Revenue Build'!F20 -> 1352494.4 | G17: ='Revenue Build'!G20 -> 1503162.3 | H17: ='Revenue Build'!H20 -> 1665684 | I17: ='Revenue Build'!I20 -> 1832755.8 | ... K17: ='Revenue Build'!K20 -> 2066507
A18: Creator Revenue | B18: ='Revenue Build'!B38 -> 979.2 | C18: ='Revenue Build'!C38 -> 1815.4368 | D18: ='Revenue Build'!D38 -> 63116.5 | E18: ='Revenue Build'!E38 -> 118065.99 | F18: ='Revenue Build'!F38 -> 205510.49 | G18: ='Revenue Build'!G38 -> 281243.39 | H18: ='Revenue Build'!H38 -> 367015.3 | I18: ='Revenue Build'!I38 -> 462827.9 | ... K18: ='Revenue Build'!K38 -> 708943.44
A19: Venue Revenue | B19: ='Revenue Build'!B56 -> 131224 | C19: ='Revenue Build'!C56 -> 196891.08 | D19: ='Revenue Build'!D56 -> 328246.35 | E19: ='Revenue Build'!E56 -> 394012.49 | F19: ='Revenue Build'!F56 -> 525510.49 | G19: ='Revenue Build'!G56 -> 525675.81 | H19: ='Revenue Build'!H56 -> 525846.08 | I19: ='Revenue Build'!I56 -> 526021.46 | ... K19: ='Revenue Build'!K56 -> 526388.17
A20: Corporate Revenue | B20: ='Revenue Build'!B71 -> 187500 | C20: ='Revenue Build'!C71 -> 546000 | D20: ='Revenue Build'!D71 -> 910000 | E20: ='Revenue Build'!E71 -> 1365000 | F20: ='Revenue Build'!F71 -> 2047500 | G20: ='Revenue Build'!G71 -> 2366000 | H20: ='Revenue Build'!H71 -> 2639000 | I20: ='Revenue Build'!I71 -> 2957500 | ... K20: ='Revenue Build'!K71 -> 3640000
A21: Gross Profit ($) | B21: ='Margin Analysis'!B43 -> 290353.4 | C21: ='Margin Analysis'!C43 -> 623213.18 | D21: ='Margin Analysis'!D43 -> 1099870.8 | E21: ='Margin Analysis'!E43 -> 1552245.1 | F21: ='Margin Analysis'!F43 -> 2264430 | G21: ='Margin Analysis'!G43 -> 2579837.7 | H21: ='Margin Analysis'!H43 -> 2890352.8 | I21: ='Margin Analysis'!I43 -> 3238179.9 | ... K21: ='Margin Analysis'!K43 -> 3981990.9
A22: Gross Margin % | B22: ='Margin Analysis'!B44 -> 0.49649978 | C22: ='Margin Analysis'!C44 -> 0.51695192 | D22: ='Margin Analysis'!D44 -> 0.531404 | E22: ='Margin Analysis'!E44 -> 0.53951524 | F22: ='Margin Analysis'!F44 -> 0.54815337 | G22: ='Margin Analysis'!G44 -> 0.5517093 | H22: ='Margin Analysis'!H44 -> 0.55609958 | I22: ='Margin Analysis'!I44 -> 0.56032548 | ... K22: ='Margin Analysis'!K44 -> 0.57362193
A23: EBITDA ($) | B23: ='Margin Analysis'!B47 -> -715646.6 | C23: ='Margin Analysis'!C47 -> -651336.82 | D23: ='Margin Analysis'!D47 -> -219866.69 | E23: ='Margin Analysis'!E47 -> -5610.34 | F23: ='Margin Analysis'!F47 -> 652175.49 | G23: ='Margin Analysis'!G47 -> 911168.83 | H23: ='Margin Analysis'!H47 -> 954215.76 | I23: ='Margin Analysis'!I47 -> 1235087.3 | ... K23: ='Margin Analysis'!K47 -> 1609199.4
A24: EBITDA Margin % | B24: ='Margin Analysis'!B48 -> -1.2237445 | C24: ='Margin Analysis'!C48 -> -0.54028033 | D24: ='Margin Analysis'!D48 -> -0.10622888 | E24: ='Margin Analysis'!E48 -> -0.001949991 | F24: ='Margin Analysis'!F48 -> 0.15787292 | G24: ='Margin Analysis'!G48 -> 0.19485735 | H24: ='Margin Analysis'!H48 -> 0.18358969 | I24: ='Margin Analysis'!I48 -> 0.21371601 | ... K24: ='Margin Analysis'!K48 -> 0.2318117
A25: Free Cash Flow ($) | B25: ='Margin Analysis'!B59 -> -791670.69 | C25: ='Margin Analysis'!C59 -> -761274.72 | D25: ='Margin Analysis'!D59 -> -392489.27 | E25: ='Margin Analysis'!E59 -> -214055.12 | F25: ='Margin Analysis'!F59 -> 213251.08 | G25: ='Margin Analysis'!G59 -> 441037.87 | H25: ='Margin Analysis'!H59 -> 453049.04 | I25: ='Margin Analysis'!I59 -> 634178.73 | ... K25: ='Margin Analysis'!K59 -> 859548.95
A26: FCF Margin % | B26: ='Margin Analysis'!B60 -> -1.3537445 | C26: ='Margin Analysis'!C60 -> -0.63147322 | D26: ='Margin Analysis'!D60 -> -0.1896317 | E26: ='Margin Analysis'!E60 -> -0.074399336 | F26: ='Margin Analysis'!F60 -> 0.051621952 | G26: ='Margin Analysis'!G60 -> 0.094317832 | H26: ='Margin Analysis'!H60 -> 0.087165961 | I26: ='Margin Analysis'!I60 -> 0.10973649 | ... K26: ='Margin Analysis'!K60 -> 0.12382151
A27: Revenue Growth (YoY) | B27: ='Revenue Build'!B85 -> N/A | C27: ='Revenue Build'!C85 -> 1.0614776 | D27: ='Revenue Build'!D85 -> 0.7168422 | E27: ='Revenue Build'!E85 -> 0.39007975 | F27: ='Revenue Build'!F85 -> 0.43582082 | G27: ='Revenue Build'!G85 -> 0.13194482 | H27: ='Revenue Build'!H85 -> 0.11151727 | I27: ='Revenue Build'!I85 -> 0.11189124 | ... K27: ='Revenue Build'!K85 -> 0.10401576
A29: UNIT ECONOMICS KPIs
A30: CAC — Platform ($) | B30: ='Unit Economics'!B7 -> 25 | C30: ='Unit Economics'!C7 -> 25 | D30: ='Unit Economics'!D7 -> 25 | E30: ='Unit Economics'!E7 -> 25 | F30: ='Unit Economics'!F7 -> 25 | G30: ='Unit Economics'!G7 -> 25 | H30: ='Unit Economics'!H7 -> 25 | I30: ='Unit Economics'!I7 -> 25 | ... K30: ='Unit Economics'!K7 -> 25
A31: Consumer LTV ($) | B31: ='Unit Economics'!B13 -> 227.7 | C31: ='Unit Economics'!C13 -> 237.501 | D31: ='Unit Economics'!D13 -> 247.49478 | E31: ='Unit Economics'!E13 -> 257.68712 | F31: ='Unit Economics'!F13 -> 268.08399 | G31: ='Unit Economics'!G13 -> 276.66651 | H31: ='Unit Economics'!H13 -> 286.141 | I31: ='Unit Economics'!I13 -> 295.16398 | ... K31: ='Unit Economics'!K13 -> 313.23242
A32: LTV / CAC Ratio | B32: ='Unit Economics'!B14 -> 9.108 | C32: ='Unit Economics'!C14 -> 9.50004 | D32: ='Unit Economics'!D14 -> 9.8997912 | E32: ='Unit Economics'!E14 -> 10.307485 | F32: ='Unit Economics'!F14 -> 10.723359 | G32: ='Unit Economics'!G14 -> 11.06666 | H32: ='Unit Economics'!H14 -> 11.44564 | I32: ='Unit Economics'!I14 -> 11.806559 | ... K32: ='Unit Economics'!K14 -> 12.529297
A33: Payback Period (months) | B33: ='Unit Economics'!B15 -> 4.3917435 | C33: ='Unit Economics'!C15 -> 4.2105086 | D33: ='Unit Economics'!D15 -> 4.0404893 | E33: ='Unit Economics'!E15 -> 3.8806751 | F33: ='Unit Economics'!F15 -> 3.7301743 | G33: ='Unit Economics'!G15 -> 3.6144599 | H33: ='Unit Economics'!H15 -> 3.4947805 | I33: ='Unit Economics'!I15 -> 3.3879472 | ... K33: ='Unit Economics'!K15 -> 3.1925176
A34: Revenue per Active Pro ($) | B34: =IF('Revenue Build'!B9=0,0,'Revenue Build'!B20/'Revenue Build'!B9) -> 4007.52 | C34: =IF('Revenue Build'!C9=0,0,'Revenue Build'!C20/'Revenue Build'!C9) -> 4180.0176 | D34: =IF('Revenue Build'!D9=0,0,'Revenue Build'!D20/'Revenue Build'!D9) -> 4355.9081 | E34: =IF('Revenue Build'!E9=0,0,'Revenue Build'!E20/'Revenue Build'!E9) -> 4535.2934 | F34: =IF('Revenue Build'!F9=0,0,'Revenue Build'!F20/'Revenue Build'!F9) -> 4718.2782 | G34: =IF('Revenue Build'!G9=0,0,'Revenue Build'!G20/'Revenue Build'!G9) -> 4869.3305 | H34: =IF('Revenue Build'!H9=0,0,'Revenue Build'!H20/'Revenue Build'!H9) -> 5036.0816 | I34: =IF('Revenue Build'!I9=0,0,'Revenue Build'!I20/'Revenue Build'!I9) -> 5194.8861 | ... K34: =IF('Revenue Build'!K9=0,0,'Revenue Build'!K20/'Revenue Build'!K9) -> 5512.8905
A35: Revenue per Venue Partner ($) | B35: =IF('Revenue Build'!B41=0,0,'Revenue Build'!B56/'Revenue Build'!B41) -> 65612 | C35: =IF('Revenue Build'!C41=0,0,'Revenue Build'!C56/'Revenue Build'!C41) -> 65630.36 | D35: =IF('Revenue Build'!D41=0,0,'Revenue Build'!D56/'Revenue Build'!D41) -> 65649.271 | E35: =IF('Revenue Build'!E41=0,0,'Revenue Build'!E56/'Revenue Build'!E41) -> 65668.749 | F35: =IF('Revenue Build'!F41=0,0,'Revenue Build'!F56/'Revenue Build'!F41) -> 65688.811 | G35: =IF('Revenue Build'!G41=0,0,'Revenue Build'!G56/'Revenue Build'!G41) -> 65709.476 | H35: =IF('Revenue Build'!H41=0,0,'Revenue Build'!H56/'Revenue Build'!H41) -> 65730.76 | I35: =IF('Revenue Build'!I41=0,0,'Revenue Build'!I56/'Revenue Build'!I41) -> 65752.683 | ... K35: =IF('Revenue Build'!K41=0,0,'Revenue Build'!K56/'Revenue Build'!K41) -> 65798.521
A36: Revenue per Corporate Client ($) | B36: =IF('Revenue Build'!B59=0,0,'Revenue Build'!B71/'Revenue Build'!B59) -> 37500 | C36: =IF('Revenue Build'!C59=0,0,'Revenue Build'!C71/'Revenue Build'!C59) -> 45500 | D36: =IF('Revenue Build'!D59=0,0,'Revenue Build'!D71/'Revenue Build'!D59) -> 45500 | E36: =IF('Revenue Build'!E59=0,0,'Revenue Build'!E71/'Revenue Build'!E59) -> 45500 | F36: =IF('Revenue Build'!F59=0,0,'Revenue Build'!F71/'Revenue Build'!F59) -> 45500 | G36: =IF('Revenue Build'!G59=0,0,'Revenue Build'!G71/'Revenue Build'!G59) -> 45500 | H36: =IF('Revenue Build'!H59=0,0,'Revenue Build'!H71/'Revenue Build'!H59) -> 45500 | I36: =IF('Revenue Build'!I59=0,0,'Revenue Build'!I71/'Revenue Build'!I59) -> 45500 | ... K36: =IF('Revenue Build'!K59=0,0,'Revenue Build'!K71/'Revenue Build'!K59) -> 45500
A37: Corporate Client LTV ($) | B37: ='Unit Economics'!B42 -> 187500 | C37: ='Unit Economics'!C42 -> 227500 | D37: ='Unit Economics'!D42 -> 227500 | E37: ='Unit Economics'!E42 -> 227500 | F37: ='Unit Economics'!F42 -> 227500 | G37: ='Unit Economics'!G42 -> 227500 | H37: ='Unit Economics'!H42 -> 227500 | I37: ='Unit Economics'!I42 -> 227500 | ... K37: ='Unit Economics'!K42 -> 227500
A38: Corporate LTV / CAC | B38: ='Unit Economics'!B43 -> 75 | C38: ='Unit Economics'!C43 -> 91 | D38: ='Unit Economics'!D43 -> 91 | E38: ='Unit Economics'!E43 -> 91 | F38: ='Unit Economics'!F43 -> 91 | G38: ='Unit Economics'!G43 -> 91 | H38: ='Unit Economics'!H43 -> 91 | I38: ='Unit Economics'!I43 -> 91 | ... K38: ='Unit Economics'!K43 -> 91
A40: VALUATION SUMMARY
A41: DCF Enterprise Value (Avg) | B41: ='DCF Valuation'!B45 -> 2720333.4
A42: LBO Sponsor MOIC | B42: ='LBO Analysis'!B53 -> 5.2400756
A43: LBO Sponsor IRR | B43: ='LBO Analysis'!B54 -> 0.39273186
A44: EV / Y5 EBITDA | B44: ='DCF Valuation'!B51 -> 4.1711678
A45: EV / Y10 Revenue | B45: ='DCF Valuation'!B50 -> 0.39187505
A128: EXECUTIVE INVESTMENT SCORECARD
A129: Criterion | B129: Score (1-10) | C129: Weight | D129: Weighted Score
A130: Market Size & Growth | B130: 8 | C130: 0.15 | D130: =B130*C130 -> 1.2
A131: Revenue Model Strength | B131: 7 | C131: 0.12 | D131: =B131*C131 -> 0.84
A132: Unit Economics (LTV/CAC) | B132: 8 | C132: 0.12 | D132: =B132*C132 -> 0.96
A133: Scalability of Platform | B133: 9 | C133: 0.1 | D133: =B133*C133 -> 0.9
A134: Competitive Moat | B134: 9 | C134: 0.1 | D134: =B134*C134 -> 0.9
A135: Management & Execution Risk | B135: 6 | C135: 0.1 | D135: =B135*C135 -> 0.6
A136: Margin Profile & Trajectory | B136: 7 | C136: 0.08 | D136: =B136*C136 -> 0.56
A137: Capital Efficiency | B137: 8 | C137: 0.08 | D137: =B137*C137 -> 0.64
A138: Downside Protection | B138: 6 | C138: 0.08 | D138: =B138*C138 -> 0.48
A139: Exit Optionality | B139: 7 | C139: 0.07 | D139: =B139*C139 -> 0.49
A140: OVERALL INVESTMENT SCORE | C140: =SUM(C130:C139) -> 1 | D140: =SUM(D130:D139) -> 7.57
A141: INVESTMENT GRADE | D141: =IF(D140>=8,"A — STRONG BUY",IF(D140>=7,"B+ — ATTRACTIVE",IF(D140>=6,"B — MODERATE",IF(D140>=5,"C — CAUTIOUS","D — PASS")))) -> B+ — ATTRACTIVE

Sheet Chart Data
A1: Revenue by Segment
A2: Segment | B2: Year 1 | C2: Year 2 | D2: Year 3 | E2: Year 4 | F2: Year 5 | G2: Year 6 | H2: Year 7 | I2: Year 8 | J2: Year 9 | K2: Year 10
A3: Platform | B3: ='Revenue Build'!B74 -> 265097.45 | C3: ='Revenue Build'!C74 -> 460846.94 | D3: ='Revenue Build'!D74 -> 768382.19 | E3: ='Revenue Build'!E74 -> 1000032.2 | F3: ='Revenue Build'!F74 -> 1352494.4 | G3: ='Revenue Build'!G74 -> 1503162.3 | H3: ='Revenue Build'!H74 -> 1665684 | I3: ='Revenue Build'!I74 -> 1832755.8 | ... K3: ='Revenue Build'!K74 -> 2066507
A4: Creator | B4: ='Revenue Build'!B75 -> 979.2 | C4: ='Revenue Build'!C75 -> 1815.4368 | D4: ='Revenue Build'!D75 -> 63116.5 | E4: ='Revenue Build'!E75 -> 118065.99 | F4: ='Revenue Build'!F75 -> 205510.49 | G4: ='Revenue Build'!G75 -> 281243.39 | H4: ='Revenue Build'!H75 -> 367015.3 | I4: ='Revenue Build'!I75 -> 462827.9 | ... K4: ='Revenue Build'!K75 -> 708943.44
A5: Venue | B5: ='Revenue Build'!B76 -> 131224 | C5: ='Revenue Build'!C76 -> 196891.08 | D5: ='Revenue Build'!D76 -> 328246.35 | E5: ='Revenue Build'!E76 -> 394012.49 | F5: ='Revenue Build'!F76 -> 525510.49 | G5: ='Revenue Build'!G76 -> 525675.81 | H5: ='Revenue Build'!H76 -> 525846.08 | I5: ='Revenue Build'!I76 -> 526021.46 | ... K5: ='Revenue Build'!K76 -> 526388.17
A6: Corporate | B6: ='Revenue Build'!B77 -> 187500 | C6: ='Revenue Build'!C77 -> 546000 | D6: ='Revenue Build'!D77 -> 910000 | E6: ='Revenue Build'!E77 -> 1365000 | F6: ='Revenue Build'!F77 -> 2047500 | G6: ='Revenue Build'!G77 -> 2366000 | H6: ='Revenue Build'!H77 -> 2639000 | I6: ='Revenue Build'!I77 -> 2957500 | ... K6: ='Revenue Build'!K77 -> 3640000
A8: Margin Progression (%)
A9: Metric | B9: Year 1 | C9: Year 2 | D9: Year 3 | E9: Year 4 | F9: Year 5 | G9: Year 6 | H9: Year 7 | I9: Year 8 | J9: Year 9 | K9: Year 10
A10: Gross Margin % | B10: ='Margin Analysis'!B44 -> 0.49649978 | C10: ='Margin Analysis'!C44 -> 0.51695192 | D10: ='Margin Analysis'!D44 -> 0.531404 | E10: ='Margin Analysis'!E44 -> 0.53951524 | F10: ='Margin Analysis'!F44 -> 0.54815337 | G10: ='Margin Analysis'!G44 -> 0.5517093 | H10: ='Margin Analysis'!H44 -> 0.55609958 | I10: ='Margin Analysis'!I44 -> 0.56032548 | ... K10: ='Margin Analysis'!K44 -> 0.57362193
A11: EBITDA Margin % | B11: ='Margin Analysis'!B48 -> -1.2237445 | C11: ='Margin Analysis'!C48 -> -0.54028033 | D11: ='Margin Analysis'!D48 -> -0.10622888 | E11: ='Margin Analysis'!E48 -> -0.001949991 | F11: ='Margin Analysis'!F48 -> 0.15787292 | G11: ='Margin Analysis'!G48 -> 0.19485735 | H11: ='Margin Analysis'!H48 -> 0.18358969 | I11: ='Margin Analysis'!I48 -> 0.21371601 | ... K11: ='Margin Analysis'!K48 -> 0.2318117
A12: FCF Margin % | B12: ='Margin Analysis'!B60 -> -1.3537445 | C12: ='Margin Analysis'!C60 -> -0.63147322 | D12: ='Margin Analysis'!D60 -> -0.1896317 | E12: ='Margin Analysis'!E60 -> -0.074399336 | F12: ='Margin Analysis'!F60 -> 0.051621952 | G12: ='Margin Analysis'!G60 -> 0.094317832 | H12: ='Margin Analysis'!H60 -> 0.087165961 | I12: ='Margin Analysis'!I60 -> 0.10973649 | ... K12: ='Margin Analysis'!K60 -> 0.12382151
A14: P&L Bridge
A15: Metric | B15: Year 1 | C15: Year 2 | D15: Year 3 | E15: Year 4 | F15: Year 5 | G15: Year 6 | H15: Year 7 | I15: Year 8 | J15: Year 9 | K15: Year 10
A16: Revenue | B16: ='Revenue Build'!B78 -> 584800.65 | C16: ='Revenue Build'!C78 -> 1205553.5 | D16: ='Revenue Build'!D78 -> 2069745 | E16: ='Revenue Build'!E78 -> 2877110.7 | F16: ='Revenue Build'!F78 -> 4131015.4 | G16: ='Revenue Build'!G78 -> 4676081.5 | H16: ='Revenue Build'!H78 -> 5197545.4 | I16: ='Revenue Build'!I78 -> 5779105.2 | ... K16: ='Revenue Build'!K78 -> 6941838.6
A17: EBITDA | B17: ='Margin Analysis'!B47 -> -715646.6 | C17: ='Margin Analysis'!C47 -> -651336.82 | D17: ='Margin Analysis'!D47 -> -219866.69 | E17: ='Margin Analysis'!E47 -> -5610.34 | F17: ='Margin Analysis'!F47 -> 652175.49 | G17: ='Margin Analysis'!G47 -> 911168.83 | H17: ='Margin Analysis'!H47 -> 954215.76 | I17: ='Margin Analysis'!I47 -> 1235087.3 | ... K17: ='Margin Analysis'!K47 -> 1609199.4
A18: Free Cash Flow | B18: ='Margin Analysis'!B59 -> -791670.69 | C18: ='Margin Analysis'!C59 -> -761274.72 | D18: ='Margin Analysis'!D59 -> -392489.27 | E18: ='Margin Analysis'!E59 -> -214055.12 | F18: ='Margin Analysis'!F59 -> 213251.08 | G18: ='Margin Analysis'!G59 -> 441037.87 | H18: ='Margin Analysis'!H59 -> 453049.04 | I18: ='Margin Analysis'!I59 -> 634178.73 | ... K18: ='Margin Analysis'!K59 -> 859548.95
A20: Revenue Mix — Year 5 | D20: Revenue Mix — Year 10 | G20: SOTP Segment | H20: Value
A21: Segment | B21: Revenue | D21: Segment | E21: Revenue | G21: Platform | H21: ='DCF Valuation'!E57 -> 9299281.6
A22: Platform | B22: ='Revenue Build'!F74 -> 1352494.4 | D22: Platform | E22: ='Revenue Build'!K74 -> 2066507 | G22: Creator | H22: ='DCF Valuation'!E58 -> 1417886.9
A23: Creator | B23: ='Revenue Build'!F75 -> 205510.49 | D23: Creator | E23: ='Revenue Build'!K75 -> 708943.44 | G23: Venue | H23: ='DCF Valuation'!E59 -> 631665.8
A24: Venue | B24: ='Revenue Build'!F76 -> 525510.49 | D24: Venue | E24: ='Revenue Build'!K76 -> 526388.17 | G24: Corporate | H24: ='DCF Valuation'!E60 -> 7280000
A25: Corporate | B25: ='Revenue Build'!F77 -> 2047500 | D25: Corporate | E25: ='Revenue Build'!K77 -> 3640000
A27: Fixed vs Variable Cost
A28: Cost Type | B28: Year 1 | C28: Year 2 | D28: Year 3 | E28: Year 4 | F28: Year 5 | G28: Year 6 | H28: Year 7 | I28: Year 8 | J28: Year 9 | K28: Year 10
A29: Fixed Costs | B29: ='Cost Build'!B53 -> 906700 | C29: ='Cost Build'!C53 -> 1170285 | D29: ='Cost Build'!D53 -> 1210259.2 | E29: ='Cost Build'!E53 -> 1442903.2 | F29: ='Cost Build'!F53 -> 1491554.8 | G29: ='Cost Build'!G53 -> 1541934.1 | H29: ='Cost Build'!H53 -> 1803065.5 | I29: ='Cost Build'!I53 -> 1863367.5 | ... K29: ='Cost Build'!K53 -> 2218744.5
A30: Variable Costs | B30: ='Cost Build'!B54 -> 393747.25 | C30: ='Cost Build'!C54 -> 686605.28 | D30: ='Cost Build'!D54 -> 1079352.5 | E30: ='Cost Build'!E54 -> 1439817.8 | F30: ='Cost Build'!F54 -> 1987285.2 | G30: ='Cost Build'!G54 -> 2222978.6 | H30: ='Cost Build'!H54 -> 2440264.1 | I30: ='Cost Build'!I54 -> 2680650.4 | ... K30: ='Cost Build'!K54 -> 3113894.6
A32: Operating Leverage
A33: Metric | B33: Year 1 | C33: Year 2 | D33: Year 3 | E33: Year 4 | F33: Year 5 | G33: Year 6 | H33: Year 7 | I33: Year 8 | J33: Year 9 | K33: Year 10
A34: Revenue | B34: ='Revenue Build'!B78 -> 584800.65 | C34: ='Revenue Build'!C78 -> 1205553.5 | D34: ='Revenue Build'!D78 -> 2069745 | E34: ='Revenue Build'!E78 -> 2877110.7 | F34: ='Revenue Build'!F78 -> 4131015.4 | G34: ='Revenue Build'!G78 -> 4676081.5 | H34: ='Revenue Build'!H78 -> 5197545.4 | I34: ='Revenue Build'!I78 -> 5779105.2 | ... K34: ='Revenue Build'!K78 -> 6941838.6
A35: Fixed Costs | B35: ='Cost Build'!B53 -> 906700 | C35: ='Cost Build'!C53 -> 1170285 | D35: ='Cost Build'!D53 -> 1210259.2 | E35: ='Cost Build'!E53 -> 1442903.2 | F35: ='Cost Build'!F53 -> 1491554.8 | G35: ='Cost Build'!G53 -> 1541934.1 | H35: ='Cost Build'!H53 -> 1803065.5 | I35: ='Cost Build'!I53 -> 1863367.5 | ... K35: ='Cost Build'!K53 -> 2218744.5
A36: Op Leverage (Rev/Fixed) | B36: ='Cost Build'!B56 -> 0.644977 | C36: ='Cost Build'!C56 -> 1.0301366 | D36: ='Cost Build'!D56 -> 1.7101667 | E36: ='Cost Build'!E56 -> 1.9939734 | F36: ='Cost Build'!F56 -> 2.7696036 | G36: ='Cost Build'!G56 -> 3.032608 | H36: ='Cost Build'!H56 -> 2.8826159 | I36: ='Cost Build'!I56 -> 3.1014307 | ... K36: ='Cost Build'!K56 -> 3.1287237
A38: Scenario Comparison
A39: Metric | B39: Base | C39: Upside | D39: Downside | E39: Stress
A40: Revenue | B40: ='Scenario Analysis'!B21 -> 4131015.4 | C40: ='Scenario Analysis'!C21 -> 5783421.6 | D40: ='Scenario Analysis'!D21 -> 2478609.3 | E40: ='Scenario Analysis'!E21 -> 1445855.4
A41: EBITDA | B41: ='Scenario Analysis'!B28 -> 652175.49 | C41: ='Scenario Analysis'!C28 -> 1619358 | D41: ='Scenario Analysis'!D28 -> 123930.46 | E41: ='Scenario Analysis'!E28 -> -144585.54
A42: FCF | B42: ='Scenario Analysis'!B30 -> 213251.08 | C42: ='Scenario Analysis'!C30 -> 1052582.7 | D42: ='Scenario Analysis'!D30 -> 37179.139 | E42: ='Scenario Analysis'!E30 -> -72292.77
A43: Implied EV | B43: ='Scenario Analysis'!B35 -> 7826105.8 | C43: ='Scenario Analysis'!C35 -> 22671013 | D43: ='Scenario Analysis'!D35 -> 991443.7 | E43: ='Scenario Analysis'!E35 -> 0
A45: LTV/CAC by Channel — Year 5
A46: Channel | B46: LTV/CAC | C46: Payback (mo)
A47: Platform Organic | B47: ='Unit Economics'!F14 -> 10.723359 | C47: ='Unit Economics'!F15 -> 3.7301743
A48: Corporate B2B | B48: ='Unit Economics'!F43 -> 91 | C48: 6
A50: Segment Gross Margins (%)
A51: Segment | B51: Year 1 | C51: Year 2 | D51: Year 3 | E51: Year 4 | F51: Year 5 | G51: Year 6 | H51: Year 7 | I51: Year 8 | J51: Year 9 | K51: Year 10
A52: Platform GM% | B52: ='Margin Analysis'!B8 -> 0.77602108 | C52: ='Margin Analysis'!C8 -> 0.77882198 | D52: ='Margin Analysis'!D8 -> 0.78138569 | E52: ='Margin Analysis'!E8 -> 0.78373356 | F52: ='Margin Analysis'!F8 -> 0.78588445 | G52: ='Margin Analysis'!G8 -> 0.78630237 | H52: ='Margin Analysis'!H8 -> 0.78717951 | I52: ='Margin Analysis'!I8 -> 0.78749586 | ... K52: ='Margin Analysis'!K8 -> 0.78755892
A53: Creator GM% | B53: ='Margin Analysis'!B17 -> -97.039216 | C53: ='Margin Analysis'!C17 -> -94.183705 | D53: ='Margin Analysis'!D17 -> -3.5629907 | E53: ='Margin Analysis'!E17 -> -2.0897974 | F53: ='Margin Analysis'!F17 -> -1.3356472 | G53: ='Margin Analysis'!G17 -> -0.87737748 | H53: ='Margin Analysis'!H17 -> -0.56941688 | I53: ='Margin Analysis'!I17 -> -0.34823332 | ... K53: ='Margin Analysis'!K17 -> 0.052110557
A54: Venue GM% | B54: ='Margin Analysis'!B26 -> 0.77138328 | C54: ='Margin Analysis'!C26 -> 0.77144724 | D54: ='Margin Analysis'!D26 -> 0.77151308 | E54: ='Margin Analysis'!E26 -> 0.77158085 | F54: ='Margin Analysis'!F26 -> 0.77165061 | G54: ='Margin Analysis'!G26 -> 0.77172242 | H54: ='Margin Analysis'!H26 -> 0.77179634 | I54: ='Margin Analysis'!I26 -> 0.77187243 | ... K54: ='Margin Analysis'!K26 -> 0.77203135
A55: Corporate GM% | B55: ='Margin Analysis'!B35 -> 0.48066667 | C55: ='Margin Analysis'!C35 -> 0.56318681 | D55: ='Margin Analysis'!D35 -> 0.56318681 | E55: ='Margin Analysis'!E35 -> 0.56318681 | F55: ='Margin Analysis'!F35 -> 0.56318681 | G55: ='Margin Analysis'!G35 -> 0.56318681 | H55: ='Margin Analysis'!H35 -> 0.56318681 | I55: ='Margin Analysis'!I35 -> 0.56318681 | ... K55: ='Margin Analysis'!K35 -> 0.56318681
A56: Blended GM% | B56: ='Margin Analysis'!B44 -> 0.49649978 | C56: ='Margin Analysis'!C44 -> 0.51695192 | D56: ='Margin Analysis'!D44 -> 0.531404 | E56: ='Margin Analysis'!E44 -> 0.53951524 | F56: ='Margin Analysis'!F44 -> 0.54815337 | G56: ='Margin Analysis'!G44 -> 0.5517093 | H56: ='Margin Analysis'!H44 -> 0.55609958 | I56: ='Margin Analysis'!I44 -> 0.56032548 | ... K56: ='Margin Analysis'!K44 -> 0.57362193
A58: Operational Scale KPIs
A59: KPI | B59: Year 1 | C59: Year 2 | D59: Year 3 | E59: Year 4 | F59: Year 5 | G59: Year 6 | H59: Year 7 | I59: Year 8 | J59: Year 9 | K59: Year 10
A60: Active Pros | B60: ='Revenue Build'!B9 -> 66.15 | C60: ='Revenue Build'!C9 -> 110.25 | D60: ='Revenue Build'!D9 -> 176.4 | E60: ='Revenue Build'!E9 -> 220.5 | F60: ='Revenue Build'!F9 -> 286.65 | G60: ='Revenue Build'!G9 -> 308.7 | H60: ='Revenue Build'!H9 -> 330.75 | I60: ='Revenue Build'!I9 -> 352.8 | ... K60: ='Revenue Build'!K9 -> 374.85
